Workbook

Sheet IA(정보구조)
A1: Depth 1 | B1: Depth 2 | C1: Depth 3 | D1: 화면 ID | E1: 화면명 | F1: 플랫폼 | G1: 화면 URL/경로 | H1: 로그인 필요 | I1: 권한 | J1: 설명 | K1: 상태 | L1: 비고
A2: 인증 | B2: 로그인 | D2: SCR-001 | E2: 로그인 | F2: Web | G2: /login | H2: N | I2: 비회원 | J2: 이메일/비밀번호 로그인 화면. 지점 선택 포함 | K2: 개발완료 | L2: 로그인 유지 체크박스, toast 안내, 에러 자동 클리어 (2026-03-13)
A3: 대시보드 | B3: 메인 | D3: SCR-002 | E3: 대시보드 | F3: Web | G3: / | H3: Y | I3: 전체 | J3: 지점별 핵심 KPI 요약 대시보드 | K3: 개발완료 | L3: 실데이터 차트, soft delete 필터, 클릭 네비게이션 (2026-03-13)
A4: 회원관리 | B4: 회원 | D4: SCR-010 | E4: 회원 목록 | F4: Web | G4: /members | H4: Y | I4: 매니저 이상 | J4: 회원 검색/필터/목록 조회 | K4: 개발완료 | L4: 상태 변경 모달 개선, 서버사이드 페이지네이션/정렬 (2026-03-13)
A5: 회원관리 | B5: 회원 | D5: SCR-011 | E5: 회원 상세 | F5: Web | G5: /members/detail | H5: Y | I5: 매니저 이상 | J5: 회원 프로필, 이용권, 출석, 결제, 체성분, 메모 탭 | K5: 개발완료 | L5: Supabase 실데이터, 메모/목표 탭 (2026-03-13)
A6: 회원관리 | B6: 회원 | D6: SCR-012 | E6: 회원 등록 | F6: Web | G6: /members/new | H6: Y | I6: 매니저 이상 | J6: 신규 회원 등록 폼 | K6: 개발완료
A7: 회원관리 | B7: 회원 | D7: SCR-013 | E7: 회원 수정 | F7: Web | G7: /members/edit | H7: Y | I7: 매니저 이상 | J7: 기존 회원 정보 수정 폼 | K7: 개발완료
A8: 회원관리 | B8: 체성분 | D8: SCR-014 | E8: 체성분 분석 | F8: Web | G8: /body-composition | H8: Y | I8: FC 이상 | J8: 체성분 측정 기록 및 변화 추이 차트 | K8: 개발완료
A9: 출석/일정 | B9: 출석 | D9: SCR-020 | E9: 출석 기록 | F9: Web | G9: /attendance | H9: Y | I9: 스태프 이상 | J9: 회원 출석 현황 조회 (일별/주별/월별) | K9: 개발완료 | L9: 날짜 필터 DataTable 연동, 키보드 접근성 개선 (2026-03-13)
A10: 출석/일정 | B10: 일정 | D10: SCR-021 | E10: 일정 관리 | F10: Web | G10: /calendar | H10: Y | I10: 스태프 이상 | J10: PT/GX 일정 캘린더 뷰 | K10: 개발완료 | L10: FullCalendar 드래그앤드롭 리뉴얼 (2026-03-13)
A11: 매출/결제 | B11: 매출 | D11: SCR-030 | E11: 매출 조회 | F11: Web | G11: /sales | H11: Y | I11: 매니저 이상 | J11: 매출 현황 조회, 필터, 통계 요약 | K11: 개발완료
A12: 매출/결제 | B12: POS | D12: SCR-031 | E12: POS | F12: Web | G12: /pos | H12: Y | I12: 스태프 이상 | J12: POS 상품 선택 및 장바구니 | K12: 개발완료
A13: 매출/결제 | B13: POS | D13: SCR-032 | E13: POS 결제 | F13: Web | G13: /pos/payment | H13: Y | I13: 스태프 이상 | J13: 결제 수단 선택 및 결제 처리 | K13: 개발완료 | L13: window.confirm → ConfirmDialog 개선 (2026-03-13)
A14: 상품관리 | B14: 상품 | D14: SCR-040 | E14: 상품 목록 | F14: Web | G14: /products | H14: Y | I14: 매니저 이상 | J14: 이용권/PT/기타 상품 목록 | K14: 개발완료
A15: 상품관리 | B15: 상품 | D15: SCR-041 | E15: 상품 등록 | F15: Web | G15: /products/new | H15: Y | I15: 센터장 이상 | J15: 신규 상품 등록 폼 | K15: 개발완료
A16: 시설관리 | B16: 락커 | D16: SCR-050 | E16: 락커 현황 | F16: Web | G16: /locker | H16: Y | I16: 스태프 이상 | J16: 락커 구역별 배정 현황 (색상 그리드) | K16: 개발완료
A17: 시설관리 | B17: 락커 | D17: SCR-051 | E17: 락커 관리 | F17: Web | G17: /locker/management | H17: Y | I17: 매니저 이상 | J17: 락커 배정/해제/일괄 관리 | K17: 개발완료
A18: 시설관리 | B18: RFID | D18: SCR-052 | E18: RFID 관리 | F18: Web | G18: /rfid | H18: Y | I18: 매니저 이상 | J18: RFID 카드 등록/해제/이력 조회 | K18: 개발완료
A19: 시설관리 | B19: 룸 | D19: SCR-053 | E19: 룸 관리 | F19: Web | G19: /rooms | H19: Y | I19: 매니저 이상 | J19: GX룸/PT룸 관리 및 예약 설정 | K19: 개발완료
A20: 직원관리 | B20: 직원 | D20: SCR-060 | E20: 직원 목록 | F20: Web | G20: /staff | H20: Y | I20: 센터장 이상 | J20: 직원 검색/필터/목록 조회 | K20: 개발완료 | L20: 페이지네이션 동작 수정, 퇴사 ConfirmDialog (2026-03-13)
A21: 직원관리 | B21: 직원 | D21: SCR-061 | E21: 직원 등록 | F21: Web | G21: /staff/new | H21: Y | I21: 센터장 이상 | J21: 신규 직원 등록 폼 | K21: 개발완료
A22: 직원관리 | B22: 급여 | D22: SCR-062 | E22: 급여 현황 | F22: Web | G22: /payroll | H22: Y | I22: 센터장 이상 | J22: 월별 급여 현황 요약 | K22: 개발완료 | L22: 페이지네이션 동작 수정, 필터 시 페이지 리셋 (2026-03-13)
A23: 직원관리 | B23: 급여 | D23: SCR-063 | E23: 급여명세서 | F23: Web | G23: /payroll/statements | H23: Y | I23: 센터장 이상 | J23: 직원별 급여명세서 상세 | K23: 개발완료
A24: 메시지/마케팅 | B24: 메시지 | D24: SCR-070 | E24: 메시지 발송 | F24: Web | G24: /message | H24: Y | I24: 매니저 이상 | J24: SMS/카카오톡 메시지 발송 | K24: 개발완료
A25: 메시지/마케팅 | B25: 자동알림 | D25: SCR-071 | E25: 자동 알림 | F25: Web | G25: /message/auto-alarm | H25: Y | I25: 매니저 이상 | J25: 자동 알림 규칙 설정 (만료/생일 등) | K25: 개발완료
A26: 메시지/마케팅 | B26: 쿠폰 | D26: SCR-072 | E26: 쿠폰 관리 | F26: Web | G26: /message/coupon | H26: Y | I26: 매니저 이상 | J26: 쿠폰 생성/발급/이력 관리 | K26: 개발완료
A27: 메시지/마케팅 | B27: 마일리지 | D27: SCR-073 | E27: 마일리지 관리 | F27: Web | G27: /mileage | H27: Y | I27: 매니저 이상 | J27: 회원 마일리지 적립/사용 이력 | K27: 개발완료 | L27: 이력 탭 엑셀 다운로드 구현 (2026-03-13)
A28: 계약/구독 | B28: 계약 | D28: SCR-080 | E28: 계약 마법사 | F28: Web | G28: /contracts/new | H28: Y | I28: 매니저 이상 | J28: 단계별 계약 등록 위자드 | K28: 개발완료 | L28: 전자서명 (양방향) Canvas 구현 (2026-03-13)
A29: 계약/구독 | B29: 구독 | D29: SCR-081 | E29: 구독 관리 | F29: Web | G29: /subscription | H29: Y | I29: 센터장 이상 | J29: 정기 구독 상품 관리 | K29: 개발완료
A30: 설정 | B30: 설정 | D30: SCR-090 | E30: 설정 | F30: Web | G30: /settings | H30: Y | I30: 센터장 이상 | J30: 시스템 기본 설정 | K30: 개발완료
A31: 설정 | B31: 권한 | D31: SCR-091 | E31: 권한 설정 | F31: Web | G31: /settings/permissions | H31: Y | I31: 최고관리자 | J31: 역할별 메뉴/기능 권한 매트릭스 | K31: 개발완료
A32: 설정 | B32: 키오스크 | D32: SCR-092 | E32: 키오스크 설정 | F32: Web | G32: /settings/kiosk | H32: Y | I32: 센터장 이상 | J32: 키오스크 디스플레이/동작 설정 | K32: 개발완료
A33: 설정 | B33: IoT | D33: SCR-093 | E33: IoT 설정 | F33: Web | G33: /settings/iot | H33: Y | I33: 센터장 이상 | J33: 출입문/체성분 기기 연동 설정 | K33: 개발완료
A34: 설정 | B34: 지점 | D34: SCR-094 | E34: 지점 관리 | F34: Web | G34: /branches | H34: Y | I34: 최고관리자 | J34: 지점 CRUD 및 멀티테넌트 관리 | K34: 개발완료
A35: 출석/일정 | B35: GX 예약 | D35: SCR-022 | E35: GX 예약 관리 | F35: Web | G35: /schedule/gx-booking | H35: Y | I35: 매니저 이상 | J35: GX 프로그램 예약 오픈/관리. N시간 전 자동 오픈, 노쇼 페널티, 출석체크 연동 | K35: 신규 | L35: 레슨북/온핏 장점 반영
A36: 출석/일정 | B36: 좌석 예약 | D36: SCR-023 | E36: 좌석 예약 관리 | F36: Web | G36: /schedule/seat-booking | H36: Y | I36: 매니저 이상 | J36: 스피닝/GX 좌석 지정 예약. 바이크 번호별 예약/고장 관리 | K36: 신규 | L36: 판교점/용산점 요구사항
A37: 출석/일정 | B37: 레슨 관리 | D37: SCR-024 | E37: 레슨 기록/서명 | F37: Web | G37: /schedule/lesson | H37: Y | I37: 트레이너 이상 | J37: PT/골프 레슨 기록, 고객 서명 확인, 수업 진위 관리 | K37: 신규 | L37: 레슨북 장점 반영
A38: 시설관리 | B38: 타석 | D38: SCR-054 | E38: 골프 타석 관리 | F38: Web | G38: /facility/golf-bay | H38: Y | I38: 매니저 이상 | J38: 골프 타석 예약/대기/제어. 꼬리물기 예약, 시간관리 | K38: 신규 | L38: 대치점 브로제이 장점 반영
A39: 시설관리 | B39: 전원제어 | D39: SCR-055 | E39: 기기 전원 제어 | F39: Web | G39: /facility/power-control | H39: Y | I39: 매니저 이상 | J39: 키오스크/프로젝터 원격 전원 ON/OFF, 스케줄 자동 제어 | K39: 신규 | L39: 고척점/대치점 핵심 요구사항
A40: 시설관리 | B40: 수건/운동복 | D40: SCR-056 | E40: 수건/운동복 관리 | F40: Web | G40: /facility/towel | H40: Y | I40: 스태프 이상 | J40: 수건/운동복 발급 관리. QR/안면인식 연동, 수량 제한, 사용량 통계 | K40: 신규 | L40: 양천향교점 벤치마크
A41: 회원관리 | B41: FC 알림 | D41: SCR-015 | E41: FC 즐겨찾기/알림 | F41: Web | G41: /members/fc-alert | H41: Y | I41: FC 이상 | J41: 담당 FC별 즐겨찾기 회원 등록, 방문 시 실시간 알림, 임박회원 자동 알림 | K41: 신규 | L41: 대치점 온핏 핵심 기능
A42: 설정 | B42: 키오스크 타입 | D42: SCR-095 | E42: 키오스크 타입 설정 | F42: Web | G42: /settings/kiosk-type | H42: Y | I42: 센터장 이상 | J42: 키오스크 타입(결제형/비결제형) 지점별 설정. UI 화면 구성 분기 | K42: 신규 | L42: 판교점 인터뷰 반영
A43: 설정 | B43: 오프라인 | D43: SCR-096 | E43: 오프라인 모드 설정 | F43: Web | G43: /settings/offline | H43: Y | I43: 센터장 이상 | J43: 네트워크 장애 시 로컬 모드 동작 설정. 자동 동기화 정책 | K43: 신규 | L43: 전 지점 공통 요구사항
A44: 매출/결제 | B44: 통합 내보내기 | D44: SCR-033 | E44: 데이터 통합 내보내기 | F44: Web | G44: /sales/export | H44: Y | I44: 매니저 이상 | J44: 모든 데이터 원장 엑셀 내보내기. 권한별 컬럼 필터, 전체 필드 포함 | K44: 신규 | L44: 고척점 레슨북 장점 반영
A45: 키오스크 | B45: 입장 | D45: SCR-K01 | E45: 키오스크 입장 | F45: Kiosk | G45: /kiosk/entry | H45: N | I45: 비회원 | J45: 회원 입장 화면. 얼굴인식/전화번호/NFC 밴드 입장. 지점별 타입(A/B) 분기 | K45: 신규 | L45: 대치점 브로제이 벤치마크
A46: 키오스크 | B46: 퇴장 | D46: SCR-K02 | E46: 키오스크 퇴장 | F46: Kiosk | G46: /kiosk/exit | H46: N | I46: 비회원 | J46: 회원 퇴장 처리. 라커 자동 해제, 이용시간 기록 | K46: 신규 | L46: 판교점 온핏
... A51: 키오스크 | B51: 골프 입장 | D51: SCR-K07 | E51: 키오스크 골프 타석 입장 | F51: Kiosk | G51: /kiosk/golf-entry | H51: N | I51: 회원 | J51: 예약한 골프 타석 입장. 전화번호 인증 → 스크린 잠금 해제 → 이용 시작 | K51: 신규 | L51: 대치점 브로제이
A52: 회원앱 | B52: 홈 | D52: SCR-M01 | E52: 앱 홈 | F52: App | G52: /app/home | H52: Y | I52: 회원 | J52: 회원 앱 메인. 이용권 잔여일, 출석 현황, 예약 내역, 공지사항 | K52: 신규
A53: 회원앱 | B53: 입장/퇴장 | D53: SCR-M02 | E53: 앱 QR 입장 | F53: App | G53: /app/checkin | H53: Y | I53: 회원 | J53: QR코드/NFC 기반 센터 입장. 라커 번호 표시, 입장 시간 기록 | K53: 신규
A54: 회원앱 | B54: GX 예약 | D54: SCR-M03 | E54: 앱 GX 예약 | F54: App | G54: /app/gx-booking | H54: Y | I54: 회원 | J54: GX 프로그램 예약/취소. 주간 시간표, 잔여석, 좌석 선택(스피닝 배치도) | K54: 신규 | L54: 판교점 온핏 앱
A55: 회원앱 | B55: 골프 예약 | D55: SCR-M04 | E55: 앱 골프 타석 예약 | F55: App | G55: /app/golf-booking | H55: Y | I55: 회원 | J55: 골프 타석 원격 예약/대기. 실시간 타석 현황, 잔여시간(시:분), 푸시 알림 | K55: 신규 | L55: 고척점 레슨북
A56: 회원앱 | B56: 레슨 예약 | D56: SCR-M05 | E56: 앱 레슨 예약/서명 | F56: App | G56: /app/lesson | H56: Y | I56: 회원 | J56: PT/골프 레슨 예약, 수업 후 서명 확인, 레슨 기록 열람, 잔여 횟수 확인 | K56: 신규 | L56: 고척점 레슨북
A57: 회원앱 | B57: 내 정보 | D57: SCR-M06 | E57: 앱 내 정보 | F57: App | G57: /app/profile | H57: Y | I57: 회원 | J57: 이용권 현황, 결제 내역, 출석 이력, 체성분 변화 추이, 포인트/쿠폰 | K57: 신규
A58: 회원앱 | B58: 알림 | D58: SCR-M07 | E58: 앱 알림 센터 | F58: App | G58: /app/notifications | H58: Y | I58: 회원 | J58: 예약 리마인드, 이용권 만료 안내, 프로모션, GX 오픈 알림 | K58: 신규
A59: 트레이너앱 | B59: 홈 | D59: SCR-T01 | E59: 트레이너 앱 홈 | F59: App | G59: /trainer/home | H59: Y | I59: 트레이너 | J59: 오늘의 수업 목록, 예약 현황, 미완료 레슨 기록 알림 | K59: 신규 | L59: 고척점 레슨북
A60: 트레이너앱 | B60: 스케줄 | D60: SCR-T02 | E60: 트레이너 스케줄 | F60: App | G60: /trainer/schedule | H60: Y | I60: 트레이너 | J60: 주간/월간 수업 캘린더. 수업 상세, 회원 정보, 예약/취소/노쇼 표시 | K60: 신규 | L60: 고척점 레슨북
A61: 트레이너앱 | B61: 레슨 기록 | D61: SCR-T03 | E61: 트레이너 레슨 기록 | F61: App | G61: /trainer/lesson-record | H61: Y | I61: 트레이너 | J61: 수업 내용 작성(텍스트/템플릿), 고객 터치 서명, 사진 첨부, 수업 완료 처리 | K61: 신규 | L61: 고척점 레슨북
A62: 트레이너앱 | B62: 회원 관리 | D62: SCR-T04 | E62: 트레이너 담당 회원 | F62: App | G62: /trainer/members | H62: Y | I62: 트레이너 | J62: 담당 회원 목록, 잔여 횟수, 레슨 이력, 다음 예약, 메모 | K62: 신규 | L62: 고척점 레슨북
A63: FC앱 | B63: 홈 | D63: SCR-F01 | E63: FC 앱 홈 | F63: App | G63: /fc/home | H63: Y | I63: FC | J63: 오늘 방문 알림, 임박 회원 목록, 개인 매출 현황, 상담 일정 | K63: 신규 | L63: 대치점 온핏
A64: FC앱 | B64: 즐겨찾기 | D64: SCR-F02 | E64: FC 즐겨찾기 알림 | F64: App | G64: /fc/favorites | H64: Y | I64: FC | J64: 즐겨찾기 회원 관리, 방문 실시간 푸시 알림, 잔여일/미납 표시, 상담 메모 | K64: 신규 | L64: 대치점 온핏 핵심
A65: FC앱 | B65: 회원 상담 | D65: SCR-F03 | E65: FC 회원 상담 기록 | F65: App | G65: /fc/consultation | H65: Y | I65: FC | J65: 상담 내용 기록, 재등록 상담 이력, 실적 귀속 확인, 프로모션 안내 | K65: 신규 | L65: 서교점 인터뷰
A66: FC앱 | B66: 매출 | D66: SCR-F04 | E66: FC 개인 매출 | F66: App | G66: /fc/sales | H66: Y | I66: FC | J66: 개인 매출/팀 매출 현황, 실적 담당 건 목록, 월별 추이, 목표 달성률 | K66: 신규 | L66: 서교점 인터뷰

Sheet 사용자 스토리
A1: 스토리 ID | B1: 에픽 | C1: 사용자 유형 | D1: 사용자 스토리 | E1: 인수 조건 | F1: 화면 ID | G1: 우선순위 | H1: 사이즈 | I1: 담당자 | J1: 상태 | K1: [자동] 화면명 | L1: [자동] 기능 수 | M1: 비고
A2: US-001 | B2: 인증 | C2: 비회원 | D2: 비회원으로서 이메일/비밀번호로 로그인하여 시스템에 접근하고 싶다 | E2: 1) 올바른 이메일/비밀번호 입력 시 대시보드로 이동 2) 5회 실패 시 계정 잠금 3) 지점 선택 후 해당 지점 데이터만 표시 | F2: SCR-001 | G2: Critical | H2: S | I2: 개발자1 | J2: Done | K2: 로그인 | L2: 1
A3: US-002 | B3: 대시보드 | C3: 센터장 | D3: 센터장으로서 대시보드에서 지점 핵심 KPI를 한눈에 파악하고 싶다 | E3: 1) 총회원/활성/만료임박/만료 회원 수 카드 표시 2) 오늘 생일 회원 리스트 3) 미납 회원 리스트 4) 당월 매출 차트 | F3: SCR-002 | G3: Critical | H3: M | I3: 개발자1 | J3: Done | K3: 대시보드 | L3: 1
A4: US-003 | B4: 회원관리 | C4: 매니저 | D4: 매니저로서 회원을 검색/필터하여 원하는 회원을 빠르게 찾고 싶다 | E4: 1) 이름/연락처/회원번호로 검색 2) 상태/성별/담당자 필터 3) 엑셀 다운로드 가능 | F4: SCR-010 | G4: Critical | H4: M | I4: 개발자1 | J4: Done | K4: 회원 목록 | L4: 2
A5: US-004 | B5: 회원관리 | C5: 매니저 | D5: 매니저로서 신규 회원을 등록하고 싶다 | E5: 1) 필수 항목(이름/연락처/성별) 입력 2) 담당 FC 배정 3) 등록 완료 시 회원 상세로 이동 | F5: SCR-012 | G5: Critical | H5: M | I5: 개발자1 | J5: Done | K5: 회원 등록 | L5: 0
A6: US-005 | B6: 회원관리 | C6: 매니저 | D6: 매니저로서 회원 상세 정보와 이용 이력을 확인하고 싶다 | E6: 1) 프로필/이용권/출석/결제/체성분/메모 탭 구성 2) 이용권 만료일 강조 표시 3) 출석 히트맵 | F6: SCR-011 | G6: High | H6: L | I6: 개발자1 | J6: Done | K6: 회원 상세 | L6: 2
A7: US-006 | B7: 회원관리 | C7: 매니저 | D7: 매니저로서 회원 정보를 수정하고 싶다 | E7: 1) 기존 정보 프리필 2) 변경 이력 자동 기록 3) 담당자 변경 가능 | F7: SCR-013 | G7: High | H7: S | I7: 개발자1 | J7: Done | K7: 회원 수정 | L7: 0
A8: US-007 | B8: 회원관리 | C8: FC | D8: FC로서 회원의 체성분 측정 결과를 기록하고 변화 추이를 분석하고 싶다 | E8: 1) 체중/골격근/체지방률 등 입력 2) 측정일 기준 변화 차트 3) 목표 대비 달성률 표시 | F8: SCR-014 | G8: High | H8: M | I8: 개발자2 | J8: Done | K8: 체성분 분석 | L8: 1
A9: US-008 | B9: 출석관리 | C9: 스태프 | D9: 스태프로서 회원의 출석 현황을 조회하고 싶다 | E9: 1) 일별/주별/월별 출석 조회 2) 출석 유형(일반/PT/GX) 구분 3) 타지점 출석 표시 | F9: SCR-020 | G9: High | H9: M | I9: 개발자2 | J9: Done | K9: 출석 기록 | L9: 1
A10: US-009 | B10: 출석관리 | C10: 스태프 | D10: 스태프로서 PT/GX 일정을 캘린더로 관리하고 싶다 | E10: 1) 월/주/일 캘린더 뷰 2) 드래그앤드롭 일정 변경 3) 트레이너별 필터 | F10: SCR-021 | G10: High | H10: L | I10: 개발자2 | J10: Done | K10: 일정 관리 | L10: 1
A11: US-010 | B11: 매출관리 | C11: 매니저 | D11: 매니저로서 매출 현황을 조회하고 통계를 확인하고 싶다 | E11: 1) 기간별 매출 필터 2) 유형별(이용권/PT/상품) 분류 3) 총매출/현금/카드/마일리지 요약 4) 엑셀 다운로드 | F11: SCR-030 | G11: Critical | H11: L | I11: 개발자1 | J11: Done | K11: 매출 조회 | L11: 2
A12: US-011 | B12: 매출관리 | C12: 스태프 | D12: 스태프로서 POS에서 상품을 선택하고 결제를 처리하고 싶다 | E12: 1) 카테고리별 상품 그리드 2) 장바구니 담기/수량 변경 3) 현금/카드/마일리지 복합결제 4) 영수증 출력 | F12: SCR-031 | G12: Critical | H12: XL | I12: 개발자1 | J12: Done | K12: POS | L12: 0
A13: US-012 | B13: 상품관리 | C13: 매니저 | D13: 매니저로서 상품 목록을 조회하고 관리하고 싶다 | E13: 1) 카테고리별 필터 2) 키오스크 노출 여부 토글 3) 상품 상태(판매중/중지) 관리 | F13: SCR-040 | G13: High | H13: M | I13: 개발자2 | J13: Done | K13: 상품 목록 | L13: 2
... A31: US-030 | B31: 설정/권한 | C31: 최고관리자 | D31: 최고관리자로서 지점을 추가/관리하고 싶다 | E31: 1) 지점 CRUD 2) 지점별 독립 데이터 3) 지점 간 회원 이동 처리 | F31: SCR-094 | G31: Critical | H31: L | I31: 개발자1 | J31: Done | K31: 지점 관리 | L31: 0
A32: US-031 | B32: 출석관리 | C32: 매니저 | D32: 매니저로서 GX 수업 예약을 N시간 전 자동 오픈 설정하여 수작업을 줄이고 싶다 | E32: 1) 수업별 예약 오픈 시간(N시간 전) 설정 가능 2) 일괄 오픈(매주 특정 요일/시간) 설정 가능 3) 강사 변경 시 기간 지정 일괄 변경 가능 4) 예약 오픈 시 회원 앱 알림 발송 | F32: SCR-022 | G32: Critical | H32: L | J32: To Do | K32: GX 예약 관리 | L32: 3
A33: US-032 | B33: 출석관리 | C33: 매니저 | D33: 매니저로서 GX 출석을 QR/NFC로 자동 체크하여 노쇼를 정확히 파악하고 싶다 | E33: 1) QR/NFC 스캔으로 출석 자동 기록 2) 센터 입장 + 프로그램 예약 매칭 자동 출석 3) 노쇼 자동 감지 및 페널티 처리 4) 비예약자 참석 시 FC 알림 | F33: SCR-022 | G33: Critical | H33: L | J33: To Do | K33: GX 예약 관리 | L33: 3
A34: US-033 | B34: 출석관리 | C34: 회원 | D34: 회원으로서 스피닝 수업 예약 시 원하는 바이크 좌석을 선택하고 싶다 | E34: 1) 바이크 배치도에서 원하는 좌석 선택 가능 2) 고장 좌석 비활성화 표시(선택 불가) 3) 예약 순서에 따른 좌석 선택 우선권 | F34: SCR-023 | G34: High | H34: M | J34: To Do | K34: 좌석 예약 관리 | L34: 2
A35: US-034 | B35: 출석관리 | C35: 트레이너 | D35: 트레이너로서 레슨 완료 후 고객 서명을 받아 수업 진위를 증명하고 싶다 | E35: 1) 수업 내용 기록 + 고객 터치 서명 2) 서명 완료 시 수업 확정 3) 모바일에서도 서명 가능 4) 서명 이력 조회 가능 | F35: SCR-024 | G35: High | H35: M | J35: To Do | K35: 레슨 기록/서명 | L35: 2
A36: US-035 | B36: 시설관리 | C36: 센터장 | D36: 센터장으로서 30개 이상의 키오스크/프로젝터를 원격으로 일괄 ON/OFF하여 오픈/마감 시간을 절약하고 싶다 | E36: 1) 관리 PC에서 전체/개별 전원 ON/OFF 2) 오픈/마감 스케줄 자동 제어 설정 3) 기기 상태 실시간 모니터링 4) 미응답 기기 알림 | F36: SCR-055 | G36: Critical | H36: L | J36: To Do | K36: 기기 전원 제어 | L36: 1
A37: US-036 | B37: 시설관리 | C37: 매니저 | D37: 매니저로서 수건/운동복 발급을 자동화하여 과다 사용을 줄이고 세탁비를 관리하고 싶다 | E37: 1) 회원별 1일 발급 수량 제한 2) QR/안면인식 발급 기록 자동화 3) 월간 사용량 통계 + 세탁비 추정 4) 과다 발급 알림 | F37: SCR-056 | G37: High | H37: M | J37: To Do | K37: 수건/운동복 관리 | L37: 1
A38: US-037 | B38: 회원관리 | C38: FC | D38: FC로서 담당 회원이 센터에 방문하면 즉시 알림을 받아 재등록 상담 타이밍을 놓치지 않고 싶다 | E38: 1) 즐겨찾기 회원 입장 시 핸드폰 푸시 알림 2) 알림에 잔여일수/미납 여부 표시 3) 이용권 만료 임박 회원 자동 즐겨찾기 4) 방문 이력 기반 상담 포인트 제공 | F38: SCR-015 | G38: Critical | H38: M | J38: Done | K38: FC 즐겨찾기/알림 | L38: 1
A39: US-038 | B39: 상품관리 | C39: 매니저 | D39: 매니저로서 상품을 한 화면에서 요일별/시간별/횟수별/기간별 세팅을 완료하고 싶다 | E39: 1) 팝업 없이 한 화면에서 전체 속성 설정 2) 주중권/주말권 분기 설정 3) 횟수제/기간제/혼합 선택 4) 상품 클릭 시 구매 회원 바로 확인 | F39: SCR-041 | G39: Critical | H39: L | J39: To Do | K39: 상품 등록 | L39: 2
A40: US-039 | B40: 설정 | C40: 센터장 | D40: 센터장으로서 키오스크 타입(결제형/비결제형)을 지점별로 설정하고 싶다 | E40: 1) 타입A(입퇴장 전용)/타입B(결제 포함) 선택 2) 선택에 따라 키오스크 UI 자동 분기 3) 타입B 시 1일권 현장 결제 가능 | F40: SCR-095 | G40: High | H40: M | J40: Done | K40: 키오스크 타입 설정 | L40: 1
A41: US-040 | B41: 설정 | C41: 센터장 | D41: 센터장으로서 네트워크 장애 시에도 출입/라커 기본 기능이 동작하여 영업 중단을 방지하고 싶다 | E41: 1) 네트워크 끊김 시 자동 로컬 모드 전환 2) 출입/라커/출석 오프라인 동작 3) 네트워크 복구 시 자동 동기화 4) 오프라인 상태 표시 배너 | F41: SCR-096 | G41: Critical | H41: XL | J41: Done | K41: 오프라인 모드 설정 | L41: 1
A42: US-041 | B42: 시설관리 | C42: 매니저 | D42: 매니저로서 라커 자동 배정 시 상단/홀수 우선 배정 규칙을 적용하여 회원 불만을 줄이고 싶다 | E42: 1) 상단>하단, 홀수>짝수 우선 배정 2) 고장/점유 라커 자동 스킵 3) 마감 시 전체 라커 일괄 해제 4) 잔류물 체크리스트 제공 | F42: SCR-050 | G42: High | H42: S | J42: To Do | K42: 락커 현황 | L42: 3
A43: US-042 | B43: 매출관리 | C43: FC | D43: FC로서 최초 상담한 회원의 실적이 정확히 나에게 귀속되길 원한다 | E43: 1) 최초 상담자 자동 실적 귀속 2) 귀속 유효기간(N일) 설정 3) 계약 처리자와 실적 담당자 분리 가능 4) 상담 이력 자동 기록 | F43: SCR-030 | G43: High | H43: M | J43: To Do | K43: 매출 조회 | L43: 3
... A57: US-056 | B57: FC앱 | C57: FC | D57: FC로서 앱에서 상담 이력을 기록하고 실적 귀속 잔여일을 확인하고 싶다 | E57: 1) 상담 내용/결과 기록 2) 실적 귀속 잔여일 표시(D-N) 3) 상담 → 계약 전환율 확인 4) 타 FC 상담 이력 참조 | F57: SCR-F03 | G57: High | H57: M | J57: To Do | K57: FC 회원 상담 기록 | L57: 1

Sheet 화면설계서
A1: 화면 ID | B1: 화면명 | C1: 플랫폼 | D1: 화면 경로 | E1: 화면 설명 | F1: [자동] UI 요소 목록 | G1: 인터랙션 정의 | H1: Web 특이사항 | I1: App 특이사항 | J1: 진입 경로 | K1: 이동 가능 화면 | L1: 에러 화면 정의 | M1: 접근성 체크 | N1: 반응형 체크 (Web) | O1: 가로/세로 모드 (App) | P1: 디자인 시안 링크 | Q1: 상태 | R1: 담당자 | S1: [자동] 관련 기능 수 | T1: [자동] 관련 TC 수 | U1: [자동] 관련 API 수 | V1: 비고 | W1: [자동] UI 요소 수 | X1: 레이아웃 구조 | Y1: 섹션 순서 | Z1: 화면 유형 | AA1: 진입 트리거 | AB1: Loading 상태 | AC1: Empty 상태 | AD1: 반응형 상세 | AE1: 고정 요소
A2: SCR-001 | B2: 로그인 | C2: Web | D2: /login | E2: 이메일/비밀번호 기반 로그인 화면. 지점 선택 드롭다운 포함 | F2: UI-001, UI-002, UI-003, UI-004, UI-005 | G2: 비밀번호 마스킹 토글, Enter키 로그인, 지점 선택 시 로고 변경 | H2: JWT 토큰 기반 세션 관리 | J2: URL 직접 접근, 세션 만료 시 리다이렉트 | K2: SCR-002 (대시보드) | L2: 이메일 미입력: '이메일을 입력하세요' 비밀번호 오류: '비밀번호가 올바르지 않습니다' 계정 잠금: '5회 실패로 잠금됨' | M2: Tab 이동 순서, aria-label | N2: 1024px 이상 중앙 정렬 | Q2: 확정 | R2: 개발팀 | S2: 1 | T2: 6 | U2: 1 | V2: 비밀번호 변경 모달 AppHeader에 구현. 로그인 유지 체크박스 추가 (2026-03-13) | W2: 5 | X2: [배경] min-h-screen 중앙정렬 그라데이션 [메인카드] max-w-[400px] 흰색 박스 중앙 - 로고 영역 (S배지 + 텍스트) - 지점선택 드롭다운 (MapPin 아이콘) - 아이디 입력 (User 아이콘) - 비밀번호 입력 (Lock 아이콘) + Eye토글 - 로그인유지 체크 + 비밀번호찾기 링크 - 에러메시지 (조건부, 빨간배경) - 로그인 버튼 [푸터] 절대위치 하단 | Y2: 1:로고 → 2:지점선택 → 3:아이디 → 4:비밀번호 → 5:옵션(유지+찾기) → 6:에러메시지 → 7:로그인버튼 | Z2: page (전체화면, 사이드바 없음) | AA2: URL 직접접근 / 세션만료 시 리다이렉트 / 로그아웃 후 | AB2: 지점목록: Loader2 스핀 아이콘 로그인 버튼: Loader2 스핀 + '로그인 중...' 텍스트 지점 로딩 중 드롭다운 비활성 | AC2: 지점 목록 없음: 드롭다운 '지점 없음' 표시 에러: 빨간 배경 박스에 에러 메시지 | AD2: ≥1024px: 중앙정렬 카드 <1024px: 카드 max-w-[400px] 유지, padding 축소 모바일: gap-sm, p-md | AE2: 없음 (단일 스크롤 없는 화면)
A3: SCR-002 | B3: 대시보드 | C3: Web | D3: / | E3: 지점별 핵심 KPI 대시보드. 회원/매출/출석 통계 카드 + 알림 리스트 | F3: UI-006, UI-007, UI-008, UI-009, UI-010, UI-011, UI-012, UI-013 | G3: 통계 카드 클릭 시 상세 이동, 차트 호버 툴팁, 기간 필터 | H3: 반응형 그리드 (2열→1열) | J3: SCR-001 (로그인 후) | K3: SCR-010, SCR-030, SCR-020 | L3: 데이터 로딩 실패: '데이터를 불러올 수 없습니다' + 재시도 버튼 | M3: 차트 alt-text | N3: 1280px 이상 4열 카드 | Q3: 확정 | R3: 개발팀 | S3: 1 | T3: 3 | U3: 5 | V3: Supabase 실데이터 차트 연동. 통계 카드 클릭→상세 이동 (2026-03-13) | W3: 8 | X3: [공지배너] 닫기 가능, 아이콘+텍스트+버튼 (조건부) [헤더] 제목/설명 + 새로고침 + 회원등록 버튼 [섹션1: 통계카드] 6개 StatCard 그리드 [섹션2: 운영현황] 기간필터(오늘/이번주/이번달/분기) + 3개 차트(회원분포 원형/주간출석 라인/매출추이 막대) [섹션3: 리스트] 4개 DataTable 카드 (생일자/미수금/홀딩/만료임박) 2x2 그리드 [섹션4: 프로모션] 2개 배너 카드 | Y3: 1:공지배너 → 2:헤더 → 3:통계카드6개 → 4:운영현황차트3개 → 5:리스트카드4개 → 6:프로모션배너2개 | Z3: page | AA3: 로그인 성공 후 자동이동 / GNB '대시보드' 클릭 | AB3: 통계카드: 숫자 부분 스켈레톤 차트: 로딩 스핀 표시 리스트: 3줄 스켈레톤 행 새로고침: RefreshCw 아이콘 회전(animate-spin) | AC3: 통계카드: 0 표시 생일자: '오늘 생일인 회원이 없습니다' 미수금: '미수금 회원이 없습니다' 홀딩: '홀딩 중인 회원이 없습니다' 만료임박: '만료 임박 회원이 없습니다' | AD3: ≥1280px(xl): 카드6열 + 차트3열 + 리스트2열 + 프로모션2열 768~1279px(md): 카드3열 + 차트2열 + 리스트1열 + 프로모션1열 <768px: 카드2열 + 차트1열 + 리스트1열 + 프로모션1열 | AE3: GNB 상단 고정 사이드바 좌측 고정
A4: SCR-010 | B4: 회원 목록 | C4: Web | D4: /members | E4: 회원 검색, 필터, 페이지네이션이 포함된 목록 화면 | F4: UI-014, UI-015, UI-016, UI-017, UI-018, UI-019, UI-020, UI-021 | G4: 실시간 검색, 필터 조합, 정렬, 페이지네이션, 엑셀 다운로드 | H4: 테이블 가로스크롤 (좁은 화면) | J4: GNB 메뉴, SCR-002 바로가기 | K4: SCR-011, SCR-012 | L4: 검색 결과 없음: '조건에 맞는 회원이 없습니다' 로딩 실패: 스켈레톤 + 재시도 | M4: 테이블 aria-label, 스크린리더 페이지 안내 | N4: 테이블 반응형 스크롤 | Q4: 확정 | R4: 개발팀 | S4: 2 | T4: 4 | U4: 2 | V4: window.prompt→상태 선택 모달 전환. DataTable 키보드 접근성 (2026-03-13) | W4: 8 | X4: [헤더] 제목/설명 + 엑셀다운로드 + 회원추가 버튼 [섹션1: 통계카드] 4개 StatCard [섹션2: 메인탭] TabNav 6개(회원/회원권/수강권/락커/운동복/상품별) [섹션3: 테이블영역] 흰색박스 - 상태필터탭 6개(전체/활성/만료/미등록/홀딩/정지) - SearchFilter(검색+5개필터) - 벌크액션바 (선택 시 조건부) - DataTable (8컬럼, 선택/정렬/페이지네이션) | Y4: 1:헤더 → 2:통계카드4개 → 3:메인탭 → 4:상태필터 → 5:검색/필터 → 6:벌크액션 → 7:테이블 | Z4: page | AA4: GNB '회원 목록' 클릭 / 대시보드 통계카드 클릭 | AB4: 통계카드: 숫자 스켈레톤 테이블: 행 스켈레톤 (5줄) 검색: 300ms debounce 후 조회 | AC4: 통계카드: 0 표시 검색결과 없음: '조건에 맞는 회원이 없습니다' EmptyState 필터 초기화 안내 | AD4: ≥1024px(lg): 통계카드4열 768~1023px(md): 통계카드2열 <768px: 통계카드1열 테이블: 가로스크롤 | AE4: GNB 상단고정 벌크액션바: 선택 시 테이블 상단 고정
A5: SCR-011 | B5: 회원 상세 | C5: Web | D5: /members/detail | E5: 회원 프로필 + 탭(이용권/출석/결제/체성분/메모) 구성 | F5: UI-022, UI-023, UI-024, UI-025, UI-026, UI-027 | G5: 탭 전환, 이용권 만료일 강조, 출석 히트맵, 결제 내역 페이지네이션 | H5: 탭 URL 파라미터 유지 | J5: SCR-010 회원 클릭 | K5: SCR-013, SCR-014, SCR-010 | L5: 회원 미존재: 404 페이지 데이터 로딩 실패: 탭별 에러 표시 | M5: 탭 키보드 네비게이션 | N5: 탭 세로 배치 (좁은 화면) | Q5: 확정 | R5: 개발팀 | S5: 2 | T5: 1 | U5: 2 | W5: 6 | X5: [헤더] 뒤로가기 + 회원 프로필카드(사진/이름/상태/기본정보) [액션바] 수정/삭제/메시지 등 버튼 [탭영역] TabNav 7개(기본정보/계약현황/출석/체성분/결제/커뮤니케이션/기타) [탭콘텐츠] 탭별 상세정보 (lazy 로드) | Y5: 1:프로필카드 → 2:액션버튼 → 3:탭네비 → 4:탭콘텐츠 | Z5: page | AA5: SCR-010 회원명 클릭 / 다른 페이지에서 moveToPage(985, {id}) | AB5: 프로필: 스켈레톤 카드 각 탭: 개별 로딩 스피너 탭 전환 시 lazy load | AC5: 회원 미존재: 404 페이지 데이터 없는 탭: 탭별 개별 empty 메시지 이용권 없음: '등록된 이용권이 없습니다' | AD5: ≥1280px: 프로필+탭 풀너비 <768px: 탭 세로배치, 프로필 축소 탭 URL 파라미터 유지 | AE5: GNB 상단고정 탭네비 스크롤 시 sticky
A6: SCR-012 | B6: 회원 등록 | C6: Web | D6: /members/new | E6: 신규 회원 등록 폼. 필수/선택 항목 구분 | F6: UI-028, UI-029, UI-030, UI-031, UI-032, UI-033, UI-034, UI-035, UI-036, UI-037 | G6: 실시간 유효성 검사, 연락처 자동 포맷, 주소 검색 API 연동 | H6: 폼 상태 유지 (뒤로가기 시) | J6: SCR-010 '회원등록' 버튼 | K6: SCR-011 (등록 완료 후) | L6: 필수 항목 미입력: 필드 하단 에러 메시지 중복 연락처: '이미 등록된 연락처입니다' 서버 오류: 토스트 알림 | M6: 필수 항목 aria-required | N6: 폼 1열 배치 | Q6: 확정 | R6: 개발팀 | S6: 0 | T6: 4 | U6: 1 | W6: 10 | X6: [헤더] 제목(등록/수정모드) + 초기화/취소 버튼 [스텝네비] TabNav 2단계 (필수정보/추가정보) [Step1: 필수정보] - 프로필이미지 드래그영역 - FormSection '기본 인적사항' 2열 (이름/성별/생년월일/연락처/회원구분) - FormSection '관리 정보' 2열 (담당FC/트레이너/방문경로/운동목적) [Step2: 추가정보] - FormSection '추가 연락' 2열 (별칭/이메일/주소검색/회사명/출석번호) - FormSection '기타 설정' (광고수신/메모 textarea 500자) [하단] 이전/다음(또는 저장) 버튼 고정 | Y6: 1:헤더 → 2:스텝표시 → 3:폼섹션들 → 4:하단버튼 | Z6: page (2-step wizard) | AA6: SCR-010 '회원등록' 버튼 클릭 | AB6: 저장 버튼: Loader2 스핀 + '저장 중...' | AC6: 담당FC/트레이너 목록 없음: '등록된 직원이 없습니다' 주소검색 결과 없음: '검색 결과가 없습니다' | AD6: ≥768px(md): FormSection 2열 <768px: FormSection 1열 하단 버튼: 모바일 전체너비 | AE6: 하단 액션버튼 고정
A7: SCR-013 | B7: 회원 수정 | C7: Web | D7: /members/edit | E7: 기존 회원 정보 수정 폼. 기존 데이터 프리필 | F7: UI-119, UI-120 | G7: 변경사항 비교 표시, 저장 전 확인 모달 | H7: 변경 이력 자동 기록 | J7: SCR-011 '수정' 버튼 | K7: SCR-011 (저장 후) | L7: 변경 없이 저장: '변경된 내용이 없습니다' 서버 오류: 토스트 알림 | M7: 폼 접근성 동일 | N7: 폼 1열 배치 | Q7: 확정 | R7: 개발팀 | S7: 0 | T7: 1 | U7: 1 | W7: 2 | X7: [헤더] 제목 + 취소/저장 버튼 [FormSection '기본 정보'] 이름/연락처/성별/생년월일/가입일/담당직원 [FormSection '이용권 정보'] 기존 이용권 리스트 + 새 이용권 추가 버튼 [FormSection '상세 정보'] 주소/유입경로/운동목적/메모 [취소확인 다이얼로그] | Y7: 1:헤더 → 2:기본정보 → 3:이용권정보 → 4:상세정보 | Z7: page | AA7: SCR-011 '수정' 버튼 클릭 | AB7: 기존 데이터 프리필 중: 전체 스켈레톤 저장: 버튼 로딩 | AC7: 이용권 없음: '등록된 이용권이 없습니다' + 안내메시지 | AD7: 폼 1열 배치 (max-width 제한) | AE7: 없음
A8: SCR-014 | B8: 체성분 분석 | C8: Web | D8: /body-composition | E8: 회원별 체성분 측정 기록 입력 및 변화 추이 차트 | F8: UI-121, UI-122 | G8: 측정값 입력 폼, 날짜별 라인 차트, 목표 대비 게이지 | H8: 차트 라이브러리 (Recharts) | J8: SCR-011 '체성분' 탭 | K8: SCR-011 | L8: 측정 데이터 없음: '아직 측정 기록이 없습니다' 입력 범위 초과: 경고 토스트 | M8: 차트 alt-text, 데이터 테이블 대체 | N8: 차트 반응형 | Q8: 확정 | R8: 개발팀 | S8: 1 | T8: 0 | U8: 0 | W8: 2 | X8: [뒤로가기 버튼] [헤더] 회원명+최근측정일 + 전체추출/새측정추가 버튼 [섹션1: 통계카드] 3개 (현재체중/골격근량/체지방률) [섹션2: 탭] 기록목록/변화그래프/목표관리 - 기록목록: DataTable - 변화그래프: SVG LineChart + 메트릭토글 + 호버툴팁 + 변화요약 - 목표관리: GoalGauge 2개 (목표체중/목표체지방) [섹션3: 분석] 2칸 그리드 - 비만분석 (BMI/체지방률 AnalysisRow 범위바) - 에너지/대사 (BMR/제지방량/권장열량) [모달] 측정추가(날짜/체중/골격근/체지방+BMI자동) / 목표수정 | Y8: 1:뒤로가기 → 2:헤더 → 3:통계카드3개 → 4:탭(기록/그래프/목표) → 5:분석그리드 | Z8: page | AA8: SCR-011 '체성분' 탭 클릭 | AB8: 데이터 로딩: 통계카드 스켈레톤 + 차트 로딩스핀 | AC8: 측정데이터 없음: '아직 측정 기록이 없습니다' 목표 미설정: '목표를 설정해주세요' | AD8: ≥768px: 분석 2열 <768px: 분석 1열 차트 반응형 (SVG viewBox) | AE8: GNB 상단고정
A9: SCR-020 | B9: 출석 기록 | C9: Web | D9: /attendance | E9: 회원 출석 현황 조회. 일별/주별/월별 뷰 전환 | F9: UI-123, UI-124 | G9: 날짜 필터, 출석 유형 필터, 타지점 출석 표시 | H9: 캘린더 컴포넌트 | J9: GNB 메뉴 | K9: SCR-011 (회원 클릭) | L9: 데이터 없음: '해당 기간 출석 기록이 없습니다' | M9: 날짜 선택 키보드 접근 | N9: 테이블 반응형 | Q9: 확정 | R9: 개발팀 | S9: 1 | T9: 1 | U9: 2 | V9: 날짜 필터 DataTable 적용. 실시간 출석 통계 (2026-03-13) | W9: 2 | X9: [헤더] 제목/설명 + 날짜네비(◀ 날짜 ▶) + 뷰전환(일/주/월) + 실시간토글 + 수동출석버튼 [일별뷰] - 통계카드 4개 (오늘출석/PT/GX/신규방문) - 출석유형 범례 (색상코딩) - SearchFilter + DataTable (10컬럼) [주별뷰] 통계카드3개 + WeeklyView(7일 막대차트) [월별뷰] 통계카드3개 + MonthlyView(28일 히트맵) [실시간팝업] 우측하단 슬라이드인, AI음성메시지 (자동사라짐) [모달] 수동출석(회원검색+유형4버튼+시간) | Y9: 1:헤더+날짜+뷰전환 → 2:통계카드 → 3:범례 → 4:검색/필터 → 5:테이블/차트 | Z9: page | AA9: GNB '출석 관리' 클릭 / 대시보드 출석카드 클릭 | AB9: 통계카드: 숫자 스켈레톤 테이블: 행 스켈레톤 뷰 전환: 데이터 재조회 로딩 | AC9: 출석기록 없음: '해당 기간 출석 기록이 없습니다' 검색결과 없음: 빈 테이블 | AD9: ≥768px(md): 통계카드4열 <768px: 통계카드2열 히트맵/차트: 가로스크롤 | AE9: GNB 상단고정 날짜네비+뷰전환: 헤더영역 고정
A10: SCR-021 | B10: 일정 관리 | C10: Web | D10: /calendar | E10: PT/GX 일정 캘린더. 월/주/일 뷰 전환 | F10: UI-125, UI-126 | G10: 드래그앤드롭 일정 이동, 클릭 상세 모달, 트레이너 필터 | H10: FullCalendar 라이브러리 | J10: GNB 메뉴 | K10: SCR-011 (회원 연결) | L10: 일정 충돌: '해당 시간에 이미 예약이 있습니다' 과거 일정 수정 불가 | M10: 캘린더 키보드 네비게이션 | N10: 뷰 자동 전환 (주→일) | Q10: 확정 | R10: 개발팀 | S10: 1 | T10: 1 | U10: 0 | V10: FullCalendar 라이브러리 전환. 드래그앤드롭 일정 이동/리사이즈 (2026-03-13) | W10: 2 | X10: [헤더] 제목/설명 + 스케줄일괄변경 + 수업등록 버튼 [탭] 5개 (일정표/수업관리/횟수관리/페널티/유효수업) [일정표탭] - 컨트롤바: 뷰전환(월/주/일) + 날짜네비 + 트레이너필터 - 범례 (강사+수업유형 색상) - MonthView(7x5 그리드, 셀당3이벤트+'+N개') - WeekView(8x14 타임테이블) - DayView(시간x슬롯) [수업관리탭] SearchFilter + DataTable [페널티탭] 필터 + DataTable [유효수업탭] DataTable [모달] EventDetail(수업상세, 수정/삭제) / EventAdd(등록/수정폼, 반복설정) | Y10: 1:헤더 → 2:탭 → 3:컨트롤바 → 4:범례 → 5:캘린더뷰(월/주/일) | Z10: page | AA10: GNB '수업/캘린더' 클릭 | AB10: 캘린더: 이벤트 스켈레톤 수업관리: 테이블 스켈레톤 | AC10: 이벤트 없음: 빈 캘린더 셀 수업 없음: '등록된 수업이 없습니다' 횟수관리: '준비 중' 안내 | AD10: ≥1280px: 캘린더 풀너비 <768px: 주→일뷰 자동전환 권장 타임테이블: 가로스크롤 | AE10: GNB 상단고정 컨트롤바 sticky
A11: SCR-030 | B11: 매출 조회 | C11: Web | D11: /sales | E11: 매출 현황 조회. 기간/유형/상태 필터 + 통계 요약 카드 | F11: UI-038, UI-039, UI-040, UI-041, UI-042, UI-043, UI-044 | G11: 날짜 범위 선택, 유형 필터, 상태 필터, 통계 카드 갱신, 엑셀 다운로드 | H11: 금액 포맷 (천단위 콤마) | J11: GNB 메뉴, SCR-002 매출 카드 | K11: SCR-031 (POS 이동) | L11: 데이터 없음: '해당 기간 매출이 없습니다' 다운로드 실패: 재시도 안내 | M11: 금액 스크린리더 읽기 | N11: 통계 카드 2열→1열 | Q11: 확정 | R11: 개발팀 | S11: 2 | T11: 2 | U11: 2 | W11: 7 | X11: [헤더] 제목/설명 + 신규결제(POS) + 엑셀다운로드 버튼 [섹션1: 요약카드] 4개 (순매출/카드/현금/미수금) [섹션2: 필터] 기간프리셋(오늘/이번주/이번달) + SearchFilter(날짜범위/유형/상태) [섹션3: 탭+테이블] TabNav 7개(매출내역/기간별/상품별/결제수단별/담당자별/환불/미납) + DataTable 13컬럼 [섹션4: 하단요약바] 총/순/현금/카드/마일리지/환불/미납 합계 | Y11: 1:헤더 → 2:요약카드4개 → 3:기간프리셋+필터 → 4:탭7개 → 5:테이블 → 6:하단합계바 | Z11: page | AA11: GNB '매출 현황' 클릭 / 대시보드 매출카드 클릭 | AB11: 요약카드: 숫자 스켈레톤 테이블: 행 스켈레톤 기간변경: 카드+테이블 동시 갱신 | AC11: 매출 없음: '해당 기간 매출이 없습니다' 다운로드 실패: 재시도 안내 toast | AD11: ≥768px(md): 요약카드4열 <768px: 요약카드2열 하단합계: flex-wrap 테이블: 가로스크롤 | AE11: GNB 상단고정 하단합계바 sticky bottom
A12: SCR-031 | B12: POS | C12: Web | D12: /pos | E12: POS 상품 선택 화면. 카테고리 탭 + 상품 그리드 + 장바구니 | F12: UI-045, UI-046, UI-047, UI-048 | G12: 카테고리 탭 전환, 상품 클릭 시 장바구니 추가, 수량 조절, 삭제 | H12: 2컬럼 레이아웃 (상품 | 장바구니) | J12: GNB 메뉴, SCR-030 | K12: SCR-032 (결제 진행) | L12: 장바구니 비어있음: '상품을 선택해주세요' 재고 없음: 상품 비활성화 | M12: 상품 그리드 키보드 선택 | N12: 장바구니 하단 고정 | Q12: 확정 | R12: 개발팀 | S12: 0 | T12: 1 | U12: 1 | W12: 4 | X12: [헤더] 제목/설명 + 상품등록 버튼 [2열 레이아웃] - [좌측: 상품그리드] - 카테고리탭 4개(이용권/PT/GX/기타) + 검색 - ProductCard 그리드 (재고배지/상품명/기간·횟수/현금가·카드가/호버+버튼) - [우측: 장바구니 사이드바 360px 고정] - 헤더(카운트, 전체삭제) - 아이템목록(상품명/수량−+/가격타입토글/소계) - 하단(총합 + 결제하기버튼) | Y12: 1:헤더 → 2좌:카테고리탭+검색 → 3좌:상품그리드 → 2우:장바구니헤더 → 3우:아이템목록 → 4우:합계+결제 | Z12: page (2-column layout) | AA12: GNB 'POS 결제' 클릭 / SCR-030 '신규 결제' 버튼 | AB12: 상품목록: 카드 스켈레톤 그리드 장바구니: 빈 상태 | AC12: 상품 없음: '등록된 상품이 없습니다' 장바구니 비어있음: ShoppingCart 아이콘 + '상품을 선택해주세요' 검색결과 없음: '검색 결과가 없습니다' | AD12: ≥1024px(lg): 2열(상품+장바구니) <1024px: 1열(상품→장바구니 순서) 상품그리드: xl:4열→md:3열→2열 장바구니: 모바일 전체너비 | AE12: 장바구니 사이드바: lg에서 우측 고정 모바일: 하단 고정 없음
A13: SCR-032 | B13: POS 결제 | C13: Web | D13: /pos/payment | E13: 결제 수단 선택 및 결제 처리. 복합결제 지원 | F13: UI-049, UI-050, UI-051, UI-052 | G13: 결제수단 선택, 금액 입력, 마일리지 사용, 결제 확인 모달 | H13: 결제 API 연동 | J13: SCR-031 '결제' 버튼 | K13: SCR-030 (결제 완료 후) | L13: 결제 실패: '결제에 실패했습니다. 다시 시도해주세요' 잔액 부족: 안내 메시지 | M13: 금액 입력 접근성 | N13: 모달 팝업 | Q13: 확정 | R13: 개발팀 | S13: 1 | T13: 3 | U13: 1 | V13: window.confirm→ConfirmDialog 컴포넌트 전환 (2026-03-13) | W13: 4 | X13: [헤더] 제목 + 초기화 버튼 [2열 레이아웃] - [좌측: 결제요약] - 주문 상품 리스트 (StatusBadge 카테고리) - 회원검색 (SearchFilter, 드롭다운) - 선택된 회원 정보 카드 - [우측: 결제수단 380px] - 4개 결제수단 버튼 (카드/현금/마일리지/복합) - 복합결제 금액분배 입력 (조건부) - 마일리지 잔액 안내 (조건부) - 결제확인 버튼 [결제완료화면] 전체페이지 교체 (체크아이콘+요약+계속판매버튼) [모달] 결제확인 (주문요약표시) | Y13: 1:헤더 → 2좌:주문리스트 → 3좌:회원검색 → 2우:결제수단4버튼 → 3우:금액입력 → 4우:결제버튼 | Z13: page (2-column layout) → 결제완료 시 전체 교체 | AA13: SCR-031 '결제하기' 버튼 클릭 | AB13: 회원검색: 드롭다운 로딩 결제처리: 버튼 로딩스핀 | AC13: 장바구니 비어있음: '상품을 먼저 선택해주세요' 안내 회원 미선택: 비회원 결제 가능 표시 | AD13: ≥1024px(lg): 2열(요약+결제) <1024px: 1열 우측패널: lg에서 w-[380px] 고정 | AE13: 없음
A14: SCR-040 | B14: 상품 목록 | C14: Web | D14: /products | E14: 이용권/PT/기타 상품 목록. 카테고리 필터 | F14: UI-082, UI-083, UI-084 | G14: 카테고리 필터, 상태 토글, 정렬 | H14: 테이블 레이아웃 | J14: GNB 메뉴 | K14: SCR-041 (등록), SCR-040 (수정 모달) | L14: 상품 없음: '등록된 상품이 없습니다' | M14: 테이블 접근성 | N14: 테이블 반응형 | Q14: 확정 | R14: 개발팀 | S14: 2 | T14: 3 | U14: 1 | W14: 3 | X14: [헤더] 제목/설명 + 상품등록 버튼 [섹션1: 통계카드] 4개 (전체/활성/비활성/카테고리수) [섹션2: 탭] 5개(전체/이용권/PT/GX/기타) + 개수표시 [섹션3: 검색] SearchFilter (상품명) [섹션4: DataTable] 7컬럼 (카테고리/상품명/가격/이용기간/세션/상태/액션) - 정렬: name,price,category (ArrowUp/Down/UpDown 아이콘) - 액션: 수정/삭제 버튼 [다이얼로그] 삭제확인 (danger) | Y14: 1:헤더 → 2:통계카드4개 → 3:탭5개 → 4:검색 → 5:테이블 | Z14: page | AA14: GNB '상품 관리' 클릭 | AB14: 통계카드: 숫자 스켈레톤 테이블: 행 스켈레톤 | AC14: 상품 없음: '등록된 상품이 없습니다' | AD14: ≥1024px(lg): 통계카드4열 <768px: 통계카드1열 테이블: 가로스크롤 | AE14: GNB 상단고정
A15: SCR-041 | B15: 상품 등록 | C15: Web | D15: /products/new | E15: 신규 상품 등록 폼. 카테고리/이름/가격/기간 설정 | F15: UI-085, UI-086, UI-087, UI-088 | G15: 카테고리 선택 시 하위 필드 변경, 가격 입력 포맷 | H15: 폼 유효성 검사 | J15: SCR-040 '등록' 버튼 | K15: SCR-040 (저장 후) | L15: 필수 미입력: 필드별 에러 중복 상품명: 경고 | M15: 폼 접근성 | N15: 폼 1열 | Q15: 확정 | R15: 개발팀 | S15: 2 | T15: 1 | U15: 1 | W15: 4 | X15: [초기: 유형선택화면] - 중앙정렬 텍스트 - 4개 유형카드 그리드 (이용권/PT/GX/기타) - 취소 링크 [메인폼] - [헤더] 동적 제목 + 액션 - [FormSection1: 기본정보 2열] 카테고리/상품명(중복체크)/현금가(콤마)/카드가/설명(2열span)/태그 - [FormSection2: 이용기간/횟수 2열] 이용기간/횟수(PT·GX만)/요일안내(GX만) - [FormSection3: 추가설정 접기가능] 홀딩설정(토글+세부)/이용시간(범위추가삭제)/판매노출(토글2개) - [하단고정바] 상태배지+카테고리 + 취소/등록버튼 | Y15: 1:유형선택 → 2:헤더 → 3:기본정보 → 4:기간/횟수 → 5:추가설정 → 6:하단고정바 | Z15: page (유형선택 → 폼 2-step) | AA15: SCR-040 '등록' 버튼 또는 수정 클릭 | AB15: 저장: 버튼 로딩스핀 상품명 중복체크: 실시간 검증 | AC15: 없음 (폼 페이지) | AD15: ≥768px(md): FormSection 2열 <768px: FormSection 1열 하단바: 모바일 전체너비, md에서 자동크기 | AE15: 하단 액션바 sticky bottom
A16: SCR-050 | B16: 락커 현황 | C16: Web | D16: /locker | E16: 구역별 락커 그리드. 색상으로 상태 구분 (사용중/빈/만료임박) | F16: UI-053, UI-054, UI-055, UI-056 | G16: 구역 탭 전환, 락커 클릭 시 상세 모달, 범례 표시 | H16: CSS Grid 레이아웃 | J16: GNB 메뉴 | K16: SCR-051 (관리 이동) | L16: 락커 없음: '등록된 락커가 없습니다' | M16: 색상 + 패턴으로 상태 구분 (색약 대응) | N16: 그리드 반응형 | Q16: 확정 | R16: 개발팀 | S16: 2 | T16: 1 | U16: 1 | W16: 4 | X16: [헤더] 제목 + 새로고침/엑셀/락커추가 버튼 [섹션1: 통계카드] 4개 (전체/사용중/만료임박/고장) [섹션2: 구역탭+검색] TabNav(A/B/C구역) + 검색input + 범례 [섹션3: 락커그리드] 4x8=32개 셀 (aspect-square, 색상으로 상태구분) - 셀내용: 번호/회원명/D-Day/고장표시 - 일괄선택모드: 체크아이콘 [모달] 락커상세(배정회원/만료일/이력테이블/배정해제) [다이얼로그] 일괄해제확인 | Y16: 1:헤더 → 2:통계카드4개 → 3:구역탭+검색+범례 → 4:락커그리드 | Z16: page | AA16: GNB '락커 관리' 클릭 | AB16: 그리드: 전체 스켈레톤 모달: 이력 로딩 | AC16: 락커 없음: '등록된 락커가 없습니다' 빈 락커: '비어있음' 표시 검색 없음: '결과가 없습니다' | AD16: ≥768px(md): 그리드8열 640~767px(sm): 6열 <640px: 4열 | AE16: GNB 상단고정
A17: SCR-051 | B17: 락커 관리 | C17: Web | D17: /locker/management | E17: 락커 배정/해제/일괄 관리 | F17: UI-089, UI-090, UI-091, UI-092 | G17: 회원 검색 → 빈 락커 선택 → 배정, 일괄 선택 해제 | H17: 배정 모달 | J17: SCR-050, GNB | K17: SCR-050 | L17: 이미 배정된 락커: '이미 사용중인 락커입니다' | M17: 모달 접근성 | N17: 모달 반응형 | Q17: 확정 | R17: 개발팀 | S17: 0 | T17: 1 | U17: 1 | W17: 4 | X17: [헤더] 밴드/카드관리 + 상태동기화/엑셀 버튼 [섹션1: 통계카드] 5개 (총/가능/사용중/시간초과/비정상) [섹션2: 탭] 3개(일일/개인/골프) [섹션3: 배정패널] 3열그리드(회원검색AutoComplete + 선택락커확인 + 배정버튼) [일괄해제경고] 시간초과 시 amber배너 [빈사물함그리드] 12열 그리드, 선택토글 [전체현황] 남자/여자 섹션별 그리드 (시간초과: pulse아이콘) [범례] 5가지 상태색상 | Y17: 1:헤더 → 2:통계카드5개 → 3:탭 → 4:배정패널 → 5:경고배너 → 6:빈사물함 → 7:전체현황 → 8:범례 | Z17: page | AA17: GNB '사물함 관리' 클릭 | AB17: 사물함 데이터: 그리드 스켈레톤 배정처리: 버튼 로딩 | AC17: 빈 사물함 없음: '모든 사물함이 사용 중입니다' | AD17: ≥1024px(lg): 그리드12열 768~1023px(md): 10열 640~767px(sm): 8열 <640px: 5열 | AE17: GNB 상단고정
A18: SCR-052 | B18: RFID 관리 | C18: Web | D18: /rfid | E18: RFID 카드 등록/해제/이력 조회 | F18: UI-108, UI-109, UI-110 | G18: 카드 번호 스캔 입력, 회원 매핑, 분실 처리 버튼 | H18: RFID 리더기 연동 | J18: GNB 메뉴 | K18: SCR-011 (회원 연결) | L18: 미등록 카드: '등록되지 않은 카드입니다' 이미 매핑: '다른 회원에게 배정된 카드' | M18: 폼 접근성 | N18: 테이블 반응형 | Q18: 확정 | R18: 개발팀 | S18: 1 | T18: 1 | U18: 3 | W18: 3 | Y18: 카드 목록 → 카드 등록/해제
A19: SCR-053 | B19: 룸 관리 | C19: Web | D19: /rooms | E19: GX룸/PT룸 등록/수정/삭제. 예약 시간대 설정 | F19: UI-111, UI-112 | G19: 룸 카드 뷰, 수용인원 설정, 시간대 슬롯 설정 | H19: 카드 레이아웃 | J19: GNB 메뉴 | K19: SCR-021 (일정 연결) | L19: 룸 삭제 시 예약 존재: '기존 예약이 있어 삭제할 수 없습니다' | M19: 카드 접근성 | N19: 카드 반응형 | Q19: 확정 | R19: 개발팀 | S19: 1 | T19: 1 | U19: 1 | W19: 2 | Y19: 시설 목록 → 시설 상태 → 관리
A20: SCR-060 | B20: 직원 목록 | C20: Web | D20: /staff | E20: 직원 검색/필터/목록 조회 | F20: UI-057, UI-058, UI-059, UI-060, UI-061 | G20: 역할 필터, 상태 필터, 검색, 테이블 정렬 | H20: 테이블 레이아웃 | J20: GNB 메뉴 | K20: SCR-061 (등록), 직원 상세 모달 | L20: 검색 결과 없음: '조건에 맞는 직원이 없습니다' | M20: 테이블 접근성 | N20: 테이블 반응형 | Q20: 확정 | R20: 개발팀 | S20: 2 | T20: 1 | U20: 3 | V20: 페이지네이션 상태 관리 구현. 퇴사 처리 ConfirmDialog (2026-03-13) | W20: 5 | X20: [헤더] 제목 + 직원등록 버튼 [섹션1: 통계카드] 4개 (전체/재직/휴직/퇴사) [섹션2: SearchFilter] 직원명/연락처 검색 + role/status 필터 [섹션3: 액션버튼] 4개 (메시지/상태변경/퇴사/다운로드) [섹션4: DataTable] 8컬럼 (No/이름/역할배지/연락처/입사일/상태/메모/메뉴) - 선택가능, 3방향정렬 [다이얼로그] 퇴사확인 (danger) | Y20: 1:헤더 → 2:통계카드4개 → 3:검색/필터 → 4:액션버튼 → 5:테이블 | Z20: page | AA20: GNB '직원 관리' 클릭 | AB20: 통계카드: 숫자 스켈레톤 테이블: 행 스켈레톤 | AC20: 직원 없음: '등록된 직원이 없습니다' | AD20: ≥1024px(lg): 통계카드4열 <768px: 통계카드1열 | AE20: GNB 상단고정
A21: SCR-061 | B21: 직원 등록 | C21: Web | D21: /staff/new | E21: 신규 직원 등록 폼 | F21: UI-093, UI-094, UI-095, UI-096, UI-097 | G21: 역할 선택 시 권한 미리보기, 관리자 계정 자동 생성 옵션 | H21: 폼 레이아웃 | J21: SCR-060 '등록' 버튼 | K21: SCR-060 (저장 후) | L21: 필수 미입력: 필드별 에러 중복 이메일: 경고 | M21: 폼 접근성 | N21: 폼 1열 | Q21: 확정 | R21: 개발팀 | S21: 0 | T21: 1 | U21: 1 | W21: 5 | X21: [헤더] 제목 + 취소/저장 버튼 [FormSection1: 기본정보] 이름(필수)/역할(select+권한미리보기)/연락처(자동하이픈)/입사일(date) [FormSection2: 추가정보] 이메일/메모(textarea) [다이얼로그] 등록취소확인 | Y21: 1:헤더 → 2:기본정보폼 → 3:추가정보폼 | Z21: page | AA21: SCR-060 '직원 등록' 버튼 | AB21: 저장: 버튼 로딩 | AC21: 없음 (폼 페이지) | AD21: max-w-[860px] 모든 필드 전체너비 | AE21: 없음
A22: SCR-062 | B22: 급여 현황 | C22: Web | D22: /payroll | E22: 월별 급여 현황 테이블. 합계/평균 요약 | F22: UI-098, UI-099, UI-100 | G22: 월 선택, 지급상태 필터, 합계 행 | H22: 테이블 + 요약 카드 | J22: GNB 메뉴 | K22: SCR-063 (명세서) | L22: 데이터 없음: '해당 월 급여 데이터가 없습니다' | M22: 테이블 접근성 | N22: 테이블 반응형 | Q22: 확정 | R22: 개발팀 | S22: 2 | T22: 1 | U22: 1 | V22: 페이지네이션 상태 관리 구현. 필터 변경 시 1페이지 리셋 (2026-03-13) | W22: 3 | Y22: 월 선택 → 급여 테이블 → 합계/액션
A23: SCR-063 | B23: 급여명세서 | C23: Web | D23: /payroll/statements | E23: 직원별 급여명세서 상세. PDF 다운로드 | F23: UI-127, UI-128, UI-129 | G23: 직원 선택, 월 선택, 명세서 상세 표시, PDF 다운로드 | H23: PDF 생성 (html2pdf) | J23: SCR-062 직원 클릭 | K23: SCR-062 | L23: 명세서 없음: '해당 월 명세서가 없습니다' | M23: 명세서 접근성 | N23: A4 레이아웃 | Q23: 확정 | R23: 개발팀 | S23: 0 | T23: 1 | U23: 1 | W23: 3 | Y23: 월 선택 → 급여 테이블 → 합계/액션
A24: SCR-070 | B24: 메시지 발송 | C24: Web | D24: /message | E24: SMS/카카오톡 메시지 발송. 수신자 선택 + 본문 편집 | F24: UI-062, UI-063, UI-064, UI-065, UI-066 | G24: 수신자 검색/그룹 선택, 메시지 유형 탭, 미리보기, 발송 이력 테이블 | H24: 메시지 API 연동 | J24: GNB 메뉴 | K24: 발송 이력 상세 모달 | L24: 수신자 미선택: '수신자를 선택해주세요' 발송 실패: 실패 건 재발송 옵션 | M24: 폼 접근성 | N24: 2컬럼→1컬럼 | Q24: 확정 | R24: 개발팀 | S24: 2 | T24: 2 | U24: 0 | W24: 5 | X24: [헤더] 월선택(최근12개월 드롭다운) + 내보내기 버튼 [섹션1: 통계카드] 4개 (총지급대상/총실지급액/지급완료/미지급보류) [섹션2: SearchFilter] 직원명/역할 + status 필터 [섹션3: DataTable] 7컬럼 (이름/역할/기본급/인센티브(녹색+)/공제(빨강-)/실지급액(파란굵음)/지급상태) - 정렬 지원 [합계행] 기본급/인센티브/공제합계+평균, 실지급액 강조 [바로가기배너] 급여명세서 링크 (FileText + 파란배경) | Y24: 1:헤더+월선택 → 2:통계카드4개 → 3:검색/필터 → 4:테이블 → 5:합계행 → 6:명세서배너 | Z24: page | AA24: GNB '급여 관리' 클릭 | AB24: 통계카드: 숫자 스켈레톤 테이블: 행 스켈레톤 월 변경: 전체 재조회 | AC24: 데이터 없음: '해당 월 급여 데이터가 없습니다' | AD24: ≥1024px(lg): 통계카드4열 <768px: 통계카드2열 | AE24: GNB 상단고정
A25: SCR-071 | B25: 자동 알림 | C25: Web | D25: /message/auto-alarm | E25: 자동 알림 규칙 설정 (만료/생일/미출석 등) | F25: UI-101, UI-102 | G25: 규칙 토글 ON/OFF, 발송 시점 설정, 메시지 템플릿 편집 | H25: 규칙 엔진 설정 UI | J25: SCR-070, GNB | K25: SCR-070 (발송 이력) | L25: 템플릿 미입력: '메시지 내용을 입력해주세요' | M25: 토글 접근성 | N25: 폼 1열 | Q25: 확정 | R25: 개발팀 | S25: 0 | T25: 0 | U25: 0 | W25: 2 | X25: [헤더] 일괄인쇄 버튼 [통계카드] 3개 (총실지급액/지급완료건/미지급건) [2열 레이아웃 xl기준] - [좌측: 선택패널 sticky] - 직원선택(select) + 월선택(select) - 명세서상세: 직원정보헤더(primary-light) + 지급항목(Plus녹색) + 공제항목(Minus빨강) + 실지급액(accent-light 강조) - 이메일/PDF 버튼 - [우측: 전체현황] - DataTable 7컬럼 [모달] 명세서상세 (스크롤, max-h-[65vh]) | Y25: 1:헤더 → 2:통계카드3개 → 3좌:직원/월선택+명세서상세 → 3우:전체현황테이블 | Z25: page (2-column layout) | AA25: SCR-070 '명세서 바로가기' 클릭 / GNB | AB25: 데이터 로딩: 전체 스켈레톤 직원변경: 명세서 갱신 | AC25: 명세서 없음: '해당 월 명세서가 없습니다' | AD25: ≥1280px(xl): 2열(선택+현황) <1280px: 1열(상하스택) 좌측패널: xl에서 sticky | AE25: 좌측패널 xl에서 sticky
A26: SCR-072 | B26: 쿠폰 관리 | C26: Web | D26: /message/coupon | E26: 쿠폰 생성/발급/이력 관리 | F26: UI-103, UI-104 | G26: 쿠폰 생성 모달, 발급 대상 선택, 사용 이력 테이블 | H26: 모달 + 테이블 | J26: GNB 메뉴 | K26: 쿠폰 상세 모달 | L26: 유효기간 만료: '만료된 쿠폰입니다' 사용 한도 초과: 비활성화 | M26: 모달 접근성 | N26: 테이블 반응형 | Q26: 확정 | R26: 개발팀 | S26: 2 | T26: 1 | U26: 0 | W26: 2 | Y26: 쿠폰 목록 → 쿠폰 생성/발급
A27: SCR-073 | B27: 마일리지 관리 | C27: Web | D27: /mileage | E27: 회원 마일리지 적립/사용 이력 조회 및 관리 | F27: UI-105, UI-106, UI-107 | G27: 회원 검색, 적립/차감 모달, 이력 테이블 | H27: 모달 + 테이블 | J27: GNB 메뉴 | K27: SCR-011 (회원 연결) | L27: 잔액 부족 차감: '마일리지가 부족합니다' | M27: 테이블 접근성 | N27: 테이블 반응형 | Q27: 확정 | R27: 개발팀 | S27: 0 | T27: 1 | U27: 0 | V27: 마일리지 이력 탭 엑셀 다운로드 실제 구현 (2026-03-13) | W27: 3 | Y27: 회원 검색 → 마일리지 현황 → 적립/차감
A28: SCR-080 | B28: 계약 마법사 | C28: Web | D28: /contracts/new | E28: 단계별 계약 등록 위자드 (회원→상품→기간→결제→확인) | F28: UI-067, UI-068, UI-069, UI-070, UI-071, UI-072 | G28: 스텝 인디케이터, 이전/다음 버튼, 단계별 유효성 검사 | H28: 위자드 컴포넌트 | J28: SCR-011, SCR-031 | K28: SCR-011 (완료 후) | L28: 필수 단계 미완료: '이전 단계를 완료해주세요' 결제 실패: 재시도 옵션 | M28: 스텝 접근성 | N28: 스텝 세로 배치 | Q28: 확정 | R28: 개발팀 | S28: 2 | T28: 2 | U28: 2 | V28: 전자서명 Canvas (센터측+고객측 양방향) 구현 (2026-03-13) | W28: 6 | X28: [헤더] 제목 [탭] 2개 (발송/이력) [포인트현황카드] 3열(잔여포인트/사용량/발신설정) [발송탭: 2열 xl기준] - [좌측: 수동발송폼] - 수신자선택: 그룹빠른선택5버튼 + 선택배지 + 대상검색모달 - 발송채널: 3라디오(알림톡8원/SMS·LMS/앱푸시무료) + 글자제한안내 - 예상비용: 단가×수신자 계산 - 메시지내용: textarea + 글자수게이지 + 변수삽입5버튼 - 예약발송: checkbox + datetime - [우측: 자동알림설정] - 고객관련 5토글 + 상품관련 4토글 [이력탭] DataTable 8컬럼 [모달] 수신자검색(체크리스트) / 미리보기(채널+내용+발송버튼) | Y28: 1:헤더 → 2:탭 → 3:포인트현황 → 4좌:수신자+채널+비용+메시지+예약 → 4우:자동알림 | Z28: page (2-column layout on send tab) | AA28: GNB '메시지 발송' 클릭 | AB28: 이력: 테이블 스켈레톤 발송처리: 버튼 로딩 | AC28: 수신자 없음: '검색 결과가 없습니다' 이력 없음: '발송 이력이 없습니다' | AD28: ≥1280px(xl): 발송2열 <1280px: 발송1열(폼→자동알림 순서) 포인트: md에서 col-span-2 | AE28: GNB 상단고정
A29: SCR-081 | B29: 구독 관리 | C29: Web | D29: /subscription | E29: 정기 구독 상품 관리. 자동 결제 현황 | F29: UI-113, UI-114 | G29: 구독 상품 목록, 결제 현황 대시보드, 구독 상세 모달 | H29: 테이블 + 카드 | J29: GNB 메뉴 | K29: 구독 상세 모달 | L29: 결제 실패 구독: 경고 배지 표시 | M29: 테이블 접근성 | N29: 카드 반응형 | Q29: 확정 | R29: 개발팀 | S29: 0 | T29: 2 | U29: 4 | W29: 2 | Y29: 현재 플랜 → 플랜 비교 → 결제 정보
A30: SCR-090 | B30: 설정 | C30: Web | D30: /settings | E30: 시스템 기본 설정. 센터 정보/영업시간/알림 등 | F30: UI-073, UI-074, UI-075 | G30: 탭 구성 (기본/알림/테마), 저장 버튼 | H30: 탭 + 폼 | J30: GNB 메뉴 | K30: SCR-091, SCR-092, SCR-093 | L30: 저장 실패: 토스트 에러 | M30: 탭 접근성 | N30: 폼 1열 | Q30: 확정 | R30: 개발팀 | S30: 5 | T30: 1 | U30: 0 | W30: 3 | X30: [헤더] 제목 + 취소 버튼 [Step Indicator] 5단계 프로그레스바 (원형번호/CheckCircle, 색상변화) [Step1: 회원선택] 검색input + DataTable(4컬럼) + 선택확인배지 [Step2: 상품선택] 2열(좌:탭4개+상품카드그리드 / 우:장바구니sticky) [Step3: 기간/금액] FormSection3개(계약기간2열/할인설정2열+미리보기/특약메모) + 안내배너 [Step4: 결제] 2열(좌:결제수단4버튼+금액요약 / 우:결제실행버튼) [Step5: 확인] 안내배너 + 계약요약카드(회원/조건/상품/금액) [하단] 이전/다음(또는 완료) 버튼 | Y30: 1:헤더 → 2:스텝인디케이터 → 3:스텝콘텐츠(1~5) → 4:이전/다음버튼 | Z30: page (5-step wizard) | AA30: GNB '전자계약' 클릭 | AB30: 회원/상품 조회: 테이블/카드 스켈레톤 Step전환: 애니메이션(animate-in) | AC30: 회원 없음: '검색 결과가 없습니다' 상품 없음: '등록된 상품이 없습니다' 장바구니 비어있음: '상품을 선택해주세요' | AD30: Step Indicator: min-w-[600px] 가로스크롤 메인: max-w-[1200px] Step2,4: lg에서 2열 | AE30: 하단 이전/다음 버튼 고정
A31: SCR-091 | B31: 권한 설정 | C31: Web | D31: /settings/permissions | E31: 역할별 메뉴/기능 권한 매트릭스 | F31: UI-076, UI-077, UI-078 | G31: 역할 탭, 권한 체크박스 매트릭스, 일괄 설정 | H31: 매트릭스 테이블 | J31: SCR-090, GNB | K31: SCR-090 | L31: 권한 충돌: 경고 표시 | M31: 체크박스 접근성 | N31: 테이블 가로스크롤 | Q31: 확정 | R31: 개발팀 | S31: 0 | T31: 2 | U31: 0 | W31: 3 | X31: [헤더] 제목 + 신규쿠폰생성 버튼 [섹션1: 통계카드] 4개 (전체/활성/총발급/사용완료) [탭] 2개 (쿠폰목록/발급이력) [쿠폰목록탭] SearchFilter(상태/유형) + DataTable 8컬럼(쿠폰명+코드배지/유형/할인값/사용현황 프로그레스바/유효기간+D-day/상태/등록일/메뉴) [발급이력탭] SearchFilter(발급일/쿠폰/상태) + DataTable 8컬럼 [모달] 쿠폰생성폼(쿠폰명/코드자동생성/유형라디오/한도/할인방식/유효기간/조건/메모) / 쿠폰발급(개인·그룹토글/수신자검색태그/수량/알림메시지) [다이얼로그] 삭제확인 | Y31: 1:헤더 → 2:통계카드4개 → 3:탭 → 4:검색/필터 → 5:테이블 | Z31: page | AA31: GNB '쿠폰 관리' 클릭 | AB31: 통계카드: 스켈레톤 테이블: 행 스켈레톤 | AC31: 쿠폰 없음: '등록된 쿠폰이 없습니다' 발급이력 없음: '발급 이력이 없습니다' | AD31: ≥768px(md): 통계카드4열 <768px: 통계카드1열 모달: max-w-2xl | AE31: GNB 상단고정
A32: SCR-092 | B32: 키오스크 설정 | C32: Web | D32: /settings/kiosk | E32: 키오스크 디스플레이/동작 설정 | F32: UI-115, UI-116 | G32: 미리보기, 로고 업로드, 동작 시나리오 설정 | H32: 미리보기 컴포넌트 | J32: SCR-090, GNB | K32: SCR-090 | L32: 이미지 용량 초과: '5MB 이하 파일만 업로드 가능합니다' | M32: 폼 접근성 | N32: 폼 1열 | Q32: 확정 | R32: 개발팀 | S32: 0 | T32: 1 | U32: 0 | V32: placeholder URL 제거, 빈 상태 UI 구현 (2026-03-13) | W32: 2 | X32: [헤더] 제목 + 엑셀다운로드 버튼 [섹션1: 통계카드] 4개 (발행/사용/잔여/이번달적립) [탭] 3개 (현황/이력/정책) [현황탭] SearchFilter(회원명/연락처+정렬/만료임박) + DataTable 9컬럼(아바타+회원명링크/연락처/적립/사용/잔여(bold)/최근적립일/만료예정일+D-day/메뉴) [이력탭] SearchFilter(회원명+기간/처리유형) + DataTable 8컬럼 [정책탭] 변경감지배너(amber) + FormSection3개(기본적립/사용제한/대상상품) + 저장버튼(isDirty) [모달] 수동조정(적립·차감토글/금액/사유/메모) [다이얼로그] 정책변경확인 | Y32: 1:헤더 → 2:통계카드4개 → 3:탭 → 4:탭콘텐츠 | Z32: page | AA32: GNB '마일리지 관리' 클릭 | AB32: 통계카드: 스켈레톤 테이블: 행 스켈레톤 | AC32: 현황 없음: '마일리지 데이터가 없습니다' 이력 없음: '이력이 없습니다' | AD32: ≥1024px(lg): 통계카드4열 <768px: 통계카드2열 정책탭: max-w-4xl | AE32: GNB 상단고정
A33: SCR-093 | B33: IoT 설정 | C33: Web | D33: /settings/iot | E33: 출입문/체성분 기기 연동 설정 | F33: UI-117, UI-118 | G33: 기기 목록, 연결 상태 표시, 테스트 버튼 | H33: 기기 연동 API | J33: SCR-090, GNB | K33: SCR-090 | L33: 연결 실패: '기기와 연결할 수 없습니다' + 재시도 | M33: 상태 아이콘 alt-text | N33: 테이블 반응형 | Q33: 확정 | R33: 개발팀 | S33: 0 | T33: 1 | U33: 0 | W33: 2 | X33: [헤더] 제목 + 신규등록 버튼 [섹션1: 통계카드] 3개 (전체/활성/미사용·해제·분실) [섹션2: SearchFilter] 카드번호/회원명 + 상태필터 [섹션3: DataTable] 9컬럼 (등록일/카드번호(mono)/회원명링크/유형배지/상태(dot)/발급일/사물함/메뉴) [모달] 카드등록(스캔UI pulse애니메이션 + 카드입력 + 사용자유형라디오 + 회원검색드롭다운 + 매핑확인카드 + 락커번호) / 이력조회(날짜범위+테이블) [다이얼로그] 삭제확인 | Y33: 1:헤더 → 2:통계카드3개 → 3:검색/필터 → 4:테이블 | Z33: page | AA33: GNB '밴드/카드' 클릭 | AB33: 통계카드: 스켈레톤 테이블: 행 스켈레톤 카드스캔: pulse 애니메이션 | AC33: 카드 없음: '등록된 카드가 없습니다' 이력 없음: '이력이 없습니다' | AD33: ≥768px(md): 통계카드3열 <768px: 통계카드1열 모달: max-w-[560px] | AE33: GNB 상단고정
A34: SCR-094 | B34: 지점 관리 | C34: Web | D34: /branches | E34: 지점 CRUD. 멀티테넌트 관리 | F34: UI-079, UI-080, UI-081 | G34: 지점 카드/테이블 뷰 전환, 지점 추가 모달, 데이터 초기화 | H34: 카드/테이블 토글 | J34: GNB 메뉴 (최고관리자만) | K34: 지점 상세 모달 | L34: 지점 삭제 시 데이터 존재: '소속 데이터가 있어 삭제 불가' | M34: 카드/테이블 접근성 | N34: 카드 반응형 | Q34: 확정 | R34: 개발팀 | S34: 0 | T34: 2 | U34: 1 | W34: 3 | X34: [헤더] 제목 + 연결상태배지(Wifi아이콘) + 설정저장 버튼 [에러배너] 오프라인 시 (조건부) [탭] 4개 (기본설정/화면설정/TTS설정/출입규칙) [기본설정탭] 2열(좌:FormSection(키오스크타입/입장방식/시스템설정) / 우:KioskPreview 폰프레임목업) [화면설정탭] FormSection(로고/배경/테마색상/환영문구/공지·날씨/광고배너) [TTS설정탭] FormSection(안내메시지) + 테이블(이벤트/메시지/Play재생버튼) [출입규칙탭] FormSection(출입시간/만료회원/중복체크인) | Y34: 1:헤더+상태 → 2:에러배너(조건부) → 3:탭 → 4:탭콘텐츠 | Z34: page | AA34: GNB '키오스크' 클릭 | AB34: 설정 로딩: 전체 스켈레톤 저장: 버튼 로딩 + toast | AC34: 없음 (설정 페이지, 기본값 존재) | AD34: 기본설정: lg에서 3열(좌2:우1 preview) <1024px: 1열(preview 아래로) 모바일: 체크인방식 숨김 | AE34: GNB 상단고정
A35: SCR-000 | B35: 공통 레이아웃 | C35: Web | D35: / | E35: 전체 화면 공통 레이아웃. AppHeader(GNB) + AppSidebar + 콘텐츠 영역. 사이드바 접기/펼치기, 반응형 | F35: UI-201,UI-202,UI-203 | G35: 사이드바 접기/펼치기 시 콘텐츠 영역 자동 조정, 반응형 브레이크포인트(1024px/768px) | Q35: 확정 | R35: 개발팀 | S35: 0 | T35: 0 | U35: 0 | W35: 0 | X35: [GNB] 상단 고정 헤더 (h:56px) [Sidebar] 좌측 사이드바 (w:240px, 접힌 상태 60px) [Content] 우측 메인 콘텐츠 영역 (flex-1, p-6) | Y35: 1:GNB → 2:Sidebar → 3:Content | Z35: layout (모든 페이지 공통 래퍼) | AA35: 로그인 성공 후 | AB35: N/A | AC35: N/A | AD35: ≥1024px: 사이드바 240px + 콘텐츠 768~1023px: 사이드바 60px(아이콘만) <768px: 사이드바 숨김, 햄버거 메뉴 | AE35: GNB 상단 고정, Sidebar 좌측 고정
A36: SCR-ERR | B36: 404 에러 | C36: Web | D36: /* | E36: 존재하지 않는 경로 접근 시 표시. 메인으로 돌아가기 버튼 | F36: (없음) | G36: 메인으로 돌아가기 버튼 클릭→대시보드(/)로 이동 | Q36: 확정 | R36: 개발팀 | S36: 0 | T36: 2 | U36: 0 | W36: 0 | X36: [중앙] 404 아이콘 + "페이지를 찾을 수 없습니다" 메시지 + 홈으로 돌아가기 버튼 | Y36: 1:404 아이콘 → 2:에러 메시지 → 3:돌아가기 버튼 | Z36: page (사이드바 없음) | AA36: 잘못된 URL 직접 접근 | AB36: N/A | AC36: N/A | AD36: 반응형 중앙 정렬 | AE36: 없음
A37: SCR-001-E | B37: 로그인 - 에러 상태 | C37: Web | D37: /login | E37: 로그인 실패 시 에러 메시지 표시 상태. 빨간 배경 에러 박스 활성 | F37: (해당 없음) | G37: 에러 메시지 닫기, 재입력 시 에러 초기화 | J37: SCR-001 로그인 실패 시 | L37: 계정 잠금: '5회 실패로 잠겼습니다. 30분 후 다시 시도하세요' | Q37: 확정 | S37: 0 | T37: 0 | U37: 0 | W37: 0 | X37: SCR-001과 동일 | Y37: 로고 → 이메일 입력 → 비밀번호 입력 → 로그인 버튼 | Z37: state (에러 상태) | AA37: 로그인 실패 시 | AB37: 없음 | AC37: 없음 | AD37: SCR-001과 동일 | AE37: 없음
A38: SCR-001-L | B38: 로그인 - 로딩 상태 | C38: Web | D38: /login | E38: 로그인 버튼 클릭 후 인증 처리 중 상태. 버튼 비활성 + Loader2 스핀 | F38: (해당 없음) | G38: 로딩 중 입력 비활성, ESC 취소 불가 | J38: SCR-001 로그인 버튼 클릭 | L38: 타임아웃: 10초 후 자동 실패 처리 | Q38: 확정 | S38: 0 | T38: 0 | U38: 0 | W38: 0 | X38: SCR-001과 동일 | Y38: 스켈레톤 UI | Z38: state (로딩 상태) | AA38: 로그인 버튼 클릭 | AB38: 로그인 버튼: Loader2 스핀 + '로그인 중...' | AC38: 없음 | AD38: SCR-001과 동일 | AE38: 없음
A39: SCR-001-M | B39: 로그인 - 모바일 뷰 | C39: Mobile | D39: /login | E39: 모바일 브라우저에서의 로그인 화면. 풀스크린 카드, 키보드 대응 | F39: (해당 없음) | G39: 키보드 올라올 때 뷰포트 조정 | I39: 키보드 올라올 때 스크롤 가능 | J39: URL 직접 접근 | L39: SCR-001과 동일 | M39: 터치 대상 44px 이상 | N39: <768px 풀너비 | Q39: 확정 | S39: 0 | T39: 0 | U39: 0 | W39: 0 | X39: 풀스크린 카드, padding 축소 | Y39: 로고 → 이메일 입력 → 비밀번호 입력 → 로그인 버튼 | Z39: page (모바일) | AA39: URL 직접접근 | AB39: SCR-001과 동일 | AC39: SCR-001과 동일 | AD39: 풀너비, gap 축소, 로고 축소 | AE39: 없음
A40: SCR-002-L | B40: 대시보드 - 로딩 상태 | C40: Web | D40: / | E40: 대시보드 초기 로딩 시 스켈레톤 UI 표시 상태 | F40: (해당 없음) | G40: 스켈레톤 애니메이션, 수동 갱신 버튼 비활성 | J40: SCR-001 로그인 성공 후 | L40: 5초 후 로딩 실패 시 에러 전환 | Q40: 확정 | S40: 0 | T40: 0 | U40: 0 | W40: 0 | X40: SCR-002와 동일 (스켈레톤) | Y40: 스켈레톤 UI | Z40: state (로딩) | AA40: 페이지 진입 | AB40: 통계카드 스켈레톤 + 차트 스피너 + 리스트 행 스켈레톤 | AC40: 없음 | AD40: SCR-002와 동일 | AE40: GNB 상단고정
A41: SCR-002-E | B41: 대시보드 - 에러 상태 | C41: Web | D41: / | E41: 데이터 로딩 실패 시 각 섹션별 독립 에러 표시 | F41: (해당 없음) | G41: 재시도 버튼 클릭 시 해당 섹션만 재로딩 | J41: SCR-002 데이터 로딩 실패 | L41: 각 섹션별 '데이터를 불러올 수 없습니다' + 재시도 버튼 | Q41: 확정 | S41: 0 | T41: 0 | U41: 0 | W41: 0 | X41: SCR-002와 동일 | Y41: 통계 카드 → 차트 영역 → 최근 활동 | Z41: state (에러) | AA41: 데이터 로딩 실패 | AB41: 없음 | AC41: 없음 | AD41: SCR-002와 동일 | AE41: GNB 상단고정
A42: SCR-002-EM | B42: 대시보드 - 빈 상태 | C42: Web | D42: / | E42: 신규 지점/데이터 없음 시 Empty State UI 표시 | F42: (해당 없음) | G42: 회원 등록/상품 등록 바로가기 버튼 | J42: SCR-001 로그인 (신규 지점) | L42: 전체: '아직 데이터가 없습니다' 안내 + 시작하기 가이드 | Q42: 확정 | S42: 0 | T42: 0 | U42: 0 | W42: 0 | X42: SCR-002와 동일 | Y42: 빈 상태 아이콘 → 안내 문구 → CTA 버튼 | Z42: state (빈 상태) | AA42: 신규 지점 로그인 | AB42: 통계: 0 표시 모든 리스트: '데이터가 없습니다' | AC42: 없음 | AD42: SCR-002와 동일 | AE42: GNB 상단고정
A43: SCR-002-M | B43: 대시보드 - 모바일 뷰 | C43: Mobile | D43: / | E43: 모바일 브라우저 대시보드. 카드 1열, 차트 축소, 리스트 축소 | F43: (해당 없음) | G43: 스와이프로 통계카드 넘기기, 탭으로 차트 전환 | I43: 터치 스와이프 대응 | J43: GNB 메뉴 | L43: SCR-002와 동일 | M43: 터치 대상 44px | N43: <768px 레이아웃 | Q43: 확정 | S43: 0 | T43: 1 | U43: 0 | W43: 0 | X43: 카드 2열→1열, 차트 1열, 리스트 1열 | Y43: 통계 카드 → 차트 영역 → 최근 활동 | Z43: page (모바일) | AA43: GNB 메뉴 | AB43: SCR-002와 동일 | AC43: SCR-002와 동일 | AD43: 카드2열, 차트1열, 리스트1열 | AE43: GNB 상단고정
A44: SCR-010-F | B44: 회원 목록 - 상태필터 활성 | C44: Web | D44: /members | E44: 상태필터(활성/만료/미등록 등) 선택 시 필터링된 결과 표시 | F44: (해당 없음) | G44: 필터 탭 전환, 검색+필터 조합, 필터 초기화 버튼 | J44: SCR-010 상태필터 클릭 | L44: 필터 결과 0건 시 EmptyState 표시 | Q44: 확정 | S44: 0 | T44: 0 | U44: 0 | W44: 0 | X44: SCR-010과 동일 | Y44: 검색/필터 바 → 데이터 테이블 → 페이지네이션 | Z44: state (필터 활성) | AA44: 상태필터 탭 클릭 | AB44: SCR-010과 동일 | AC44: 필터 결과 0건: '조건에 맞는 회원이 없습니다' | AD44: SCR-010과 동일 | AE44: GNB + 벌크액션바
A45: SCR-010-S | B45: 회원 목록 - 검색결과 | C45: Web | D45: /members | E45: 검색어 입력 후 실시간 검색 결과 표시. 300ms debounce | F45: (해당 없음) | G45: 실시간 검색, 검색어 하이라이트, 검색 초기화 X버튼 | J45: SCR-010 검색창 입력 | L45: 결과 없음: '검색 결과가 없습니다' + 검색어 확인 안내 | Q45: 확정 | S45: 0 | T45: 0 | U45: 0 | W45: 0 | X45: SCR-010과 동일 | Y45: 검색/필터 바 → 데이터 테이블 → 페이지네이션 | Z45: state (검색) | AA45: 검색창 입력 | AB45: 검색 중: 인풋 우측 스피너 | AC45: 검색 결과 없음: EmptyState | AD45: SCR-010과 동일 | AE45: GNB
A46: SCR-010-EM | B46: 회원 목록 - 빈 상태 | C46: Web | D46: /members | E46: 회원 0명일 때 EmptyState 표시. 회원 등록 바로가기 버튼 | F46: (해당 없음) | G46: 회원 등록 버튼 → SCR-012 이동 | J46: SCR-010 (데이터 0건) | L46: '등록된 회원이 없습니다' + '회원을 등록해보세요' CTA | Q46: 확정 | S46: 0 | T46: 0 | U46: 0 | W46: 0 | X46: SCR-010과 동일 | Y46: 빈 상태 아이콘 → 안내 문구 → CTA 버튼 | Z46: state (빈 상태) | AA46: 페이지 진입 (회원 0건) | AB46: 통계카드: 0 | AC46: '등록된 회원이 없습니다' EmptyState | AD46: SCR-010과 동일 | AE46: GNB
A47: SCR-010-BK | B47: 회원 목록 - 벌크액션바 | C47: Web | D47: /members | E47: 체크박스로 회원 다중 선택 시 벌크 액션바 표시 (상태변경/메시지발송 등) | F47: (해당 없음) | G47: 전체선택, 선택 해제, 상태 일괄변경, 메시지 일괄발송 | J47: SCR-010 체크박스 선택 | L47: 1000명 이상 선택 시 경고 | Q47: 확정 | S47: 0 | T47: 1 | U47: 0 | W47: 0 | X47: SCR-010과 동일 + 벌크액션바 | Y47: 검색/필터 바 → 데이터 테이블 → 페이지네이션 | Z47: state (벌크 선택) | AA47: 체크박스 1개 이상 선택 | AB47: SCR-010과 동일 | AC47: SCR-010과 동일 | AD47: SCR-010과 동일 | AE47: 벌크액션바: 테이블 상단 고정
A48: SCR-010-L | B48: 회원 목록 - 로딩 상태 | C48: Web | D48: /members | E48: 회원 목록 초기 로딩 시 스켈레톤 UI | F48: (해당 없음) | G48: 스켈레톤 행 5줄 표시 | J48: SCR-010 페이지 진입 | L48: 5초 후 타임아웃 시 에러 전환 | Q48: 확정 | S48: 0 | T48: 0 | U48: 0 | W48: 0 | X48: SCR-010과 동일 (스켈레톤) | Y48: 스켈레톤 UI | Z48: state (로딩) | AA48: 페이지 진입 | AB48: 통계카드 스켈레톤 + 테이블 행 스켈레톤 5줄 | AC48: 없음 | AD48: SCR-010과 동일 | AE48: GNB
A49: SCR-010-E | B49: 회원 목록 - 에러 상태 | C49: Web | D49: /members | E49: 회원 목록 로딩 실패 시 에러 표시 + 재시도 | F49: (해당 없음) | G49: 재시도 버튼 클릭 시 목록 재조회 | J49: SCR-010 데이터 로딩 실패 | L49: '데이터를 불러올 수 없습니다' + 재시도 버튼 | Q49: 확정 | S49: 0 | T49: 0 | U49: 0 | W49: 0 | X49: SCR-010과 동일 | Y49: 검색/필터 바 → 데이터 테이블 → 페이지네이션 | Z49: state (에러) | AA49: 데이터 로딩 실패 | AB49: 없음 | AC49: 없음 | AD49: SCR-010과 동일 | AE49: GNB
A50: SCR-010-M | B50: 회원 목록 - 모바일 뷰 | C50: Mobile | D50: /members | E50: 모바일 회원 목록. 카드형 리스트, 검색 상단 고정 | F50: (해당 없음) | G50: 스와이프 동작, 무한스크롤, 검색 고정 | I50: 터치 대응, 카드형 리스트 | J50: GNB 메뉴 | L50: SCR-010과 동일 | M50: 터치 대상 44px | N50: 카드형 리스트 | Q50: 확정 | S50: 0 | T50: 1 | U50: 0 | W50: 0 | X50: 카드형 리스트 레이아웃 | Y50: 검색/필터 바 → 데이터 테이블 → 페이지네이션 | Z50: page (모바일) | AA50: GNB 메뉴 | AB50: SCR-010과 동일 | AC50: SCR-010과 동일 | AD50: 카드형, 검색 상단고정 | AE50: GNB + 검색바
A51: SCR-011-T1 | B51: 회원 상세 - 기본정보 탭 | C51: Web | D51: /members/detail | E51: 기본정보 탭 활성 상태. 이름/연락처/성별/생년월일/상태/메모 표시 | F51: (해당 없음) | G51: 정보 인라인 수정, 프로필 사진 클릭 시 확대 | J51: SCR-011 기본정보 탭 클릭 | L51: 필수 정보 누락 시 경고 | Q51: 확정 | S51: 0 | T51: 1 | U51: 0 | W51: 0 | X51: SCR-011과 동일 + 기본정보 영역 | Y51: 프로필 헤더 → 탭 네비게이션 → 탭 콘텐츠 | Z51: state (기본정보 탭) | AA51: 탭 클릭 / 기본 진입 | AB51: 탭 콘텐츠 로딩 스피너 | AC51: 정보 없음: '-' 표시 | AD51: SCR-011과 동일 | AE51: GNB + 탭네비 sticky
A52: SCR-011-T2 | B52: 회원 상세 - 계약현황 탭 | C52: Web | D52: /members/detail | E52: 계약현황(이용권/수강권) 탭. 활성/만료 이용권 목록 + 잔여일 표시 | F52: (해당 없음) | G52: 이용권 상세 펼치기, 환불 버튼, 연장 버튼 | J52: SCR-011 계약현황 탭 클릭 | L52: 이용권 없음: '등록된 이용권이 없습니다' | Q52: 확정 | S52: 0 | T52: 0 | U52: 0 | W52: 0 | X52: SCR-011과 동일 + 이용권 목록 | Y52: 프로필 헤더 → 탭 네비게이션 → 탭 콘텐츠 | Z52: state (계약현황 탭) | AA52: 계약현황 탭 클릭 | AB52: 탭 콘텐츠 lazy load | AC52: 이용권 없음: EmptyState | AD52: SCR-011과 동일 | AE52: GNB + 탭네비 sticky
A53: SCR-011-T3 | B53: 회원 상세 - 출석이력 탭 | C53: Web | D53: /members/detail | E53: 출석이력 탭. 캘린더 히트맵 + 출석 로그 테이블 | F53: (해당 없음) | G53: 캘린더 날짜 클릭 시 상세, 월 네비게이션 | J53: SCR-011 출석 탭 클릭 | L53: 출석 없음: '출석 기록이 없습니다' | Q53: 확정 | S53: 0 | T53: 0 | U53: 0 | W53: 0 | X53: SCR-011과 동일 + 캘린더 + 테이블 | Y53: 프로필 헤더 → 탭 네비게이션 → 탭 콘텐츠 | Z53: state (출석 탭) | AA53: 출석 탭 클릭 | AB53: 캘린더/테이블 로딩 | AC53: 출석 없음: EmptyState | AD53: SCR-011과 동일 | AE53: GNB + 탭네비 sticky
A54: SCR-011-T4 | B54: 회원 상세 - 체성분 탭 | C54: Web | D54: /members/detail | E54: 체성분 탭. InBody 기록 차트 + 측정 이력 테이블 | F54: (해당 없음) | G54: 차트 기간 필터, 측정값 비교, 새 측정 기록 추가 | J54: SCR-011 체성분 탭 클릭 | L54: 측정 없음: '체성분 측정 기록이 없습니다' | Q54: 확정 | S54: 0 | T54: 0 | U54: 0 | W54: 0 | X54: SCR-011과 동일 + 차트 + 테이블 | Y54: 프로필 헤더 → 탭 네비게이션 → 탭 콘텐츠 | Z54: state (체성분 탭) | AA54: 체성분 탭 클릭 | AB54: 차트/테이블 로딩 | AC54: 측정 없음: EmptyState | AD54: SCR-011과 동일 | AE54: GNB + 탭네비 sticky
A55: SCR-011-T5 | B55: 회원 상세 - 결제내역 탭 | C55: Web | D55: /members/detail | E55: 결제내역 탭. 결제/환불 이력 테이블 + 미수금 표시 | F55: (해당 없음) | G55: 결제상세 펼치기, 영수증 출력, 환불 처리 | J55: SCR-011 결제내역 탭 클릭 | L55: 결제 없음: '결제 내역이 없습니다' | Q55: 확정 | S55: 0 | T55: 0 | U55: 0 | W55: 0 | X55: SCR-011과 동일 + 결제 테이블 | Y55: 프로필 헤더 → 탭 네비게이션 → 탭 콘텐츠 | Z55: state (결제 탭) | AA55: 결제내역 탭 클릭 | AB55: 테이블 로딩 | AC55: 결제 없음: EmptyState | AD55: SCR-011과 동일 | AE55: GNB + 탭네비 sticky
A56: SCR-011-T6 | B56: 회원 상세 - 커뮤니케이션 탭 | C56: Web | D56: /members/detail | E56: 커뮤니케이션 탭. 상담기록/메시지발송이력/메모 관리 | F56: (해당 없음) | G56: 상담기록 추가, 메시지 발송, 메모 작성 | J56: SCR-011 커뮤니케이션 탭 클릭 | L56: 기록 없음: '커뮤니케이션 기록이 없습니다' | Q56: 확정 | S56: 0 | T56: 1 | U56: 0 | W56: 0 | X56: SCR-011과 동일 + 기록 목록 | Y56: 프로필 헤더 → 탭 네비게이션 → 탭 콘텐츠 | Z56: state (커뮤니케이션 탭) | AA56: 커뮤니케이션 탭 클릭 | AB56: 기록 목록 로딩 | AC56: 기록 없음: EmptyState | AD56: SCR-011과 동일 | AE56: GNB + 탭네비 sticky
A57: SCR-011-RF | B57: 회원 상세 - 환불 모달 | C57: Web | D57: /members/detail | E57: 이용권/결제 환불 처리 모달. 환불금액 계산 + 사유 입력 | F57: (해당 없음) | G57: 환불 금액 자동계산, 사유 필수입력, 환불 확인 더블체크 | J57: SCR-011 환불 버튼 클릭 | L57: 환불 불가: 이미 환불됨/기간 초과 안내 | Q57: 확정 | S57: 0 | T57: 0 | U57: 0 | W57: 0 | X57: 오버레이 모달 (max-w-[500px]) | Y57: 모달 헤더 → 입력 폼 → 하단 버튼 | Z57: modal | AA57: 환불 버튼 클릭 | AB57: 환불 처리 중 스피너 | AC57: 없음 | AD57: 모달 내부 스크롤 | AE57: 모달 오버레이 배경
A58: SCR-011-DEL | B58: 회원 상세 - 삭제 확인 모달 | C58: Web | D58: /members/detail | E58: 회원 삭제(비활성화) 확인 다이얼로그. 경고 메시지 + 확인/취소 | F58: (해당 없음) | G58: 삭제 확인 시 soft delete 처리, 목록으로 이동 | J58: SCR-011 삭제 버튼 클릭 | L58: 삭제 실패: 에러 toast | Q58: 확정 | S58: 0 | T58: 0 | U58: 0 | W58: 0 | X58: AlertDialog 중앙 | Y58: 모달 헤더 → 입력 폼 → 하단 버튼 | Z58: dialog | AA58: 삭제 버튼 클릭 | AB58: 삭제 처리 중 스피너 | AC58: 없음 | AD58: 고정 너비 다이얼로그 | AE58: 오버레이 배경
A59: SCR-011-L | B59: 회원 상세 - 로딩 상태 | C59: Web | D59: /members/detail | E59: 회원 상세 초기 진입 시 프로필 카드 + 탭 콘텐츠 스켈레톤 | F59: (해당 없음) | G59: 스켈레톤 표시 | J59: SCR-010 회원 클릭 | L59: 5초 후 타임아웃 | Q59: 확정 | S59: 0 | T59: 0 | U59: 0 | W59: 0 | X59: SCR-011과 동일 (스켈레톤) | Y59: 스켈레톤 UI | Z59: state (로딩) | AA59: 페이지 진입 | AB59: 프로필 카드 스켈레톤 + 탭 콘텐츠 스피너 | AC59: 없음 | AD59: SCR-011과 동일 | AE59: GNB
A60: SCR-011-404 | B60: 회원 상세 - 404 상태 | C60: Web | D60: /members/detail | E60: 존재하지 않는 회원 ID 접근 시 404 표시 | F60: (해당 없음) | G60: 목록으로 돌아가기 버튼 | J60: 잘못된 회원 ID로 접근 | L60: '회원을 찾을 수 없습니다' + 목록 돌아가기 | Q60: 확정 | S60: 0 | T60: 0 | U60: 0 | W60: 0 | X60: 404 EmptyState 중앙 | Y60: 프로필 헤더 → 탭 네비게이션 → 탭 콘텐츠 | Z60: state (404) | AA60: 잘못된 ID 접근 | AB60: 없음 | AC60: '회원을 찾을 수 없습니다' | AD60: SCR-011과 동일 | AE60: GNB
A61: SCR-011-M | B61: 회원 상세 - 모바일 뷰 | C61: Mobile | D61: /members/detail | E61: 모바일 회원 상세. 프로필 축소, 탭 세로배치 | F61: (해당 없음) | G61: 탭 스와이프 전환 | I61: 탭 스와이프, 프로필 축소 | J61: 회원 목록 카드 클릭 | L61: SCR-011과 동일 | M61: 터치 44px | N61: <768px | Q61: 확정 | S61: 0 | T61: 0 | U61: 0 | W61: 0 | X61: 프로필 축소 + 탭 세로배치 | Y61: 프로필 헤더 → 탭 네비게이션 → 탭 콘텐츠 | Z61: page (모바일) | AA61: 회원 카드 클릭 | AB61: SCR-011과 동일 | AC61: SCR-011과 동일 | AD61: 프로필 축소, 탭 세로 | AE61: GNB
A62: SCR-012-V | B62: 회원 등록 - 유효성 에러 | C62: Web | D62: /members/new | E62: 폼 유효성 검사 실패 시 각 필드별 에러 메시지 표시 | F62: (해당 없음) | G62: 에러 필드 포커스, 스크롤 이동, 에러 메시지 표시 | J62: SCR-012 저장 버튼 클릭 | L62: 필수 필드 미입력 시 에러, 연락처 형식 에러 | Q62: 확정 | S62: 0 | T62: 1 | U62: 0 | W62: 0 | X62: SCR-012와 동일 | Y62: 폼 섹션 → 입력 필드 → 저장/취소 버튼 | Z62: state (유효성 에러) | AA62: 저장 클릭 (유효성 실패) | AB62: SCR-012와 동일 | AC62: 없음 | AD62: SCR-012와 동일 | AE62: GNB
A63: SCR-012-L | B63: 회원 등록 - 저장 중 | C63: Web | D63: /members/new | E63: 회원 등록 API 호출 중 로딩 상태. 버튼 비활성 + 스피너 | F63: (해당 없음) | G63: 저장 버튼 비활성, 폼 수정 불가 | J63: SCR-012 저장 클릭 | L63: 저장 실패 시 에러 toast | Q63: 확정 | S63: 0 | T63: 0 | U63: 0 | W63: 0 | X63: SCR-012와 동일 | Y63: 폼 섹션 → 입력 필드 → 저장/취소 버튼 | Z63: state (저장 중) | AA63: 저장 버튼 클릭 | AB63: 저장 버튼: 스피너 + '등록 중...' | AC63: 없음 | AD63: SCR-012와 동일 | AE63: GNB
A64: SCR-012-M | B64: 회원 등록 - 모바일 뷰 | C64: Mobile | D64: /members/new | E64: 모바일 회원 등록 폼. 풀너비 입력, 세로 레이아웃 | F64: (해당 없음) | G64: 키보드 대응, 스크롤 | I64: 키보드 올라올 때 뷰포트 조정 | J64: SCR-010 회원추가 버튼 | L64: SCR-012와 동일 | M64: 터치 44px | N64: <768px | Q64: 확정 | S64: 0 | T64: 0 | U64: 0 | W64: 0 | X64: 풀너비 세로 레이아웃 | Y64: 폼 섹션 → 입력 필드 → 저장/취소 버튼 | Z64: page (모바일) | AA64: 회원추가 버튼 | AB64: SCR-012와 동일 | AC64: SCR-012와 동일 | AD64: 풀너비 입력, 세로 레이아웃 | AE64: GNB
A65: SCR-013-V | B65: 회원 수정 - 유효성 에러 | C65: Web | D65: /members/edit | E65: 수정 폼 유효성 검사 실패 상태 | F65: (해당 없음) | G65: 에러 필드 포커스, 에러 메시지 표시 | J65: SCR-013 저장 클릭 | L65: 필수 필드 에러, 연락처 중복 체크 | Q65: 확정 | S65: 0 | T65: 0 | U65: 0 | W65: 0 | X65: SCR-013과 동일 | Y65: 폼 섹션 → 입력 필드 → 저장/취소 버튼 | Z65: state (유효성 에러) | AA65: 저장 클릭 (유효성 실패) | AB65: SCR-013과 동일 | AC65: 없음 | AD65: SCR-013과 동일 | AE65: GNB
A66: SCR-013-L | B66: 회원 수정 - 저장 중 | C66: Web | D66: /members/edit | E66: 회원 수정 API 호출 중 로딩 상태 | F66: (해당 없음) | G66: 저장 버튼 비활성 | J66: SCR-013 저장 클릭 | L66: 저장 실패 시 에러 toast | Q66: 확정 | S66: 0 | T66: 0 | U66: 0 | W66: 0 | X66: SCR-013과 동일 | Y66: 폼 섹션 → 입력 필드 → 저장/취소 버튼 | Z66: state (저장 중) | AA66: 저장 클릭 | AB66: 저장 버튼: 스피너 + '수정 중...' | AC66: 없음 | AD66: SCR-013과 동일 | AE66: GNB
A67: SCR-020-L | B67: 출석 관리 - 로딩 상태 | C67: Web | D67: /attendance | E67: 출석 목록 로딩 시 스켈레톤 표시 | F67: (해당 없음) | G67: 스켈레톤 행 표시 | J67: SCR-020 페이지 진입 | L67: 로딩 실패 시 에러 전환 | Q67: 확정 | S67: 0 | T67: 0 | U67: 0 | W67: 0 | X67: SCR-020과 동일 (스켈레톤) | Y67: 스켈레톤 UI | Z67: state (로딩) | AA67: 페이지 진입 | AB67: 통계카드 스켈레톤 + 테이블 스켈레톤 | AC67: 없음 | AD67: SCR-020과 동일 | AE67: GNB
A68: SCR-020-EM | B68: 출석 관리 - 빈 상태 | C68: Web | D68: /attendance | E68: 오늘 출석 0건일 때 EmptyState 표시 | F68: (해당 없음) | G68: 수동 체크인 버튼 | J68: SCR-020 (출석 0건) | L68: '오늘 출석한 회원이 없습니다' | Q68: 확정 | S68: 0 | T68: 1 | U68: 0 | W68: 0 | X68: SCR-020과 동일 | Y68: 빈 상태 아이콘 → 안내 문구 → CTA 버튼 | Z68: state (빈 상태) | AA68: 페이지 진입 (출석 0건) | AB68: 없음 | AC68: '오늘 출석한 회원이 없습니다' EmptyState | AD68: SCR-020과 동일 | AE68: GNB
A69: SCR-020-E | B69: 출석 관리 - 에러 상태 | C69: Web | D69: /attendance | E69: 출석 데이터 로딩 실패 시 에러 표시 | F69: (해당 없음) | G69: 재시도 버튼 | J69: SCR-020 로딩 실패 | L69: '데이터를 불러올 수 없습니다' + 재시도 | Q69: 확정 | S69: 0 | T69: 1 | U69: 0 | W69: 0 | X69: SCR-020과 동일 | Y69: 날짜 선택 → 출석 목록 → 수동 체크인 | Z69: state (에러) | AA69: 로딩 실패 | AB69: 없음 | AC69: 없음 | AD69: SCR-020과 동일 | AE69: GNB
A70: SCR-020-CI | B70: 출석 관리 - 수동 체크인 모달 | C70: Web | D70: /attendance | E70: 수동 체크인 모달. 회원 검색 + 체크인 유형 선택 | F70: (해당 없음) | G70: 회원 검색 자동완성, 유형 선택(정규/PT/GX/수동) | J70: SCR-020 체크인 버튼 클릭 | L70: 회원 미선택 시 에러 | Q70: 확정 | S70: 0 | T70: 4 | U70: 0 | W70: 0 | X70: 오버레이 모달 | Y70: 모달 헤더 → 입력 폼 → 하단 버튼 | Z70: modal | AA70: 체크인 버튼 클릭 | AB70: 체크인 처리 중 스피너 | AC70: 없음 | AD70: 모달 내부 스크롤 | AE70: 모달 오버레이
A71: SCR-020-M | B71: 출석 관리 - 모바일 뷰 | C71: Mobile | D71: /attendance | E71: 모바일 출석 관리. 카드형 출석 목록 | F71: (해당 없음) | G71: 스와이프 체크아웃 | I71: 터치 대응 | J71: GNB 메뉴 | L71: SCR-020과 동일 | M71: 터치 44px | N71: <768px | Q71: 확정 | S71: 0 | T71: 1 | U71: 0 | W71: 0 | X71: 카드형 리스트 | Y71: 날짜 선택 → 출석 목록 → 수동 체크인 | Z71: page (모바일) | AA71: GNB 메뉴 | AB71: SCR-020과 동일 | AC71: SCR-020과 동일 | AD71: 카드형 리스트 | AE71: GNB
A72: SCR-021-L | B72: 캘린더 - 로딩 상태 | C72: Web | D72: /calendar | E72: 캘린더 일정 로딩 중 스켈레톤 | F72: (해당 없음) | G72: 캘린더 셀 스켈레톤 | J72: SCR-021 진입/월 전환 | L72: 로딩 실패 시 에러 | Q72: 확정 | S72: 0 | T72: 0 | U72: 0 | W72: 0 | X72: SCR-021과 동일 (스켈레톤) | Y72: 스켈레톤 UI | Z72: state (로딩) | AA72: 페이지 진입/월 전환 | AB72: 캘린더 셀 스켈레톤 | AC72: 없음 | AD72: SCR-021과 동일 | AE72: GNB
A73: SCR-021-EM | B73: 캘린더 - 빈 상태 | C73: Web | D73: /calendar | E73: 선택 월에 일정 0건일 때 | F73: (해당 없음) | G73: 일정 추가 버튼 | J73: SCR-021 (일정 0건) | L73: '등록된 일정이 없습니다' | Q73: 확정 | S73: 0 | T73: 1 | U73: 0 | W73: 0 | X73: SCR-021과 동일 | Y73: 빈 상태 아이콘 → 안내 문구 → CTA 버튼 | Z73: state (빈 상태) | AA73: 일정 없는 월 | AB73: 없음 | AC73: '등록된 일정이 없습니다' | AD73: SCR-021과 동일 | AE73: GNB
A74: SCR-021-ADD | B74: 캘린더 - 일정 추가 모달 | C74: Web | D74: /calendar | E74: 새 일정/수업 추가 모달. 날짜/시간/유형/회원 선택 | F74: (해당 없음) | G74: 날짜/시간 피커, 회원 검색, 반복 설정 | J74: SCR-021 일정 추가 클릭 | L74: 시간 겹침 경고 | Q74: 확정 | S74: 0 | T74: 1 | U74: 0 | W74: 0 | X74: 오버레이 모달 | Y74: 모달 헤더 → 입력 폼 → 하단 버튼 | Z74: modal | AA74: 일정 추가 클릭 | AB74: 저장 중 스피너 | AC74: 없음 | AD74: 모달 내부 스크롤 | AE74: 모달 오버레이
A75: SCR-021-M | B75: 캘린더 - 모바일 뷰 | C75: Mobile | D75: /calendar | E75: 모바일 캘린더. 리스트 뷰 기본, 캘린더 접기/펼치기 | F75: (해당 없음) | G75: 캘린더 토글, 날짜 스와이프 | I75: 스와이프 날짜 이동 | J75: GNB 메뉴 | L75: SCR-021과 동일 | M75: 터치 44px | N75: <768px | Q75: 확정 | S75: 0 | T75: 1 | U75: 0 | W75: 0 | X75: 리스트 뷰 + 접이식 캘린더 | Y75: 캘린더 헤더 → 캘린더 그리드 → 일정 목록 | Z75: page (모바일) | AA75: GNB 메뉴 | AB75: SCR-021과 동일 | AC75: SCR-021과 동일 | AD75: 리스트 뷰 기본 | AE75: GNB
A76: SCR-030-L | B76: 매출 관리 - 로딩 상태 | C76: Web | D76: /sales | E76: 매출 데이터 로딩 중 스켈레톤 | F76: (해당 없음) | G76: 스켈레톤 표시 | J76: SCR-030 진입 | L76: 로딩 실패 시 에러 | Q76: 확정 | S76: 0 | T76: 0 | U76: 0 | W76: 0 | X76: SCR-030과 동일 (스켈레톤) | Y76: 스켈레톤 UI | Z76: state (로딩) | AA76: 페이지 진입 | AB76: 통계 스켈레톤 + 테이블 스켈레톤 | AC76: 없음 | AD76: SCR-030과 동일 | AE76: GNB
A77: SCR-030-EM | B77: 매출 관리 - 빈 상태 | C77: Web | D77: /sales | E77: 매출 0건 시 EmptyState | F77: (해당 없음) | G77: 매출 등록 바로가기 | J77: SCR-030 (매출 0건) | L77: '등록된 매출이 없습니다' | Q77: 확정 | S77: 0 | T77: 1 | U77: 0 | W77: 0 | X77: SCR-030과 동일 | Y77: 빈 상태 아이콘 → 안내 문구 → CTA 버튼 | Z77: state (빈 상태) | AA77: 매출 0건 | AB77: 없음 | AC77: '등록된 매출이 없습니다' | AD77: SCR-030과 동일 | AE77: GNB
A78: SCR-030-E | B78: 매출 관리 - 에러 상태 | C78: Web | D78: /sales | E78: 매출 로딩 실패 에러 표시 | F78: (해당 없음) | G78: 재시도 버튼 | J78: SCR-030 로딩 실패 | L78: '데이터를 불러올 수 없습니다' | Q78: 확정 | S78: 0 | T78: 0 | U78: 0 | W78: 0 | X78: SCR-030과 동일 | Y78: 기간 필터 → 통계 카드 → 매출 테이블 | Z78: state (에러) | AA78: 로딩 실패 | AB78: 없음 | AC78: 없음 | AD78: SCR-030과 동일 | AE78: GNB
A79: SCR-030-FLT | B79: 매출 관리 - 기간필터 활성 | C79: Web | D79: /sales | E79: 기간 필터(오늘/이번주/이번달/커스텀) 선택 시 필터링된 결과 | F79: (해당 없음) | G79: 기간 선택, 날짜 피커, 필터 초기화 | J79: SCR-030 기간필터 클릭 | L79: 필터 결과 0건: '해당 기간 매출이 없습니다' | Q79: 확정 | S79: 0 | T79: 1 | U79: 0 | W79: 0 | X79: SCR-030과 동일 | Y79: 기간 필터 → 통계 카드 → 매출 테이블 | Z79: state (필터) | AA79: 기간 필터 클릭 | AB79: SCR-030과 동일 | AC79: 결과 0건: EmptyState | AD79: SCR-030과 동일 | AE79: GNB
A80: SCR-030-M | B80: 매출 관리 - 모바일 뷰 | C80: Mobile | D80: /sales | E80: 모바일 매출 관리. 카드형 리스트 | F80: (해당 없음) | G80: 스와이프, 무한스크롤 | I80: 터치 대응 | J80: GNB 메뉴 | L80: SCR-030과 동일 | M80: 터치 44px | N80: <768px | Q80: 확정 | S80: 0 | T80: 1 | U80: 0 | W80: 0 | X80: 카드형 리스트 | Y80: 기간 필터 → 통계 카드 → 매출 테이블 | Z80: page (모바일) | AA80: GNB 메뉴 | AB80: SCR-030과 동일 | AC80: SCR-030과 동일 | AD80: 카드형 리스트 | AE80: GNB
A81: SCR-031-V | B81: POS 결제 - 유효성 에러 | C81: Web | D81: /sales/pos | E81: POS 결제 폼 유효성 에러 상태 | F81: (해당 없음) | G81: 에러 필드 포커스 | J81: SCR-031 결제 클릭 | L81: 필수 항목 에러, 금액 불일치 에러 | Q81: 확정 | S81: 0 | T81: 1 | U81: 0 | W81: 0 | X81: SCR-031과 동일 | Y81: 회원 선택 → 상품/결제 정보 → 결제 확인 | Z81: state (유효성 에러) | AA81: 결제 클릭 (유효성 실패) | AB81: SCR-031과 동일 | AC81: 없음 | AD81: SCR-031과 동일 | AE81: GNB
A82: SCR-031-L | B82: POS 결제 - 처리 중 | C82: Web | D82: /sales/pos | E82: 결제 처리 중 로딩 상태. 버튼 비활성 | F82: (해당 없음) | G82: 결제 버튼 비활성, 폼 수정 불가 | J82: SCR-031 결제 클릭 | L82: 결제 실패 시 에러 toast | Q82: 확정 | S82: 0 | T82: 0 | U82: 0 | W82: 0 | X82: SCR-031과 동일 | Y82: 회원 선택 → 상품/결제 정보 → 결제 확인 | Z82: state (처리 중) | AA82: 결제 클릭 | AB82: 결제 버튼: 스피너 + '처리 중...' | AC82: 없음 | AD82: SCR-031과 동일 | AE82: GNB
A83: SCR-031-OK | B83: POS 결제 - 완료 | C83: Web | D83: /sales/pos | E83: 결제 완료 시 성공 화면. 영수증 출력 옵션 | F83: (해당 없음) | G83: 영수증 출력, 새 결제, 목록 이동 버튼 | J83: SCR-031 결제 성공 | L83: 없음 | Q83: 확정 | S83: 0 | T83: 1 | U83: 0 | W83: 0 | X83: 성공 아이콘 + 결제 요약 | Y83: 회원 선택 → 상품/결제 정보 → 결제 확인 | Z83: state (완료) | AA83: 결제 성공 | AB83: 없음 | AC83: 없음 | AD83: SCR-031과 동일 | AE83: GNB
A84: SCR-032-L | B84: SalesPos - 로딩 상태 | C84: Web | D84: /pos | E84: POS 화면 초기 로딩 (상품 목록, 회원 정보) | F84: (해당 없음) | G84: 상품 그리드 스켈레톤 | J84: SCR-032 진입 | L84: 로딩 실패 에러 | Q84: 확정 | S84: 0 | T84: 1 | U84: 0 | W84: 0 | X84: SCR-032와 동일 (스켈레톤) | Y84: 스켈레톤 UI | Z84: state (로딩) | AA84: 페이지 진입 | AB84: 상품 그리드 스켈레톤 | AC84: 없음 | AD84: SCR-032와 동일 | AE84: GNB
A85: SCR-032-CART | B85: SalesPos - 장바구니 활성 | C85: Web | D85: /pos | E85: 상품 선택 후 장바구니에 아이템이 있는 상태 | F85: (해당 없음) | G85: 수량 변경, 삭제, 할인 적용 | J85: SCR-032 상품 클릭 | L85: 재고 초과 경고 | Q85: 확정 | S85: 0 | T85: 2 | U85: 0 | W85: 0 | X85: SCR-032와 동일 + 장바구니 패널 | Y85: 페이지 헤더 → 메인 콘텐츠 → 하단 액션 | Z85: state (장바구니) | AA85: 상품 선택 | AB85: SCR-032와 동일 | AC85: 없음 | AD85: SCR-032와 동일 | AE85: GNB + 장바구니 패널
A86: SCR-040-L | B86: 상품 목록 - 로딩 상태 | C86: Web | D86: /products | E86: 상품 목록 로딩 중 스켈레톤 | F86: (해당 없음) | G86: 스켈레톤 그리드 | J86: SCR-040 진입 | L86: 로딩 실패 에러 | Q86: 확정 | S86: 0 | T86: 0 | U86: 0 | W86: 0 | X86: SCR-040과 동일 (스켈레톤) | Y86: 스켈레톤 UI | Z86: state (로딩) | AA86: 페이지 진입 | AB86: 상품 카드 스켈레톤 | AC86: 없음 | AD86: SCR-040과 동일 | AE86: GNB
A87: SCR-040-EM | B87: 상품 목록 - 빈 상태 | C87: Web | D87: /products | E87: 상품 0건 시 EmptyState | F87: (해당 없음) | G87: 상품 등록 바로가기 | J87: SCR-040 (상품 0건) | L87: '등록된 상품이 없습니다' | Q87: 확정 | S87: 0 | T87: 1 | U87: 0 | W87: 0 | X87: SCR-040과 동일 | Y87: 빈 상태 아이콘 → 안내 문구 → CTA 버튼 | Z87: state (빈 상태) | AA87: 상품 0건 | AB87: 없음 | AC87: '등록된 상품이 없습니다' | AD87: SCR-040과 동일 | AE87: GNB
A88: SCR-040-E | B88: 상품 목록 - 에러 상태 | C88: Web | D88: /products | E88: 상품 로딩 실패 에러 | F88: (해당 없음) | G88: 재시도 버튼 | J88: SCR-040 로딩 실패 | L88: '데이터를 불러올 수 없습니다' | Q88: 확정 | S88: 0 | T88: 0 | U88: 0 | W88: 0 | X88: SCR-040과 동일 | Y88: 검색/필터 바 → 데이터 테이블 → 페이지네이션 | Z88: state (에러) | AA88: 로딩 실패 | AB88: 없음 | AC88: 없음 | AD88: SCR-040과 동일 | AE88: GNB
A89: SCR-040-FLT | B89: 상품 목록 - 카테고리 필터 | C89: Web | D89: /products | E89: 카테고리 필터(PT/회원권/GX/상품/서비스) 선택 상태 | F89: (해당 없음) | G89: 카테고리 탭 전환, 활성/비활성 토글 | J89: SCR-040 카테고리 탭 클릭 | L89: 필터 결과 0건: '해당 카테고리 상품이 없습니다' | Q89: 확정 | S89: 0 | T89: 2 | U89: 0 | W89: 0 | X89: SCR-040과 동일 | Y89: 검색/필터 바 → 데이터 테이블 → 페이지네이션 | Z89: state (필터) | AA89: 카테고리 탭 클릭 | AB89: SCR-040과 동일 | AC89: 결과 0건: EmptyState | AD89: SCR-040과 동일 | AE89: GNB
A90: SCR-040-M | B90: 상품 목록 - 모바일 뷰 | C90: Mobile | D90: /products | E90: 모바일 상품 목록. 카드형 | F90: (해당 없음) | G90: 카드 터치, 무한스크롤 | I90: 터치 대응 | J90: GNB 메뉴 | L90: SCR-040과 동일 | M90: 터치 44px | N90: <768px | Q90: 확정 | S90: 0 | T90: 0 | U90: 0 | W90: 0 | X90: 카드형 2열 그리드 | Y90: 검색/필터 바 → 데이터 테이블 → 페이지네이션 | Z90: page (모바일) | AA90: GNB 메뉴 | AB90: SCR-040과 동일 | AC90: SCR-040과 동일 | AD90: 카드형 2열 | AE90: GNB
A91: SCR-041-V | B91: 상품 등록 - 유효성 에러 | C91: Web | D91: /products/new | E91: 상품 폼 유효성 에러 상태 | F91: (해당 없음) | G91: 에러 필드 포커스 | J91: SCR-041 저장 클릭 | L91: 필수 필드 에러, 가격 0원 이하 에러 | Q91: 확정 | S91: 0 | T91: 1 | U91: 0 | W91: 0 | X91: SCR-041과 동일 | Y91: 폼 섹션 → 입력 필드 → 저장/취소 버튼 | Z91: state (유효성 에러) | AA91: 저장 클릭 (유효성 실패) | AB91: SCR-041과 동일 | AC91: 없음 | AD91: SCR-041과 동일 | AE91: GNB
A92: SCR-041-L | B92: 상품 등록 - 저장 중 | C92: Web | D92: /products/new | E92: 상품 등록 API 호출 중 | F92: (해당 없음) | G92: 저장 버튼 비활성 | J92: SCR-041 저장 클릭 | L92: 저장 실패 에러 toast | Q92: 확정 | S92: 0 | T92: 0 | U92: 0 | W92: 0 | X92: SCR-041과 동일 | Y92: 폼 섹션 → 입력 필드 → 저장/취소 버튼 | Z92: state (저장 중) | AA92: 저장 클릭 | AB92: 스피너 + '등록 중...' | AC92: 없음 | AD92: SCR-041과 동일 | AE92: GNB
A93: SCR-050-L | B93: 직원 목록 - 로딩 상태 | C93: Web | D93: /staff | E93: 직원 목록 로딩 중 스켈레톤 | F93: (해당 없음) | G93: 스켈레톤 행 표시 | J93: SCR-050 진입 | L93: 로딩 실패 에러 | Q93: 확정 | S93: 0 | T93: 0 | U93: 0 | W93: 0 | X93: SCR-050과 동일 (스켈레톤) | Y93: 스켈레톤 UI | Z93: state (로딩) | AA93: 페이지 진입 | AB93: 테이블 스켈레톤 | AC93: 없음 | AD93: SCR-050과 동일 | AE93: GNB
A94: SCR-050-EM | B94: 직원 목록 - 빈 상태 | C94: Web | D94: /staff | E94: 직원 0명 시 EmptyState | F94: (해당 없음) | G94: 직원 등록 바로가기 | J94: SCR-050 (직원 0명) | L94: '등록된 직원이 없습니다' | Q94: 확정 | S94: 0 | T94: 1 | U94: 0 | W94: 0 | X94: SCR-050과 동일 | Y94: 빈 상태 아이콘 → 안내 문구 → CTA 버튼 | Z94: state (빈 상태) | AA94: 직원 0명 | AB94: 없음 | AC94: '등록된 직원이 없습니다' | AD94: SCR-050과 동일 | AE94: GNB
A95: SCR-050-E | B95: 직원 목록 - 에러 상태 | C95: Web | D95: /staff | E95: 직원 로딩 실패 에러 | F95: (해당 없음) | G95: 재시도 버튼 | J95: SCR-050 로딩 실패 | L95: '데이터를 불러올 수 없습니다' | Q95: 확정 | S95: 0 | T95: 0 | U95: 0 | W95: 0 | X95: SCR-050과 동일 | Y95: 검색/필터 바 → 데이터 테이블 → 페이지네이션 | Z95: state (에러) | AA95: 로딩 실패 | AB95: 없음 | AC95: 없음 | AD95: SCR-050과 동일 | AE95: GNB
A96: SCR-050-M | B96: 직원 목록 - 모바일 뷰 | C96: Mobile | D96: /staff | E96: 모바일 직원 목록 | F96: (해당 없음) | G96: 카드형 리스트 | I96: 터치 대응 | J96: GNB 메뉴 | L96: SCR-050과 동일 | M96: 터치 44px | N96: <768px | Q96: 확정 | S96: 0 | T96: 1 | U96: 0 | W96: 0 | X96: 카드형 리스트 | Y96: 검색/필터 바 → 데이터 테이블 → 페이지네이션 | Z96: page (모바일) | AA96: GNB 메뉴 | AB96: SCR-050과 동일 | AC96: SCR-050과 동일 | AD96: 카드형 리스트 | AE96: GNB
A97: SCR-051-V | B97: 직원 등록 - 유효성 에러 | C97: Web | D97: /staff/new | E97: 직원 등록 폼 유효성 에러 | F97: (해당 없음) | G97: 에러 필드 포커스 | J97: SCR-051 저장 클릭 | L97: 필수 필드 에러 | Q97: 확정 | S97: 0 | T97: 1 | U97: 0 | W97: 0 | X97: SCR-051과 동일 | Y97: 폼 섹션 → 입력 필드 → 저장/취소 버튼 | Z97: state (유효성 에러) | AA97: 저장 클릭 (실패) | AB97: SCR-051과 동일 | AC97: 없음 | AD97: SCR-051과 동일 | AE97: GNB
A98: SCR-051-L | B98: 직원 등록 - 저장 중 | C98: Web | D98: /staff/new | E98: 직원 등록 API 호출 중 | F98: (해당 없음) | G98: 저장 버튼 비활성 | J98: SCR-051 저장 클릭 | L98: 저장 실패 에러 toast | Q98: 확정 | S98: 0 | T98: 0 | U98: 0 | W98: 0 | X98: SCR-051과 동일 | Y98: 폼 섹션 → 입력 필드 → 저장/취소 버튼 | Z98: state (저장 중) | AA98: 저장 클릭 | AB98: 스피너 + '등록 중...' | AC98: 없음 | AD98: SCR-051과 동일 | AE98: GNB
A99: SCR-052-L | B99: 급여 관리 - 로딩 상태 | C99: Web | D99: /payroll | E99: 급여 목록 로딩 중 | F99: (해당 없음) | G99: 스켈레톤 표시 | J99: SCR-052 진입 | L99: 로딩 실패 에러 | Q99: 확정 | S99: 0 | T99: 0 | U99: 0 | W99: 0 | X99: SCR-052와 동일 (스켈레톤) | Y99: 스켈레톤 UI | Z99: state (로딩) | AA99: 페이지 진입 | AB99: 테이블 스켈레톤 | AC99: 없음 | AD99: SCR-052와 동일 | AE99: GNB
A100: SCR-052-EM | B100: 급여 관리 - 빈 상태 | C100: Web | D100: /payroll | E100: 급여 0건 시 EmptyState | F100: (해당 없음) | G100: 급여 등록 바로가기 | J100: SCR-052 (0건) | L100: '등록된 급여 데이터가 없습니다' | Q100: 확정 | S100: 0 | T100: 1 | U100: 0 | W100: 0 | X100: SCR-052와 동일 | Y100: 빈 상태 아이콘 → 안내 문구 → CTA 버튼 | Z100: state (빈 상태) | AA100: 급여 0건 | AB100: 없음 | AC100: '등록된 급여 데이터가 없습니다' | AD100: SCR-052와 동일 | AE100: GNB
...

Sheet UI 요소 상세
A1: 요소 ID | B1: 화면 ID | C1: 요소명 | D1: 요소 유형 | E1: 요소 설명 | F1: 인터랙션 정의 | G1: 기능 ID | H1: API ID | I1: Web 구현 | J1: App 구현 | K1: 유효성 검사 | L1: 에러 메시지 | M1: 접근성 | N1: 상태 | O1: 담당자 | P1: [자동] 화면명 | Q1: [자동] 기능명 | R1: [자동] API 엔드포인트 | S1: 비고 | T1: 내부 구성 | U1: 크기/간격 | V1: 상태 목록 | W1: 호버/클릭 피드백 | X1: 소속 섹션 | Y1: 정렬 순서 | Z1: 조건부 표시 | AA1: 관련 디자인토큰
A2: ▼ SCR-001 | B2: 로그인 (5개 요소) | C2: 5개 요소
A3: UI-001 | B3: SCR-001 | C3: 이메일 입력 | D3: Input | E3: 로그인 이메일 주소 입력 필드 | F3: 포커스 시 라벨 상단 이동, 실시간 이메일 형식 검증 | G3: FN-001 | H3: API-001 | I3: <input type='email'> + 실시간 validation | K3: 이메일 형식 검증 (regex) | L3: 올바른 이메일 주소를 입력하세요 | M3: aria-label='이메일' | N3: 설계중 | P3: 로그인 | Q3: 로그인 | R3: /api/v1/auth/login | T3: 라벨('이메일') 상단 + input(type=email) + 실시간 형식검증 | U3: w:100%, h:40px, padding:12px, label:14px gray-500 | V3: default / focus(border-primary) / error(border-red + 에러텍스트) / filled | W3: focus: 라벨 상단이동 + border-primary blur: 에러 시 border-red | X3: 폼 영역 | Y3: 1 | Z3: 항상 | AA3: TK-304(input radius), TK-206(높이), TK-024(라벨색)
A4: UI-002 | B4: SCR-001 | C4: 비밀번호 입력 | D4: Input | E4: 로그인 비밀번호 입력 필드 | F4: 마스킹 토글 버튼, Enter키 로그인 트리거 | G4: FN-001 | H4: API-001 | I4: <input type='password'> + visibility toggle | K4: 최소 1자 이상 | L4: 비밀번호를 입력하세요 | M4: aria-label='비밀번호' | N4: 설계중 | P4: 로그인 | Q4: 로그인 | R4: /api/v1/auth/login | T4: 라벨('비밀번호') + input(type=password) + Eye/EyeOff 토글버튼 | U4: w:100%, h:40px, 토글버튼:24px 우측 | V4: default / focus / error / masked / visible | W4: Eye클릭: password↔text 전환 Enter: 로그인 트리거 | X4: 폼 영역 | Y4: 2 | Z4: 항상 | AA4: TK-304, TK-206
A5: UI-003 | B5: SCR-001 | C5: 지점 선택 | D5: Select | E5: 로그인 시 접근할 지점 선택 드롭다운 | F5: 선택 시 지점 로고/색상 변경 | G5: FN-001 | H5: API-001 | I5: <select> 커스텀 드롭다운 | K5: 필수 선택 | L5: 지점을 선택하세요 | M5: aria-label='지점 선택' | N5: 설계중 | P5: 로그인 | Q5: 로그인 | R5: /api/v1/auth/login | T5: MapPin아이콘 + select 드롭다운 + 옵션리스트 | U5: w:100%, h:40px | V5: default / loading(Loader2) / open(드롭다운펼침) / selected / error | W5: click: 드롭다운 열기 선택: 지점 로고/색상 변경 | X5: 폼 영역 | Y5: 0 (폼 최상단) | Z5: 항상 | AA5: TK-304, TK-206, TK-036(선택됨)
A6: UI-004 | B6: SCR-001 | C6: 로그인 버튼 | D6: Button | E6: 로그인 실행 버튼 | F6: 클릭/Enter 시 로그인 API 호출, 로딩 스피너 | G6: FN-001 | H6: API-001 | I6: <button> + loading state | K6: 이메일/비밀번호/지점 모두 입력 시 활성화 | L6: 로그인에 실패했습니다 | M6: aria-label='로그인' | N6: 설계중 | P6: 로그인 | Q6: 로그인 | R6: /api/v1/auth/login | T6: 텍스트('로그인') + 조건부 Loader2 스핀 | U6: w:100%, h:48px, font:16px bold white | V6: default(비활성, gray) / active(primary) / loading(스핀+'로그인 중...') / disabled | W6: hover: primary-600 click: scale(0.98) loading: 클릭 불가 | X6: 폼 영역 | Y6: 5 (폼 하단) | Z6: 이메일/비밀번호/지점 모두 입력 시 활성 | AA6: TK-004(bg), TK-209(높이), TK-604(press)
A7: UI-005 | B7: SCR-001 | C7: 비밀번호 찾기 링크 | D7: Link | E7: 비밀번호 재설정 페이지 이동 링크 | F7: 클릭 시 비밀번호 찾기 모달 오픈 | I7: <a> + 모달 트리거 | M7: aria-label='비밀번호 찾기' | N7: 설계중 | P7: 로그인 | Q7: =IFERROR(VLOOKUP(G7,기능명세서!A:B,2,FALSE()),"") | R7: =IFERROR(VLOOKUP(H7,API명세서!A:D,4,FALSE()),"") | T7: 텍스트 링크('비밀번호 찾기') | U7: font:13px, color:gray-500 | V7: default / hover(underline) | W7: click: 비밀번호 찾기 모달 오픈 | X7: 옵션 영역 | Y7: 4 | Z7: 항상 | AA7: TK-024(색상)
A8: ▼ SCR-002 | B8: 대시보드 (8개 요소) | C8: 8개 요소
A9: UI-006 | B9: SCR-002 | C9: 총회원 통계 카드 | D9: Card | E9: 전체 회원 수 표시 카드 | F9: 클릭 시 SCR-010 이동, 전일 대비 증감 표시 | G9: FN-002 | H9: API-003 | I9: Card 컴포넌트 + 숫자 애니메이션 | M9: aria-label='총 회원 수' | N9: 설계중 | P9: 대시보드 | Q9: 대시보드 통계 조회 | R9: /api/v1/dashboard/stats | T9: [좌] Users아이콘(24px) + [중앙] 라벨('총 회원') 위 + 수치('450명') 아래 + [우하단] 증감배지('+3 ▲' 초록) | U9: w:카드1/6, h:auto, p:24px, 라벨:14px gray-500, 수치:32px bold | V9: default / hover(shadow-md) / loading(숫자 스켈레톤) / zero(수치0) | W9: hover: shadow-md + cursor-pointer click: 회원목록 이동 | X9: 섹션1: 통계카드 영역 | Y9: 1 (6개 중 첫째) | Z9: 항상 | AA9: TK-108(숫자), TK-024(라벨), TK-030(증가), TK-032(감소)
A10: UI-007 | B10: SCR-002 | C10: 활성회원 통계 카드 | D10: Card | E10: 활성(이용중) 회원 수 카드 | F10: 클릭 시 SCR-010 활성 필터 이동 | G10: FN-002 | H10: API-003 | I10: Card 컴포넌트 | M10: aria-label='활성 회원 수' | N10: 설계중 | P10: 대시보드 | Q10: 대시보드 통계 조회 | R10: /api/v1/dashboard/stats | T10: [좌] UserCheck아이콘 + [중앙] '활성회원' + 수치 + 증감 | U10: 동일 StatCard 규격 | V10: default / hover / loading / zero | W10: hover: shadow-md click: 회원목록(활성필터) 이동 | X10: 섹션1: 통계카드 영역 | Y10: 2 | Z10: 항상 | AA10: TK-108, TK-030
A11: UI-008 | B11: SCR-002 | C11: 만료임박 통계 카드 | D11: Card | E11: 7일 내 만료 예정 회원 수 카드 | F11: 클릭 시 SCR-010 만료임박 필터 이동, 경고 색상 | G11: FN-002 | H11: API-006 | I11: Card 컴포넌트 + 경고 스타일 | M11: aria-label='만료 임박 회원' | N11: 설계중 | P11: 대시보드 | Q11: 대시보드 통계 조회 | R11: /api/v1/dashboard/expiring-members | T11: [좌] AlertTriangle아이콘 + [중앙] '만료임박' + 수치 + 경고스타일 | U11: 동일 StatCard, 경고색상 | V11: default / hover / loading / zero / warning(>0일때 amber) | W11: hover: shadow-md click: 회원목록(만료임박필터) 이동 | X11: 섹션1: 통계카드 영역 | Y11: 3 | Z11: 항상 | AA11: TK-034(경고), TK-108
A12: UI-009 | B12: SCR-002 | C12: 만료회원 통계 카드 | D12: Card | E12: 이용권 만료된 회원 수 카드 | F12: 클릭 시 SCR-010 만료 필터 이동 | G12: FN-002 | H12: API-003 | I12: Card 컴포넌트 | M12: aria-label='만료 회원 수' | N12: 설계중 | P12: 대시보드 | Q12: 대시보드 통계 조회 | R12: /api/v1/dashboard/stats | T12: [좌] UserX아이콘 + [중앙] '만료회원' + 수치 | U12: 동일 StatCard 규격 | V12: default / hover / loading / zero | W12: hover: shadow-md click: 회원목록(만료필터) 이동 | X12: 섹션1: 통계카드 영역 | Y12: 4 | Z12: 항상 | AA12: TK-108
A13: UI-010 | B13: SCR-002 | C13: 생일회원 리스트 | D13: List | E13: 오늘 생일인 회원 목록 | F13: 회원명 클릭 시 SCR-011 이동 | G13: FN-002 | H13: API-004 | I13: 리스트 컴포넌트 (최대 5명) | M13: aria-label='오늘 생일 회원' | N13: 설계중 | P13: 대시보드 | Q13: 대시보드 통계 조회 | R13: /api/v1/dashboard/birthday-members | T13: 리스트: 회원명(링크) + 연락처 + 생일일자, 최대5명 | U13: w:카드1/2, max-h:300px | V13: default / empty('오늘 생일인 회원이 없습니다') / loading(3줄 스켈레톤) | W13: 회원명 click: 회원상세 이동 | X13: 섹션3: 리스트 카드 | Y13: 1 (4개 중) | Z13: 항상 | AA13: TK-004(링크)
A14: UI-011 | B14: SCR-002 | C14: 미납회원 리스트 | D14: List | E14: 미납 내역이 있는 회원 목록 | F14: 회원명 클릭 시 SCR-011 이동, 미납 금액 표시 | G14: FN-002 | H14: API-005 | I14: 리스트 컴포넌트 + 금액 강조 | M14: aria-label='미납 회원' | N14: 설계중 | P14: 대시보드 | Q14: 대시보드 통계 조회 | R14: /api/v1/dashboard/unpaid-members | T14: 리스트: 회원명(링크) + 미납금액(빨간) + 결제버튼 | U14: w:카드1/2, 금액:빨간bold | V14: default / empty / loading | W14: 회원명 click: 회원상세 결제 click: POS 이동 | X14: 섹션3: 리스트 카드 | Y14: 2 | Z14: 항상 | AA14: TK-032(미납금액)
A15: UI-012 | B15: SCR-002 | C15: 만료예정 리스트 | D15: List | E15: 7일 내 만료 예정 회원 목록 | F15: 회원명 클릭 시 SCR-011 이동, D-day 표시 | G15: FN-002 | H15: API-006 | I15: 리스트 컴포넌트 + D-day 배지 | M15: aria-label='만료 예정 회원' | N15: 설계중 | P15: 대시보드 | Q15: 대시보드 통계 조회 | R15: /api/v1/dashboard/expiring-members
A16: UI-013 | B16: SCR-002 | C16: 매출 차트 | D16: Card | E16: 당월 매출 추이 라인 차트 | F16: 호버 시 일별 금액 툴팁, 기간 필터 | G16: FN-002 | H16: API-003 | I16: Recharts LineChart | M16: 차트 데이터 테이블 대체 제공 | N16: 설계중 | P16: 대시보드 | Q16: 대시보드 통계 조회 | R16: /api/v1/dashboard/stats
A17: ▼ SCR-010 | B17: 회원 목록 (8개 요소) | C17: 8개 요소
A18: UI-014 | B18: SCR-010 | C18: 검색바 | D18: Input | E18: 회원 이름/연락처/번호 검색 입력 | F18: 실시간 검색 (300ms debounce), 검색 아이콘 | G18: FN-003 | H18: API-007 | I18: SearchInput 컴포넌트 | K18: 최소 2자 이상 | L18: 검색어를 입력하세요 | M18: aria-label='회원 검색' | N18: 설계중 | P18: 회원 목록 | Q18: 회원 목록 조회/검색/필터 | R18: /api/v1/members
A19: UI-015 | B19: SCR-010 | C19: 상태 필터 | D19: Select | E19: 회원 상태(활성/만료/휴회/탈퇴) 필터 | F19: 멀티 선택 가능, 선택 시 즉시 필터 적용 | G19: FN-003 | H19: API-007 | I19: MultiSelect 컴포넌트 | K19: 1개 이상 선택 필수 | L19: 상태 필터을(를) 선택하세요 | M19: aria-label='상태 필터' | N19: 설계중 | P19: 회원 목록 | Q19: 회원 목록 조회/검색/필터 | R19: /api/v1/members
A20: UI-016 | B20: SCR-010 | C20: 성별 필터 | D20: Select | E20: 성별(전체/남/여) 필터 | F20: 단일 선택, 즉시 적용 | G20: FN-003 | H20: API-007 | I20: Select 컴포넌트 | K20: 1개 이상 선택 필수 | L20: 성별 필터을(를) 선택하세요 | M20: aria-label='성별 필터' | N20: 설계중 | P20: 회원 목록 | Q20: 회원 목록 조회/검색/필터 | R20: /api/v1/members
A21: UI-017 | B21: SCR-010 | C21: 담당자 필터 | D21: Select | E21: 담당 FC 필터 | F21: 단일 선택, 즉시 적용 | G21: FN-003 | H21: API-007 | I21: Select 컴포넌트 | K21: 1개 이상 선택 필수 | L21: 담당자 필터을(를) 선택하세요 | M21: aria-label='담당자 필터' | N21: 설계중 | P21: 회원 목록 | Q21: 회원 목록 조회/검색/필터 | R21: /api/v1/members
A22: UI-018 | B22: SCR-010 | C22: 회원 테이블 | D22: List | E22: 회원 목록 데이터 테이블 | F22: 행 클릭 시 SCR-011 이동, 컬럼 정렬, 행 호버 | G22: FN-003 | H22: API-007 | I22: DataTable 컴포넌트 + 정렬/페이지네이션 | M22: aria-label='회원 목록 테이블' | N22: 설계중 | P22: 회원 목록 | Q22: 회원 목록 조회/검색/필터 | R22: /api/v1/members
A23: UI-019 | B23: SCR-010 | C23: 페이지네이션 | D23: Nav | E23: 테이블 하단 페이지 네비게이션 | F23: 페이지 이동, 페이지당 행 수 선택 | G23: FN-003 | H23: API-007 | I23: Pagination 컴포넌트 | M23: aria-label='페이지 이동' | N23: 설계중 | P23: 회원 목록 | Q23: 회원 목록 조회/검색/필터 | R23: /api/v1/members
A24: UI-020 | B24: SCR-010 | C24: 엑셀 다운로드 | D24: Button | E24: 현재 필터 결과 엑셀 다운로드 | F24: 클릭 시 xlsx 파일 다운로드, 로딩 표시 | G24: FN-003 | H24: API-007 | I24: 다운로드 버튼 + 로딩 스피너 | M24: aria-label='엑셀 다운로드' | N24: 설계중 | P24: 회원 목록 | Q24: 회원 목록 조회/검색/필터 | R24: /api/v1/members
A25: UI-021 | B25: SCR-010 | C25: 회원등록 버튼 | D25: Button | E25: 신규 회원 등록 페이지 이동 버튼 | F25: 클릭 시 SCR-012 이동 | G25: FN-004 | I25: Primary Button | M25: aria-label='회원 등록' | N25: 설계중 | P25: 회원 목록 | Q25: 회원 등록 | R25: =IFERROR(VLOOKUP(H25,API명세서!A:D,4,FALSE()),"")
A26: ▼ SCR-011 | B26: 회원 상세 (6개 요소) | C26: 6개 요소
A27: UI-022 | B27: SCR-011 | C27: 프로필 영역 | D27: Card | E27: 회원 기본 정보 카드 (사진/이름/연락처/상태) | F27: 수정 버튼 → SCR-013 이동 | G27: FN-006 | H27: API-008 | I27: 프로필 Card 컴포넌트 | M27: aria-label='회원 프로필' | N27: 설계중 | P27: 회원 상세 | Q27: 회원 상세 조회 | R27: /api/v1/members/:id
A28: UI-023 | B28: SCR-011 | C28: 이용권 탭 | D28: Tab | E28: 보유 이용권 목록 탭 | F28: 만료일 강조, 잔여 횟수 표시 | G28: FN-006 | H28: API-008 | I28: Tab + 이용권 리스트 | M28: aria-label='이용권 탭' | N28: 설계중 | P28: 회원 상세 | Q28: 회원 상세 조회 | R28: /api/v1/members/:id
A29: UI-024 | B29: SCR-011 | C29: 출석 탭 | D29: Tab | E29: 출석 이력 탭 (히트맵 + 리스트) | F29: 히트맵 날짜 클릭 시 상세, 타지점 출석 구분 | G29: FN-006 | H29: API-013 | I29: Tab + 히트맵 + 테이블 | M29: aria-label='출석 탭' | N29: 설계중 | P29: 회원 상세 | Q29: 회원 상세 조회 | R29: /api/v1/attendance
A30: UI-025 | B30: SCR-011 | C30: 결제 탭 | D30: Tab | E30: 결제/매출 이력 탭 | F30: 결제 상세 모달, 환불 처리 | G30: FN-006 | H30: API-015 | I30: Tab + 결제 테이블 | M30: aria-label='결제 탭' | N30: 설계중 | P30: 회원 상세 | Q30: 회원 상세 조회 | R30: /api/v1/sales
A31: UI-026 | B31: SCR-011 | C31: 체성분 탭 | D31: Tab | E31: 체성분 측정 이력 + 차트 탭 | F31: 측정 추가, 변화 추이 차트 | G31: FN-007 | H31: API-008 | I31: Tab + 차트 + 입력 폼 | M31: aria-label='체성분 탭' | N31: 설계중 | P31: 회원 상세 | Q31: 체성분 기록/분석 | R31: /api/v1/members/:id
A32: UI-027 | B32: SCR-011 | C32: 메모 탭 | D32: Tab | E32: 상담/메모 기록 탭 | F32: 메모 추가/수정/삭제, 시간순 정렬 | G32: FN-006 | H32: API-008 | I32: Tab + 메모 리스트 + 에디터 | M32: aria-label='메모 탭' | N32: 설계중 | P32: 회원 상세 | Q32: 회원 상세 조회 | R32: /api/v1/members/:id
A33: ▼ SCR-012 | B33: 회원 등록 (10개 요소) | C33: 10개 요소
A34: UI-028 | B34: SCR-012 | C34: 이름 입력 | D34: Input | E34: 회원 이름 입력 필드 | F34: 필수 항목, 한글 2~20자 | G34: FN-004 | H34: API-009 | I34: <input> + validation | K34: 한글 2~20자 | L34: 이름을 입력하세요 | M34: aria-required='true' | N34: 설계중 | P34: 회원 등록 | Q34: 회원 등록 | R34: /api/v1/members
A35: UI-029 | B35: SCR-012 | C35: 성별 선택 | D35: Radio | E35: 성별 선택 (남/여) | F35: 라디오 버튼 2개 | G35: FN-004 | H35: API-009 | I35: RadioGroup 컴포넌트 | K35: 필수 선택 | L35: 성별을 선택하세요 | M35: role='radiogroup' | N35: 설계중 | P35: 회원 등록 | Q35: 회원 등록 | R35: /api/v1/members
A36: UI-030 | B36: SCR-012 | C36: 생년월일 | D36: Input | E36: 생년월일 입력 (date picker) | F36: 달력 팝업 또는 직접 입력 | G36: FN-004 | H36: API-009 | I36: DatePicker 컴포넌트 | K36: 미래 날짜 불가 | L36: 올바른 날짜를 입력하세요 | M36: aria-label='생년월일' | N36: 설계중 | P36: 회원 등록 | Q36: 회원 등록 | R36: /api/v1/members
A37: UI-031 | B37: SCR-012 | C37: 연락처 입력 | D37: Input | E37: 연락처 입력 (자동 하이픈) | F37: 입력 시 자동 포맷 (010-xxxx-xxxx) | G37: FN-004 | H37: API-009 | I37: PhoneInput 컴포넌트 | K37: 전화번호 형식 검증, 중복 체크 | L37: 올바른 연락처를 입력하세요 | M37: aria-label='연락처' | N37: 설계중 | P37: 회원 등록 | Q37: 회원 등록 | R37: /api/v1/members
A38: UI-032 | B38: SCR-012 | C38: 이메일 입력 | D38: Input | E38: 이메일 주소 입력 | F38: 선택 항목 | G38: FN-004 | H38: API-009 | I38: <input type='email'> | K38: 이메일 형식 검증 | L38: 올바른 이메일을 입력하세요 | M38: aria-label='이메일' | N38: 설계중 | P38: 회원 등록 | Q38: 회원 등록 | R38: /api/v1/members
A39: UI-033 | B39: SCR-012 | C39: 주소 입력 | D39: Input | E39: 주소 검색 및 입력 | F39: 다음 주소 API 연동 | G39: FN-004 | H39: API-009 | I39: AddressSearch 컴포넌트 | K39: 최소 5자 이상 | L39: 주소를 입력하세요 | M39: aria-label='주소' | N39: 설계중 | P39: 회원 등록 | Q39: 회원 등록 | R39: /api/v1/members
A40: UI-034 | B40: SCR-012 | C40: 메모 입력 | D40: Textarea | E40: 관리자 메모 입력 | F40: 최대 500자, 글자수 카운터 | G40: FN-004 | H40: API-009 | I40: <textarea> + counter | K40: 최대 500자 | L40: 메모 입력을(를) 입력하세요 | M40: aria-label='메모' | N40: 설계중 | P40: 회원 등록 | Q40: 회원 등록 | R40: /api/v1/members
A41: UI-035 | B41: SCR-012 | C41: 담당자 선택 | D41: Select | E41: 담당 FC 선택 드롭다운 | F41: 직원 목록에서 FC 역할만 필터 | G41: FN-004 | H41: API-009 | I41: Select 컴포넌트 | K41: 1개 이상 선택 필수 | L41: 담당자 선택을(를) 선택하세요 | M41: aria-label='담당자 선택' | N41: 설계중 | P41: 회원 등록 | Q41: 회원 등록 | R41: /api/v1/members
A42: UI-036 | B42: SCR-012 | C42: 저장 버튼 | D42: Button | E42: 회원 등록 저장 | F42: 모든 필수 항목 입력 시 활성화, 클릭 시 API 호출 | G42: FN-004 | H42: API-009 | I42: Primary Button + loading | K42: 필수 항목 검증 | L42: 등록에 실패했습니다 | M42: aria-label='저장' | N42: 설계중 | P42: 회원 등록 | Q42: 회원 등록 | R42: /api/v1/members
A43: UI-037 | B43: SCR-012 | C43: 취소 버튼 | D43: Button | E43: 등록 취소, 목록으로 이동 | F43: 변경사항 있을 시 확인 모달 | I43: Secondary Button | M43: aria-label='취소' | N43: 설계중 | P43: 회원 등록 | Q43: =IFERROR(VLOOKUP(G43,기능명세서!A:B,2,FALSE()),"") | R43: =IFERROR(VLOOKUP(H43,API명세서!A:D,4,FALSE()),"")
A44: ▼ SCR-030 | B44: 매출 조회 (7개 요소) | C44: 7개 요소
A45: UI-038 | B45: SCR-030 | C45: 날짜 범위 선택 | D45: Input | E45: 시작일~종료일 범위 선택 | F45: DateRangePicker, 프리셋(오늘/이번주/이번달) | G45: FN-010 | H45: API-015 | I45: DateRangePicker 컴포넌트 | K45: 시작일 ≤ 종료일 | L45: 올바른 기간을 선택하세요 | M45: aria-label='조회 기간' | N45: 설계중 | P45: 매출 조회 | Q45: 매출 조회/통계 | R45: /api/v1/sales
A46: UI-039 | B46: SCR-030 | C46: 유형 필터 | D46: Select | E46: 매출 유형(이용권/PT/상품/기타) 필터 | F46: 멀티 선택, 즉시 적용 | G46: FN-010 | H46: API-015 | I46: MultiSelect 컴포넌트 | K46: 1개 이상 선택 필수 | L46: 유형 필터을(를) 선택하세요 | M46: aria-label='매출 유형' | N46: 설계중 | P46: 매출 조회 | Q46: 매출 조회/통계 | R46: /api/v1/sales
A47: UI-040 | B47: SCR-030 | C47: 상태 필터 | D47: Select | E47: 결제 상태(완료/환불/미납) 필터 | F47: 멀티 선택, 즉시 적용 | G47: FN-010 | H47: API-015 | I47: MultiSelect 컴포넌트 | K47: 1개 이상 선택 필수 | L47: 상태 필터을(를) 선택하세요 | M47: aria-label='결제 상태' | N47: 설계중 | P47: 매출 조회 | Q47: 매출 조회/통계 | R47: /api/v1/sales
A48: UI-041 | B48: SCR-030 | C48: 검색바 | D48: Input | E48: 구매자/상품명 검색 | F48: 실시간 검색 (debounce) | G48: FN-010 | H48: API-015 | I48: SearchInput | K48: 최소 1자 이상 | L48: 검색어를 입력하세요 | M48: aria-label='매출 검색' | N48: 설계중 | P48: 매출 조회 | Q48: 매출 조회/통계 | R48: /api/v1/sales
A49: UI-042 | B49: SCR-030 | C49: 매출 테이블 | D49: List | E49: 매출 내역 데이터 테이블 | F49: 행 클릭 시 상세 모달, 정렬, 페이지네이션 | G49: FN-010 | H49: API-015 | I49: DataTable 컴포넌트 | M49: aria-label='매출 목록' | N49: 설계중 | P49: 매출 조회 | Q49: 매출 조회/통계 | R49: /api/v1/sales
A50: UI-043 | B50: SCR-030 | C50: 총매출 요약 | D50: Card | E50: 총매출/현금/카드/마일리지 요약 카드 | F50: 필터 변경 시 자동 갱신 | G50: FN-010 | H50: API-017 | I50: 요약 Card 4개 | M50: aria-label='매출 요약' | N50: 설계중 | P50: 매출 조회 | Q50: 매출 조회/통계 | R50: /api/v1/sales/stats/summary
A51: UI-044 | B51: SCR-030 | C51: 엑셀 다운로드 | D51: Button | E51: 매출 데이터 엑셀 다운로드 | F51: 클릭 시 xlsx 다운로드 | G51: FN-010 | H51: API-015 | I51: 다운로드 버튼 | M51: aria-label='엑셀 다운로드' | N51: 설계중 | P51: 매출 조회 | Q51: 매출 조회/통계 | R51: /api/v1/sales
A52: ▼ SCR-031 | B52: POS (4개 요소) | C52: 4개 요소
A53: UI-045 | B53: SCR-031 | C53: 카테고리 탭 | D53: Tab | E53: 상품 카테고리 탭 (이용권/PT/GX/기타) | F53: 탭 전환 시 상품 그리드 갱신 | G53: FN-011 | H53: API-018 | I53: Tab 컴포넌트 | M53: aria-label='상품 카테고리' | N53: 설계중 | P53: POS | Q53: POS 상품 선택/결제 | R53: /api/v1/products
A54: UI-046 | B54: SCR-031 | C54: 상품 그리드 | D54: List | E54: 카테고리별 상품 카드 그리드 | F54: 카드 클릭 시 장바구니 추가 | G54: FN-011 | H54: API-018 | I54: CSS Grid + Card | M54: aria-label='상품 목록' | N54: 설계중 | P54: POS | Q54: POS 상품 선택/결제 | R54: /api/v1/products
A55: UI-047 | B55: SCR-031 | C55: 장바구니 | D55: List | E55: 선택한 상품 목록 + 합계 | F55: 수량 조절, 삭제, 합계 자동 계산 | G55: FN-011 | I55: 장바구니 컴포넌트 | M55: aria-label='장바구니' | N55: 설계중 | P55: POS | Q55: POS 상품 선택/결제 | R55: =IFERROR(VLOOKUP(H55,API명세서!A:D,4,FALSE()),"")
A56: UI-048 | B56: SCR-031 | C56: 결제 버튼 | D56: Button | E56: 결제 화면(SCR-032) 이동 | F56: 장바구니 1개 이상 시 활성화 | G56: FN-011 | I56: Primary Button | K56: 장바구니 비어있으면 비활성 | L56: 상품을 선택해주세요 | M56: aria-label='결제하기' | N56: 설계중 | P56: POS | Q56: POS 상품 선택/결제 | R56: =IFERROR(VLOOKUP(H56,API명세서!A:D,4,FALSE()),"")
A57: ▼ SCR-032 | B57: POS 결제 (4개 요소) | C57: 4개 요소
A58: UI-049 | B58: SCR-032 | C58: 결제 요약 | D58: Card | E58: 결제 대상 상품 요약 및 총액 | F58: 상품명, 수량, 금액 표시 | G58: FN-012 | H58: API-016 | I58: 요약 Card | M58: aria-label='결제 요약' | N58: 설계중 | P58: POS 결제 | Q58: POS 결제 처리 | R58: /api/v1/sales
A59: UI-050 | B59: SCR-032 | C59: 결제수단 선택 | D59: Radio | E59: 현금/카드/마일리지/복합 선택 | F59: 복합 선택 시 금액 분배 입력 필드 표시 | G59: FN-012 | H59: API-016 | I59: RadioGroup + 조건부 입력 | K59: 필수 선택 | L59: 결제수단 선택을(를) 선택하세요 | M59: role='radiogroup' | N59: 설계중 | P59: POS 결제 | Q59: POS 결제 처리 | R59: /api/v1/sales
A60: UI-051 | B60: SCR-032 | C60: 회원 검색 | D60: Input | E60: 결제 대상 회원 검색 | F60: 회원 선택 시 마일리지 잔액 표시 | G60: FN-012 | H60: API-007 | I60: AutoComplete 컴포넌트 | K60: 최소 1자 이상 | L60: 검색어를 입력하세요 | M60: aria-label='회원 검색' | N60: 설계중 | P60: POS 결제 | Q60: POS 결제 처리 | R60: /api/v1/members
A61: UI-052 | B61: SCR-032 | C61: 결제 확인 버튼 | D61: Button | E61: 결제 실행 | F61: 결제 확인 모달 → API 호출 → 영수증 | G61: FN-012 | H61: API-016 | I61: Primary Button + 확인 모달 | K61: 결제수단/금액 검증 | L61: 결제에 실패했습니다 | M61: aria-label='결제 확인' | N61: 설계중 | P61: POS 결제 | Q61: POS 결제 처리 | R61: /api/v1/sales
A62: ▼ SCR-050 | B62: 락커 현황 (4개 요소) | C62: 4개 요소
A63: UI-053 | B63: SCR-050 | C63: 구역 탭 | D63: Tab | E63: 락커 구역(A/B/C...) 탭 | F63: 탭 전환 시 해당 구역 그리드 표시 | G63: FN-015 | H63: API-020 | I63: Tab 컴포넌트 | M63: aria-label='락커 구역' | N63: 설계중 | P63: 락커 현황 | Q63: 락커 현황 조회 | R63: /api/v1/lockers
A64: UI-054 | B64: SCR-050 | C64: 락커 그리드 | D64: List | E64: 락커 번호별 색상 그리드 | F64: 사용중(파랑)/빈(회색)/만료임박(주황)/고장(빨강) | G64: FN-015 | H64: API-020 | I64: CSS Grid + 색상 매핑 | M64: 색상+패턴으로 상태 구분 | N64: 설계중 | P64: 락커 현황 | Q64: 락커 현황 조회 | R64: /api/v1/lockers
A65: UI-055 | B65: SCR-050 | C65: 범례 | D65: Label | E65: 락커 상태별 색상 범례 | F65: 4가지 상태 색상 설명 | I65: 범례 컴포넌트 | M65: aria-label='범례' | N65: 설계중 | P65: 락커 현황 | Q65: =IFERROR(VLOOKUP(G65,기능명세서!A:B,2,FALSE()),"") | R65: =IFERROR(VLOOKUP(H65,API명세서!A:D,4,FALSE()),"")
A66: UI-056 | B66: SCR-050 | C66: 락커 상세 모달 | D66: Modal | E66: 락커 클릭 시 상세 정보 모달 | F66: 배정 회원, 만료일, 이력 표시 | G66: FN-015 | H66: API-020 | I66: Modal 컴포넌트 | M66: aria-modal='true' | N66: 설계중 | P66: 락커 현황 | Q66: 락커 현황 조회 | R66: /api/v1/lockers
A67: ▼ SCR-060 | B67: 직원 목록 (5개 요소) | C67: 5개 요소
A68: UI-057 | B68: SCR-060 | C68: 검색바 | D68: Input | E68: 직원 이름/연락처 검색 | F68: 실시간 검색 | G68: FN-019 | H68: API-022 | I68: SearchInput | K68: 최소 1자 이상 | L68: 검색어를 입력하세요 | M68: aria-label='직원 검색' | N68: 설계중 | P68: 직원 목록 | Q68: 직원 목록 조회 | R68: /api/v1/staff
A69: UI-058 | B69: SCR-060 | C69: 역할 필터 | D69: Select | E69: 역할(센터장/매니저/FC/스태프) 필터 | F69: 단일 선택 | G69: FN-019 | H69: API-022 | I69: Select | K69: 1개 이상 선택 필수 | L69: 역할 필터을(를) 선택하세요 | M69: aria-label='역할 필터' | N69: 설계중 | P69: 직원 목록 | Q69: 직원 목록 조회 | R69: /api/v1/staff
A70: UI-059 | B70: SCR-060 | C70: 상태 필터 | D70: Select | E70: 재직 상태(재직/휴직/퇴사) 필터 | F70: 단일 선택 | G70: FN-019 | H70: API-022 | I70: Select | K70: 1개 이상 선택 필수 | L70: 상태 필터을(를) 선택하세요 | M70: aria-label='상태 필터' | N70: 설계중 | P70: 직원 목록 | Q70: 직원 목록 조회 | R70: /api/v1/staff
A71: UI-060 | B71: SCR-060 | C71: 직원 테이블 | D71: List | E71: 직원 목록 데이터 테이블 | F71: 행 클릭 시 상세 모달 | G71: FN-019 | H71: API-022 | I71: DataTable | M71: aria-label='직원 목록' | N71: 설계중 | P71: 직원 목록 | Q71: 직원 목록 조회 | R71: /api/v1/staff
A72: UI-061 | B72: SCR-060 | C72: 직원등록 버튼 | D72: Button | E72: SCR-061 이동 | F72: 클릭 시 등록 페이지 이동 | G72: FN-020 | I72: Primary Button | M72: aria-label='직원 등록' | N72: 설계중 | P72: 직원 목록 | Q72: 직원 등록/수정 | R72: =IFERROR(VLOOKUP(H72,API명세서!A:D,4,FALSE()),"")
A73: ▼ SCR-070 | B73: 메시지 발송 (5개 요소) | C73: 5개 요소
A74: UI-062 | B74: SCR-070 | C74: 수신자 선택 | D74: Input | E74: 회원 검색/그룹 선택으로 수신자 지정 | F74: AutoComplete + 그룹 선택 토글 | G74: FN-023 | I74: AutoComplete + ChipInput | K74: 필수 입력 | L74: 수신자 선택을(를) 입력하세요 | M74: aria-label='수신자' | N74: 설계중 | P74: 메시지 발송 | Q74: 메시지 발송 | R74: =IFERROR(VLOOKUP(H74,API명세서!A:D,4,FALSE()),"")
A75: UI-063 | B75: SCR-070 | C75: 메시지 유형 | D75: Tab | E75: SMS/카카오톡 탭 | F75: 탭에 따라 본문 제한 변경 | G75: FN-023 | I75: Tab 컴포넌트 | M75: aria-label='메시지 유형' | N75: 설계중 | P75: 메시지 발송 | Q75: 메시지 발송 | R75: =IFERROR(VLOOKUP(H75,API명세서!A:D,4,FALSE()),"")
A76: UI-064 | B76: SCR-070 | C76: 본문 에디터 | D76: Textarea | E76: 메시지 본문 입력 | F76: 글자수 카운터, 변수 삽입 (#{이름} 등) | G76: FN-023 | I76: Textarea + 변수 버튼 | K76: SMS 90자/LMS 2000자 | L76: 본문 에디터을(를) 입력하세요 | M76: aria-label='메시지 본문' | N76: 설계중 | P76: 메시지 발송 | Q76: 메시지 발송 | R76: =IFERROR(VLOOKUP(H76,API명세서!A:D,4,FALSE()),"")
A77: UI-065 | B77: SCR-070 | C77: 발송 버튼 | D77: Button | E77: 메시지 발송 실행 | F77: 발송 전 미리보기 확인 모달 | G77: FN-023 | I77: Primary Button + 확인 모달 | K77: 수신자/본문 필수 | L77: 수신자를 선택해주세요 | M77: aria-label='발송' | N77: 설계중 | P77: 메시지 발송 | Q77: 메시지 발송 | R77: =IFERROR(VLOOKUP(H77,API명세서!A:D,4,FALSE()),"")
A78: UI-066 | B78: SCR-070 | C78: 발송 이력 | D78: List | E78: 발송 이력 테이블 | F78: 발송일시/유형/수신자수/성공률 표시 | G78: FN-023 | I78: DataTable | M78: aria-label='발송 이력' | N78: 설계중 | P78: 메시지 발송 | Q78: 메시지 발송 | R78: =IFERROR(VLOOKUP(H78,API명세서!A:D,4,FALSE()),"")
A79: ▼ SCR-080 | B79: 계약 마법사 (6개 요소) | C79: 6개 요소
A80: UI-067 | B80: SCR-080 | C80: 스텝 인디케이터 | D80: Nav | E80: 계약 단계 표시 (1.회원→2.상품→3.기간→4.결제→5.확인) | F80: 현재 단계 강조, 완료 단계 체크마크 | G80: FN-027 | I80: Stepper 컴포넌트 | M80: aria-label='계약 단계' | N80: 설계중 | P80: 계약 마법사 | Q80: 계약 등록 | R80: =IFERROR(VLOOKUP(H80,API명세서!A:D,4,FALSE()),"")
A81: UI-068 | B81: SCR-080 | C81: 회원 선택 스텝 | D81: Card | E81: 계약 대상 회원 검색/선택 | F81: AutoComplete 검색, 선택 시 프로필 카드 표시 | G81: FN-027 | H81: API-007 | I81: 검색 + 프로필 Card | K81: 회원 필수 선택 | L81: 회원을 선택하세요 | M81: aria-label='회원 선택' | N81: 설계중 | P81: 계약 마법사 | Q81: 계약 등록 | R81: /api/v1/members
A82: UI-069 | B82: SCR-080 | C82: 상품 선택 스텝 | D82: Card | E82: 계약 상품 선택 | F82: 카테고리별 상품 목록, 복수 선택 가능 | G82: FN-027 | H82: API-018 | I82: 상품 Card Grid | K82: 상품 필수 선택 | L82: 상품을 선택하세요 | M82: aria-label='상품 선택' | N82: 설계중 | P82: 계약 마법사 | Q82: 계약 등록 | R82: /api/v1/products
A83: UI-070 | B83: SCR-080 | C83: 기간/금액 스텝 | D83: Card | E83: 계약 기간 및 결제 금액 설정 | F83: 시작일/종료일, 할인 적용, 총액 자동 계산 | G83: FN-027 | I83: DatePicker + 금액 입력 | K83: 시작일 필수 | L83: 기간을 설정하세요 | M83: aria-label='기간 설정' | N83: 설계중 | P83: 계약 마법사 | Q83: 계약 등록 | R83: =IFERROR(VLOOKUP(H83,API명세서!A:D,4,FALSE()),"")
A84: UI-071 | B84: SCR-080 | C84: 결제 스텝 | D84: Card | E84: 결제 수단 선택 및 처리 | F84: 현금/카드/마일리지/복합결제 | G84: FN-027 | H84: API-016 | I84: 결제 컴포넌트 | K84: 결제수단 필수 | L84: 결제에 실패했습니다 | M84: aria-label='결제' | N84: 설계중 | P84: 계약 마법사 | Q84: 계약 등록 | R84: /api/v1/sales
A85: UI-072 | B85: SCR-080 | C85: 확인 스텝 | D85: Card | E85: 계약 내용 최종 확인 및 완료 | F85: 계약 요약, 확인 버튼, 인쇄 옵션 | G85: FN-027 | I85: 요약 Card + 확인 버튼 | M85: aria-label='계약 확인' | N85: 설계중 | P85: 계약 마법사 | Q85: 계약 등록 | R85: =IFERROR(VLOOKUP(H85,API명세서!A:D,4,FALSE()),"")
A86: ▼ SCR-090 | B86: 설정 (3개 요소) | C86: 3개 요소
A87: UI-073 | B87: SCR-090 | C87: 기본 설정 탭 | D87: Tab | E87: 센터명/영업시간/연락처 등 기본 정보 | F87: 폼 입력, 저장 버튼 | G87: FN-029 | I87: Tab + Form | M87: aria-label='기본 설정' | N87: 설계중 | P87: 설정 | Q87: 시스템 설정 | R87: =IFERROR(VLOOKUP(H87,API명세서!A:D,4,FALSE()),"")
A88: UI-074 | B88: SCR-090 | C88: 알림 설정 탭 | D88: Tab | E88: 푸시/이메일/SMS 알림 ON/OFF | F88: 토글 스위치 | G88: FN-029 | I88: Tab + Toggle List | M88: aria-label='알림 설정' | N88: 설계중 | P88: 설정 | Q88: 시스템 설정 | R88: =IFERROR(VLOOKUP(H88,API명세서!A:D,4,FALSE()),"")
A89: UI-075 | B89: SCR-090 | C89: 저장 버튼 | D89: Button | E89: 설정 저장 | F89: 변경사항 감지 시 활성화 | G89: FN-029 | I89: Primary Button | M89: aria-label='설정 저장' | N89: 설계중 | P89: 설정 | Q89: 시스템 설정 | R89: =IFERROR(VLOOKUP(H89,API명세서!A:D,4,FALSE()),"")
A90: ▼ SCR-091 | B90: 권한 설정 (3개 요소) | C90: 3개 요소
A91: UI-076 | B91: SCR-091 | C91: 역할 탭 | D91: Tab | E91: 6단계 역할별 탭 | F91: 탭 전환 시 해당 역할 권한 매트릭스 | G91: FN-030 | I91: Tab 컴포넌트 | M91: aria-label='역할 선택' | N91: 설계중 | P91: 권한 설정 | Q91: 권한 관리 | R91: =IFERROR(VLOOKUP(H91,API명세서!A:D,4,FALSE()),"")
A92: UI-077 | B92: SCR-091 | C92: 권한 매트릭스 | D92: List | E92: 메뉴/기능별 읽기/쓰기/삭제 체크박스 테이블 | F92: 체크/해제 시 즉시 반영, 변경 이력 기록 | G92: FN-030 | I92: 체크박스 매트릭스 테이블 | M92: aria-label='권한 매트릭스' | N92: 설계중 | P92: 권한 설정 | Q92: 권한 관리 | R92: =IFERROR(VLOOKUP(H92,API명세서!A:D,4,FALSE()),"")
A93: UI-078 | B93: SCR-091 | C93: 일괄 설정 버튼 | D93: Button | E93: 전체 선택/해제 | F93: 메뉴 단위 일괄 설정 | G93: FN-030 | I93: Toggle Button | M93: aria-label='일괄 설정' | N93: 설계중 | P93: 권한 설정 | Q93: 권한 관리 | R93: =IFERROR(VLOOKUP(H93,API명세서!A:D,4,FALSE()),"")
A94: ▼ SCR-094 | B94: 지점 관리 (3개 요소) | C94: 3개 요소
A95: UI-079 | B95: SCR-094 | C95: 지점 카드 뷰 | D95: Card | E95: 지점별 카드 (이름/주소/회원수/상태) | F95: 카드 클릭 시 상세 모달 | G95: FN-033 | I95: Card Grid | M95: aria-label='지점 목록' | N95: 설계중 | P95: 지점 관리 | Q95: 지점 관리 | R95: =IFERROR(VLOOKUP(H95,API명세서!A:D,4,FALSE()),"")
A96: UI-080 | B96: SCR-094 | C96: 지점 추가 버튼 | D96: Button | E96: 신규 지점 추가 모달 오픈 | F96: 모달 폼 (이름/코드/주소/연락처) | G96: FN-033 | I96: Primary Button + Modal | K96: 지점명/코드 필수 | L96: 지점명을 입력하세요 | M96: aria-label='지점 추가' | N96: 설계중 | P96: 지점 관리 | Q96: 지점 관리 | R96: =IFERROR(VLOOKUP(H96,API명세서!A:D,4,FALSE()),"")
A97: UI-081 | B97: SCR-094 | C97: 데이터 초기화 버튼 | D97: Button | E97: 지점 데이터 초기화 (개발용) | F97: 2중 확인 모달 (비밀번호 입력) | G97: FN-033 | H97: API-027 | I97: Danger Button + 확인 모달 | K97: 관리자 비밀번호 필수 | L97: 비밀번호가 올바르지 않습니다 | M97: aria-label='데이터 초기화' | N97: 설계중 | P97: 지점 관리 | Q97: 지점 관리 | R97: /api/v1/system/reset
A98: ▼ SCR-040 | B98: 상품 목록 (3개 요소) | C98: 3개 요소
A99: UI-082 | B99: SCR-040 | C99: 카테고리 필터 | D99: Select | E99: 상품 카테고리 필터 | F99: 단일 선택, 즉시 적용 | G99: FN-013 | H99: API-018 | I99: Select 컴포넌트 | K99: 1개 이상 선택 필수 | L99: 카테고리 필터을(를) 선택하세요 | M99: aria-label='카테고리' | N99: 설계중 | P99: 상품 목록 | Q99: 상품 목록 조회 | R99: /api/v1/products
A100: UI-083 | B100: SCR-040 | C100: 상품 테이블 | D100: List | E100: 상품 목록 테이블 | F100: 정렬, 키오스크 노출 토글 | G100: FN-013 | H100: API-018 | I100: DataTable + Toggle | M100: aria-label='상품 목록' | N100: 설계중 | P100: 상품 목록 | Q100: 상품 목록 조회 | R100: /api/v1/products
...

Sheet 기능명세서
A1: 기능 ID | B1: 기능명 | C1: 기능 분류 | D1: 플랫폼 | E1: 우선순위 | F1: 기능 설명 | G1: 상세 요구사항 | H1: 화면 ID | I1: 입력 항목 | J1: 출력 항목 | K1: 비즈니스 규칙 | L1: 예외 처리 | M1: Web 구현 사항 | N1: App 구현 사항 | O1: 관련 API ID | P1: 상태 | Q1: 담당자 | R1: [자동] 화면명 | S1: [자동] API 엔드포인트 | T1: 비고 | U1: [자동] 관련 UI 요소
A2: ▼ SCR-001 | B2: 로그인 (1개 기능)
A3: FN-001 | B3: 로그인 | C3: 인증 | D3: Web | E3: Critical | F3: Supabase Auth 기반 로그인 (signInWithPassword) + 평문 비밀번호 fallback. 지점 선택 포함. | G3: 1) Supabase Auth signInWithPassword({email}@spogym.local, password) 1차 시도 2) Auth 실패 시 기존 평문 비밀번호 fallback (마이그레이션 호환) 3) 지점 선택 필수 4) 로그인 유지 체크 시 localStorage 아이디 저장 5) onAuthStateChange 리스너로 세션 자동 관리 6) TOKEN_REFRESHED 시 토큰 자동 갱신, SIGNED_OUT 시 자동 로그아웃 | H3: SCR-001 | I3: 이메일, 비밀번호, 지점ID | J3: JWT 토큰, 사용자 정보, 권한 목록 | K3: 1) 5회 연속 실패 시 30분 계정 잠금 2) 비밀번호: 최소 8자, 영문+숫자+특수문자 조합 필수 3) 이전 3개 비밀번호 재사용 금지 4) 90일 경과 시 비밀번호 변경 권장 팝업 (강제 변경 or 건너뛰기) 5) 동시 세션 1개 제한 – 신규 로그인 시 기존 세션 강제 종료 6) 토큰 만료: 기본 2시간 / 로그인 유지 체크 시 7일 (refresh token) 7) 로그인 시 선택한 지점만 데이터 접근 허용 8) 탈퇴·비활성 계정 접근 불가 | L3: 계정 잠금: '5회 실패로 잠금. 30분 후 재시도 또는 비밀번호 찾기' 서버 오류: '일시적 오류. 잠시 후 다시 시도하세요' 탈퇴 계정: '탈퇴 처리된 계정입니다' 네트워크 오류: '인터넷 연결을 확인하세요' 지점 미선택: '지점을 선택해주세요' 잘못된 자격증명: '이메일 또는 비밀번호를 확인하세요' | M3: Supabase Auth + React Zustand 스토어 authStore.ts: initAuthListener() 세션 관리 비밀번호 변경: AppHeader 모달 → supabase.auth.updateUser() 감사로그: 로그인 실패/로그아웃 시 자동 기록 | O3: API-001 | P3: 개발완료 | R3: 로그인 | S3: /api/v1/auth/login | T3: Supabase Auth 전환 완료 (2026-03-12). 비밀번호 변경 모달 구현 (2026-03-13). 로그인 유지 + 세션 자동관리 + 감사로그 연동 | U3: 5
A4: ▼ SCR-002 | B4: 대시보드 (1개 기능)
A5: FN-002 | B5: 대시보드 통계 조회 | C5: 대시보드 | D5: Web | E5: Critical | F5: 지점별 핵심 KPI 대시보드 (회원/매출/출석 요약) | G5: 1) 총회원/활성/만료임박/만료 카운트 2) 오늘 생일 회원 리스트 3) 미납 회원 리스트 4) 만료 예정 회원 5) 당월 매출 차트 | H5: SCR-002 | I5: 지점ID (JWT에서 추출) | J5: 통계 데이터, 리스트, 차트 데이터 | K5: 1) 통계 카드: 페이지 진입 시 + 5분 주기 자동 갱신 2) 만료임박: D-7 이내 카운트, D-3 이내 긴급(빨간색), D-0 만료 처리 3) 미납: 결제예정일 초과 + 미결제 → 미납, 30일 초과 시 장기미납 표시 4) 차트: 페이지 진입 시 1회 조회 (BarChart/PieChart/LineChart) 5) 통계 카드 클릭 시 해당 목록으로 이동 (status 필터 자동 적용) 6) 지점별 데이터 격리 – branch_id 기준 필터 필수 7) 알림 리스트: 실시간 polling 30초 주기 | L5: 데이터 로드 실패: 각 섹션 독립 에러 표시 + 재시도 버튼 빈 데이터: '아직 데이터가 없습니다' Empty State UI 지점 미설정: '지점 정보를 설정하세요' 안내 네트워크 단절: 마지막 갱신 시각 표시 + 수동 갱신 버튼 | M5: TanStack Query (5분 refetchInterval, staleTime 설정) Recharts – BarChart, PieChart, LineChart useNavigate() + query string으로 필터 목록 이동 Skeleton 로딩 UI (카드/차트 영역) RefreshCw 아이콘 수동 갱신 버튼 date-fns 날짜 계산 (D-day) | O5: API-003 | P5: 개발완료 | R5: 대시보드 | S5: /api/v1/dashboard/stats | T5: 실 데이터 차트 연동 완료. soft delete 필터 적용. 클릭 네비게이션 구현 (2026-03-13) | U5: 8
A6: ▼ SCR-010 | B6: 회원 목록 (2개 기능)
A7: FN-003 | B7: 회원 목록 조회/검색/필터 | C7: 회원관리 | D7: Web | E7: Critical | F7: 회원 검색, 필터, 페이지네이션 목록 조회 | G7: 1) 이름/연락처/회원번호 검색 (300ms debounce) 2) 상태/성별/담당자 필터 조합 3) 컬럼 정렬 4) 페이지당 20/50/100건 5) 엑셀 다운로드 | H7: SCR-010 | I7: 검색어, 필터 조건, 페이지 번호, 정렬 기준 | J7: 회원 목록 (이름/연락처/상태/이용권/담당자) | K7: 1) 검색: 이름 부분일치(2자 이상), 연락처 숫자만 추출 후 부분일치, 회원번호 완전일치 2) 검색 debounce 300ms 적용 3) 모든 필터는 AND 조합, 탭 필터와 상세 필터 동시 적용 4) 회원 상태: 활성/만료/예정/임박(D-30 이내)/홀딩/미등록 정의 5) 일괄 처리 최대 100명 동시 선택 6) 삭제 회원 기본 미표시, 옵션으로 표시 전환 가능 7) 권한별 조회 범위 제한 (FC: 담당 회원만, 스태프: 조회만) | L7: 검색 결과 없음: '조건에 맞는 회원이 없습니다' Empty State 필터 오류: 필터 초기화 버튼 항상 노출 API 오류: '회원 목록을 불러오지 못했습니다. 재시도' 버튼 일괄 처리 100명 초과: '최대 100명까지 선택 가능합니다' 권한 없음: 해당 기능 버튼 비활성화 처리 | M7: TanStack Query – GET /api/v1/members (캐싱) useDebounce() 훅 (300ms) DataTable 컴포넌트 (정렬/페이지네이션/다중선택) URL 쿼리 파라미터로 필터 상태 동기화 xlsx 라이브러리 – 엑셀 다운로드 Checkbox 다중선택 + 일괄 처리 드롭다운 | O7: API-007 | P7: 개발완료 | R7: 회원 목록 | S7: /api/v1/members | T7: 서버사이드 페이지네이션/정렬/필터 완료. 상태 변경 모달 (window.prompt→셀렉트) 개선 (2026-03-13) | U7: 8
A8: FN-004 | B8: 회원 등록 | C8: 회원관리 | D8: Web | E8: Critical | F8: 신규 회원 등록 | G8: 1) 필수: 이름, 성별, 연락처 2) 선택: 이메일, 주소, 생년월일, 메모 3) 담당 FC 배정 4) 연락처 중복 체크 | H8: SCR-010 | I8: 이름, 성별, 생년월일, 연락처, 이메일, 주소, 메모, 담당자ID | J8: 등록된 회원 정보 | K8: 1) 필수 입력: 이름(2~20자, 한글/영문), 성별, 연락처(010-XXXX-XXXX), 회원구분 2) 연락처: 동일 지점 내 중복 불가 (API 중복확인) 3) 회원번호 자동 생성: 지점코드-YYMMDD-순번 4) 출석번호 자동 생성: 4자리 랜덤 (중복 체크) 5) 기본 상태: '미등록' (이용권 구매 시 '활성'으로 자동 전환) 6) 프로필 사진: JPG/PNG, 5MB 이하 7) 생년월일: 미래 날짜 입력 불가 8) 이메일: RFC 5322 형식 검증 | L8: 연락처 중복: '이미 등록된 연락처입니다 (지점 내)' 이름 형식 오류: '이름은 2~20자 한글 또는 영문으로 입력하세요' 연락처 형식 오류: '010-XXXX-XXXX 형식으로 입력하세요' 파일 크기 초과: '이미지 파일은 5MB 이하만 업로드 가능합니다' 저장 실패: '회원 등록에 실패했습니다. 다시 시도하세요' 취소 시: '변경사항이 있습니다. 정말 나가시겠습니까?' 확인 다이얼로그 | M8: React Hook Form + Zod 스키마 (2단계 폼) useMutation – POST /api/v1/members Kakao 주소 API 연동 (주소 검색 버튼) 이미지 업로드 – FileReader + presigned URL 연락처 입력 자동 하이픈 포맷팅 취소 확인 useBlocker() (React Router v6) | O8: API-009 | P8: 개발완료 | R8: 회원 목록 | S8: /api/v1/members | U8: 8
A9: ▼ SCR-011 | B9: 회원 상세 (2개 기능)
A10: FN-005 | B10: 회원 정보 수정 | C10: 회원관리 | D10: Web | E10: High | F10: 기존 회원 정보 수정 | G10: 1) 기존 데이터 프리필 2) 변경 필드 강조 3) 변경 이력 자동 기록 4) 담당자 변경 가능 | H10: SCR-011 | I10: 수정할 회원 정보 | J10: 수정된 회원 정보 | K10: 1) 수정 시 변경 전/후 값 audit log 자동 저장 2) 변경자 + 변경일시 자동 기록 3) 연락처 변경 시 재중복 체크 필수 4) 변경된 필드 강조 표시 (초록색 border) 5) 미납 건 있는 회원 삭제 불가 6) 유효 이용권 있는 회원 삭제 불가 (환불 선행 필요) 7) 소프트 삭제 (is_deleted 플래그), 삭제 후 30일 복구 가능 | L10: 수정 중 다른 관리자 수정 감지: '다른 사용자가 수정 중입니다' 미납 상태 삭제 시도: '미납 건이 있어 삭제할 수 없습니다' 유효 이용권 삭제 시도: '유효한 이용권이 있습니다. 환불 후 삭제 가능' 저장 실패: '회원 정보 수정에 실패했습니다' 연락처 중복: '이미 등록된 연락처입니다' | M10: React Hook Form + defaultValues 초기값 설정 useMutation – PATCH /api/v1/members/:id dirtyFields로 변경 필드 감지 + 강조 표시 Optimistic update (TanStack Query) 삭제 확인 AlertDialog (shadcn/ui) Kakao 주소 API 연동 | O10: API-010 | P10: 개발완료 | R10: 회원 상세 | S10: /api/v1/members/:id | U10: 6
A11: FN-006 | B11: 회원 상세 조회 | C11: 회원관리 | D11: Web | E11: High | F11: 회원 프로필 + 탭별 상세 정보 조회 | G11: 1) 프로필: 기본 정보 + 사진 2) 이용권 탭: 보유 이용권 목록 3) 출석 탭: 히트맵 + 리스트 4) 결제 탭: 결제 이력 5) 체성분 탭: 측정 기록 + 차트 6) 메모 탭: 상담/메모 | H11: SCR-011 | I11: 회원ID | J11: 회원 전체 정보 (프로필+이용권+출석+결제+체성분+메모) | K11: 1) 기본정보 탭: 페이지 진입 시 즉시 로드 2) 나머지 탭: 클릭 시 lazy 로드 (React.lazy + Suspense) 3) 탭 전환 시 이전 데이터 캐싱 유지 4) 탭 상태 URL 파라미터 유지 (?tab=attendance) 5) 출석 히트맵: 최근 6개월, 1회=연한색, 3회 이상=진한색 6) 이용권 유효 → 상단, 만료 → 하단 접힘, D-7 주황 경고 7) 회원 미존재 시 404 페이지 리다이렉트 | L11: 존재하지 않는 회원 ID: 404 페이지 이동 탭 데이터 로드 실패: 해당 탭 내 에러 메시지 + 재시도 버튼 네트워크 오류: 마지막 캐시 데이터 표시 + 경고 배너 권한 없는 탭 접근: 탭 비활성화 처리 | M11: TanStack Query – GET /api/v1/members/:id React.lazy() + Suspense 탭별 코드 스플리팅 useSearchParams()로 탭 URL 동기화 출석 히트맵 – react-calendar-heatmap Skeleton 로딩 UI (탭 콘텐츠 영역) date-fns – D-day, 날짜 포맷 | O11: API-008 | P11: 개발완료 | R11: 회원 상세 | S11: /api/v1/members/:id | T11: Supabase 실데이터 전환 완료. 메모/목표 탭 구현 (2026-03-13) | U11: 6
A12: ▼ SCR-014 | B12: 체성분 (1개 기능)
A13: FN-007 | B13: 체성분 기록/분석 | C13: 회원관리 | D13: Web | E13: High | F13: 회원 체성분 측정 기록 입력 및 변화 추이 분석 | G13: 1) 체중/골격근/체지방률/BMI 등 입력 2) 측정일 기준 시계열 차트 3) 목표 대비 달성률 게이지 | H13: SCR-014 | I13: 체중, 골격근, 체지방률, 측정일 | J13: 체성분 이력, 변화 차트 | K13: 1) 체중 유효 범위: 20~300kg, 골격근량: 5~80kg, 체지방률: 3~60% 2) BMI 자동 계산: 체중(kg) / 신장(m)² 3) 범위 초과 시: 경고 후 저장 허용 (강제 차단 아님) 4) 동일 날짜 기존 기록 존재 시 '덮어쓰기' 확인 모달 5) 미래 날짜 측정 불가 6) 목표 체중/체지방률 대비 달성률 게이지 표시 7) 달성 시 축하 메시지 표시 | L13: 범위 초과 입력: '입력값이 정상 범위를 벗어났습니다. 그래도 저장하시겠습니까?' 미래 날짜: '미래 날짜에는 측정 기록을 입력할 수 없습니다' 동일 날짜 중복: '해당 날짜에 이미 기록이 있습니다. 덮어쓰시겠습니까?' 저장 실패: '체성분 기록 저장에 실패했습니다' 신장 미입력: 'BMI 계산을 위해 회원 신장을 먼저 입력하세요' | M13: React Hook Form + Zod (범위 검증 + 경고) useMutation – POST /api/v1/members/:id/body-composition Recharts LineChart – 시계열 추이 차트 진행률 게이지 – shadcn/ui Progress 확인 모달 – AlertDialog (덮어쓰기) date-fns – 날짜 비교/포맷 | O13: API-008 | P13: 개발완료 | R13: 체성분 분석 | S13: /api/v1/members/:id | U13: 2
A14: ▼ SCR-020 | B14: 출석 (1개 기능)
A15: FN-008 | B15: 출석 기록 조회 | C15: 출석관리 | D15: Web | E15: High | F15: 회원 출석 현황 조회 (일별/주별/월별) | G15: 1) 날짜 필터 (일/주/월 뷰) 2) 출석 유형(일반/PT/GX) 필터 3) 타지점 출석 표시 4) 키오스크/앱 체크인 구분 | H15: SCR-020 | I15: 날짜 범위, 필터 조건 | J15: 출석 목록, 통계 | K15: 1) 출석 유형: 일반(키오스크/앱), PT, GX, 수동(관리자) 2) 이용권 만료 회원: 출입 차단 (센터 설정에 따라 경고만 가능) 3) 미납 회원: 센터 설정에 따라 허용/경고/차단 4) 타지점 출석: 전지점 이용권 보유 시 허용, 원지점에 알림 5) 실시간 팝업: 5초 자동 종료, 거부 시 빨간색 팝업 6) 일별/주별/월별 뷰 제공 7) 수동 출석: 관리자 권한, 사유 필수 입력 | L15: 이용권 만료 회원 체크인: '이용권이 만료되었습니다. 관리자에게 문의하세요' 미납 회원 체크인: '미납이 있습니다. 결제 후 이용 가능합니다' 타지점 전용 이용권: '이 지점은 이용 불가한 이용권입니다' 데이터 로드 실패: '출석 기록을 불러오지 못했습니다' 날짜 범위 초과: '조회 가능한 최대 기간은 1년입니다' | M15: TanStack Query – GET /api/v1/attendance WebSocket or SSE – 실시간 체크인 팝업 DataTable + 날짜 필터 (date-fns) 일별/주별/월별 뷰 탭 전환 유형별 색상 Badge (일반/PT/GX/수동) 수동 출석 등록 모달 (React Hook Form) | O15: API-013 | P15: 개발완료 | R15: 출석 기록 | S15: /api/v1/attendance | T15: 주간/월간 통계 실 데이터 전환 완료 (2026-03-12). 날짜 필터 DataTable 연동 개선 (2026-03-13) | U15: 2
A16: ▼ SCR-021 | B16: 일정 (1개 기능)
A17: FN-009 | B17: 일정 관리 | C17: 출석관리 | D17: Web | E17: High | F17: PT/GX 일정 캘린더 관리 | G17: 1) 월/주/일 캘린더 뷰 전환 2) 드래그앤드롭 일정 이동 3) 트레이너별 색상 구분 4) 일정 충돌 감지 | H17: SCR-021 | I17: 일정 제목, 시간, 트레이너, 회원, 룸 | J17: 캘린더 일정 목록 | K17: 1) 일정 충돌: 동일 시간대 + 동일 트레이너 or 동일 룸 → 경고 2) 1:1 PT: 트레이너당 동시 1건만 등록 가능 3) GX: 룸 수용인원 초과 불가 4) 과거 일정 수정/삭제 불가 5) 당일 일정: 시작 2시간 전까지 수정 가능 6) 반복 일정: 개별/전체 수정 선택 7) PT 예약 취소: 24시간 전 무료, 당일 취소 1회 차감, 노쇼 1회 차감 + 패널티 8) 페널티 3회 누적 → 관리자 알림 | L17: 일정 충돌: '해당 시간에 이미 일정이 있습니다 (트레이너/룸 충돌)' 수용인원 초과: '룸 수용 인원을 초과했습니다' 과거 일정 수정 시도: '과거 일정은 수정할 수 없습니다' 당일 2시간 내 수정: '수업 2시간 전부터 수정이 불가합니다' 반복 일정 수정: '이 일정만 수정' / '이후 모든 일정 수정' 선택 모달 | M17: FullCalendar React (@fullcalendar/react + daygrid/timegrid/interaction 플러그인) 드래그앤드롭 일정 이동/리사이즈 주/월/일 뷰 전환 일정 추가/수정 모달 Supabase 연동 CRUD | P17: 개발완료 | R17: 일정 관리 | S17: =IFERROR(VLOOKUP(O17,API명세서!A:D,4,FALSE()),"") | T17: FullCalendar 드래그앤드롭 리뉴얼 완료 (2026-03-13). 기존 커스텀 캘린더→FullCalendar 전환 | U17: 2
A18: ▼ SCR-030 | B18: 매출 (2개 기능)
A19: FN-010 | B19: 매출 조회/통계 | C19: 매출관리 | D19: Web | E19: Critical | F19: 매출 현황 조회 및 통계 요약 | G19: 1) 기간별 필터 (프리셋: 오늘/이번주/이번달/커스텀) 2) 유형별 필터 (이용권/PT/상품/기타) 3) 상태별 필터 (완료/환불/미납) 4) 통계 카드: 총매출/현금/카드/마일리지 5) 엑셀 다운로드 | H19: SCR-030 | I19: 기간, 유형, 상태, 페이지 | J19: 매출 목록, 통계 요약 | K19: 1) 총매출 = 현금 + 카드 + 마일리지 - 환불 2) 순매출 = 총매출 - 부가세 (10%) 3) 일/주/월/연 단위 집계, 지점별 독립 집계 4) 환불 정책: 7일 이내 전액, 7일 초과~이용 전 위약금 10%, 이용 후 잔여일 일할 계산 5) 미납 7일 경과 시 SMS 자동 발송 (설정 시) 6) 미납 30일 경과 시 장기미납 분류 7) 기간 프리셋: 오늘/이번주/이번달/커스텀 | L19: 날짜 범위 오류: '시작일이 종료일보다 클 수 없습니다' 데이터 없음: 해당 기간 매출 없음 Empty State 엑셀 다운로드 실패: '파일 생성에 실패했습니다' 권한 없음: 매출 데이터 접근 불가 (FC 이하) 네트워크 오류: 마지막 조회 데이터 캐시 유지 | M19: TanStack Query – GET /api/v1/sales Recharts – BarChart, PieChart (매출 분포) date-fns – 기간 프리셋, 날짜 포맷 xlsx 라이브러리 – 엑셀 다운로드 금액 포맷 – Intl.NumberFormat (천단위 콤마) DataTable (23개 컬럼, 가로 스크롤) | O19: API-015 | P19: 개발완료 | R19: 매출 조회 | S19: /api/v1/sales | T19: 매출 통계 Supabase 실데이터 연동 완료. 엑셀 다운로드 구현 (2026-03-13) | U19: 7
A20: FN-011 | B20: POS 상품 선택/결제 | C20: 매출관리 | D20: Web | E20: Critical | F20: POS 상품 선택 및 장바구니 관리 | G20: 1) 카테고리별 상품 그리드 2) 상품 클릭 → 장바구니 추가 3) 수량 조절/삭제 4) 합계 자동 계산 | H20: SCR-030 | I20: 상품 선택, 수량 | J20: 장바구니 목록, 합계 | K20: 1) 상품 그리드: 카테고리 탭 + 검색으로 필터 2) 재고 0인 상품 자동 비활성화 표시 3) 재고 5개 이하 경고 표시 (노란 뱃지) 4) 비회원 결제 시 마일리지 적립/사용 불가 5) 장바구니 수량 변경 시 즉시 소계 재계산 6) 부가세 10% 자동 계산 (포함/별도 상품별 설정) 7) 회원 검색: 이름/전화번호 검색 | L20: 재고 없는 상품 추가: '재고가 없는 상품입니다' 장바구니 비어있음: '상품을 선택해주세요' 회원 검색 결과 없음: '검색된 회원이 없습니다' 수량 0 이하 입력: '수량은 1 이상이어야 합니다' 상품 판매 중지: '현재 판매 중지된 상품입니다' | M20: Zustand cartStore (장바구니 상태 관리) TanStack Query – GET /api/v1/products (카테고리별) 실시간 소계/합계 계산 (useMemo) 회원 검색 Combobox (debounce 300ms) 상품 이미지 lazy loading Badge 컴포넌트 – 재고 상태 표시 | O20: API-018 | P20: 개발완료 | R20: 매출 조회 | S20: /api/v1/products | U20: 7
A21: ▼ SCR-032 | B21: POS 결제 (1개 기능)
A22: FN-012 | B22: POS 결제 처리 | C22: 매출관리 | D22: Web | E22: Critical | F22: 결제 수단 선택 및 결제 실행 | G22: 1) 현금/카드/마일리지/복합결제 2) 회원 검색 → 마일리지 잔액 표시 3) 결제 확인 모달 4) 영수증 출력 옵션 | H22: SCR-032 | I22: 결제수단, 금액, 회원ID | J22: 결제 결과, 영수증 | K22: 1) 혼합결제: 각 수단 합계 = 총 결제금액 일치 필수 2) 마일리지: 잔액 초과 사용 불가, 최소 1,000원 3) 마일리지 최대 사용: 결제금액의 50% (센터 설정) 4) 현금 결제: 거스름돈 자동 계산 5) 당일 취소: 즉시 환불, 익일 이후: 환불 프로세스 6) 결제 완료 시 재고 자동 차감 7) 마일리지 자동 적립 (설정된 적립률 기준) 8) 영수증 자동 생성 + 프린트/문자 발송 | L22: 혼합결제 금액 불일치: '결제 수단 합계가 총 결제금액과 다릅니다' 마일리지 잔액 초과: '사용 가능한 마일리지가 부족합니다 (잔액: N원)' 결제 실패: '결제 처리에 실패했습니다. 다시 시도하세요' 카드 단말기 오류: '카드 단말기 연결을 확인하세요' 재고 부족: '결제 처리 중 재고가 부족해졌습니다' | M22: useMutation – POST /api/v1/sales/payment 결제 수단별 금액 입력 폼 (React Hook Form) 거스름돈 실시간 계산 (useMemo) 마일리지 잔액 조회 – GET /api/v1/members/:id/mileage 영수증 컴포넌트 – react-to-print 결제 성공 애니메이션 (Framer Motion) | O22: API-016 | P22: 개발완료 | R22: POS 결제 | S22: /api/v1/sales | U22: 4
A23: ▼ SCR-040 | B23: 상품 (2개 기능)
A24: FN-013 | B24: 상품 목록 조회 | C24: 상품관리 | D24: Web | E24: High | F24: 이용권/PT/GX/기타 상품 목록 조회 | G24: 1) 카테고리 필터 2) 상태(판매중/중지) 필터 3) 키오스크 노출 토글 | H24: SCR-040 | I24: 카테고리, 상태 | J24: 상품 목록 | K24: 1) 상품 카테고리: 시설이용권/수강권(PT)/수강권(GX)/대여/기타 2) 가격: 0원(무료) ~ 99,999,999원 3) 현금가 ≤ 카드가 권장 (강제 아님) 4) 판매 중지 상품: POS/키오스크 모두 비활성화 5) 키오스크 노출 ON/OFF 별도 관리 6) 상태별 탭: 전체/판매중/판매중지/재고소진 7) 검색: 상품명 부분일치 | L24: 검색 결과 없음: '검색된 상품이 없습니다' Empty State 데이터 로드 실패: '상품 목록을 불러오지 못했습니다' 권한 없음: 상품 등록/수정/삭제 버튼 비활성화 (FC 이하) 삭제 시도 (결제 이력 있음): '결제 이력이 있어 삭제할 수 없습니다' | M24: TanStack Query – GET /api/v1/products DataTable (정렬, 페이지네이션) 카테고리 탭 필터 (URL 쿼리 파라미터 동기화) xlsx 라이브러리 – 상품 목록 다운로드 상품 상태 Badge 색상 구분 Skeleton 로딩 UI | O24: API-018 | P24: 개발완료 | R24: 상품 목록 | S24: /api/v1/products | U24: 3
A25: FN-014 | B25: 상품 등록/수정 | C25: 상품관리 | D25: Web | E25: High | F25: 신규 상품 등록 및 기존 상품 수정 | G25: 1) 카테고리/이름/현금가/카드가/기간 입력 2) 키오스크 노출 설정 3) 상품명 중복 체크 | H25: SCR-040 | I25: 카테고리, 이름, 가격, 기간 | J25: 등록/수정된 상품 정보 | K25: 1) 상품명: 동일 카테고리 내 중복 불가 2) 가격: 0 이상 정수, 음수 불가 3) 홀딩 설정: 최대 N일, 최대 N회 (상품별 개별 설정) 4) 홀딩 시 잔여일 정지 (소진 아님) 5) 만료 후 재활성화 불가 (재구매 필요) 6) 이용 시간 설정: 요일별/시간대별 이용 가능 설정 7) 부가세 포함/별도 선택 8) 이미지: JPG/PNG, 5MB 이하 | L25: 상품명 중복: '동일 카테고리에 같은 이름의 상품이 있습니다' 가격 음수/문자 입력: '가격은 0 이상의 숫자만 입력 가능합니다' 이미지 형식 오류: 'JPG 또는 PNG 파일만 업로드 가능합니다' 이미지 크기 초과: '이미지 파일은 5MB 이하만 가능합니다' 저장 실패: '상품 저장에 실패했습니다' 취소 시: '변경사항이 있습니다. 나가시겠습니까?' | M25: React Hook Form + Zod (상품 유형별 동적 스키마) useMutation – POST/PATCH /api/v1/products 이미지 업로드 – FileReader + presigned URL 이용 시간 설정 – 요일별 체크박스 + 시간 범위 선택 상품 유형 선택 시 폼 필드 동적 변경 Tabs 컴포넌트 (기본/기간/추가설정) | O25: API-019 | P25: 개발완료 | R25: 상품 목록 | S25: /api/v1/products | U25: 3
A26: ▼ SCR-050 | B26: 락커 (2개 기능)
A27: FN-015 | B27: 락커 현황 조회 | C27: 시설관리 | D27: Web | E27: High | F27: 구역별 락커 배정 현황 조회 (색상 그리드) | G27: 1) 구역별 탭 2) 색상 상태 (사용중/빈/만료임박/고장) 3) 클릭 시 상세 모달 | H27: SCR-050 | I27: 구역 | J27: 락커 그리드 데이터 | K27: 1) 락커 상태: 사용중/빈/만료임박/고장 4가지 2) D-3 이내: 만료임박 (노란색), D-0: 만료 (빨간색) 3) D+3 초과: 자동 해제 여부 센터 설정에 따름 4) 고장 상태 락커: 배정 불가 5) 구역별 필터링, 그리드/리스트 뷰 전환 6) 통계: 전체/사용중/빈/만료임박/고장 카운트 | L27: 데이터 로드 실패: '락커 현황을 불러오지 못했습니다' 구역 없음: '등록된 구역이 없습니다. 구역을 먼저 설정하세요' 권한 없음: 배정/반납 버튼 비활성화 | M27: TanStack Query – GET /api/v1/lockers 그리드/리스트 뷰 전환 토글 상태별 색상 코딩 (CSS variables) 구역별 필터 Select 컴포넌트 Skeleton 로딩 (그리드 레이아웃) date-fns – D-day 계산 | O27: API-020 | P27: 개발완료 | R27: 락커 현황 | S27: /api/v1/lockers | U27: 4
A28: FN-016 | B28: 락커 배정/관리 | C28: 시설관리 | D28: Web | E28: High | F28: 락커 배정/해제/일괄 관리 | G28: 1) 회원 검색 → 빈 락커 선택 → 배정 2) 만료일 설정 3) 일괄 해제 (만료 락커) 4) 고장 등록 | H28: SCR-050 | I28: 회원ID, 락커번호, 만료일 | J28: 배정 결과 | K28: 1) 1회원 1락커 (동일 유형 내) 2) 배정 시 만료일 필수 (상품 기간 연동 or 수동 입력) 3) 이미 배정된 락커 재배정 불가 4) 배정 취소: 배정일 당일만 가능 5) 일괄 해제: 만료+N일 초과 건 일괄 처리 6) 고장 등록 시 해당 락커 배정 불가 7) 수리 완료 → 사용가능으로 복원 | L28: 이미 배정된 락커: '이미 사용 중인 락커입니다' 만료일 미입력: '만료일을 입력해주세요' 1인 1락커 초과: '해당 회원에게 이미 배정된 락커가 있습니다' 당일 이후 취소 시도: '배정일 당일만 취소 가능합니다' API 오류: '락커 배정 처리에 실패했습니다' | M28: useMutation – PATCH /api/v1/lockers/:id 회원 검색 Combobox (배정 시) DatePicker – 만료일 선택 (react-day-picker) 일괄 해제 – 체크박스 다중선택 + Confirm 모달 고장 등록/해제 AlertDialog 반납 처리 Confirm 다이얼로그 | O28: API-021 | P28: 개발완료 | R28: 락커 현황 | S28: /api/v1/lockers/:id | U28: 4
A29: ▼ SCR-052 | B29: RFID (1개 기능)
A30: FN-017 | B30: RFID 관리 | C30: 시설관리 | D30: Web | E30: Medium | F30: RFID 카드 등록/해제/이력 조회 | G30: 1) 카드 번호 스캔/수동 입력 2) 회원-카드 매핑 3) 분실 처리 4) 이력 조회 | H30: SCR-052 | I30: 카드 번호, 회원ID | J30: 매핑 결과, 이력 | K30: 1) 1회원 1카드 원칙 (활성 카드 기준) 2) 카드 번호: 10자리 영숫자 형식 3) 분실 신고 → 기존 카드 비활성화 → 신규 발급 4) 카드 반납 시 초기화 후 재사용 가능 5) RFID 태그 → 회원 조회 → 이용권 유효 확인 → 출입 허용/거부 6) 미등록 카드: '등록되지 않은 카드' 즉시 표시 7) 만료 회원: 센터 설정에 따라 허용/차단 | L30: 1인 1카드 초과: '해당 회원에게 이미 활성 카드가 등록되어 있습니다' 카드 번호 형식 오류: '카드 번호는 10자리 영숫자로 입력하세요' 중복 카드 번호: '이미 등록된 카드 번호입니다' 미등록 카드 태그: '등록되지 않은 카드입니다' 삭제 시 확인: '삭제하려면 카드 번호를 입력하세요' (확인 텍스트 입력) | M30: TanStack Query – GET/POST/PATCH/DELETE /api/v1/rfid RFID 시뮬레이션 – WebSocket 이벤트 삭제 확인 – 텍스트 입력 방식 (Confirmation Input) 사용 이력 모달 – 페이지네이션 테이블 카드 번호 자동 대문자 변환 상태 Badge (활성/분실/반납/비활성) | P30: 개발완료 | R30: RFID 관리 | S30: =IFERROR(VLOOKUP(O30,API명세서!A:D,4,FALSE()),"") | U30: 3
A31: ▼ SCR-053 | B31: 룸 (1개 기능)
A32: FN-018 | B32: 룸 관리 | C32: 시설관리 | D32: Web | E32: Medium | F32: GX룸/PT룸 등록/수정/삭제 | G32: 1) 룸 CRUD 2) 수용 인원 설정 3) 예약 가능 시간대 설정 | H32: SCR-053 | I32: 룸명, 유형, 수용인원, 시간대 | J32: 룸 정보 | K32: 1) 룸명: 고유값, 2~20자 2) 수용 인원: 1~100명 3) 유형: PT룸/GX룸/다목적 4) 예약 가능 시간: 요일별 개별 설정 5) 미래 예약 존재 시 삭제 불가 6) 삭제 시 관련 일정에서 룸 정보 자동 제거 7) 비활성화: 신규 예약 차단 (기존 예약 유지) | L32: 룸명 중복: '이미 사용 중인 룸 이름입니다' 수용 인원 범위 오류: '수용 인원은 1~100명으로 입력하세요' 예약 있는 룸 삭제 시도: '미래 예약이 있어 삭제할 수 없습니다' 저장 실패: '룸 정보 저장에 실패했습니다' | M32: TanStack Query – GET/POST/PATCH/DELETE /api/v1/rooms React Hook Form + Zod 룸 폼 검증 요일별 시간 설정 UI (요일 체크박스 + 시간 범위) 배치도 탭 – 드래그 배치 (react-dnd) 삭제 확인 AlertDialog 상태 토글 Switch 컴포넌트 | P32: 개발완료 | R32: 룸 관리 | S32: =IFERROR(VLOOKUP(O32,API명세서!A:D,4,FALSE()),"") | U32: 2
A33: ▼ SCR-060 | B33: 직원 (2개 기능)
A34: FN-019 | B34: 직원 목록 조회 | C34: 직원관리 | D34: Web | E34: High | F34: 직원 검색/필터/목록 조회 | G34: 1) 이름/연락처 검색 2) 역할/상태 필터 3) 테이블 정렬 | H34: SCR-060 | I34: 검색어, 필터 | J34: 직원 목록 | K34: 1) 역할 체계: 최고관리자/센터장/매니저/FC/스태프/조회전용 2) 역할별 기본 권한 자동 배정 3) 고용 유형: 정규직(월급)/계약직(월급+계약기간)/시간제(시급) 4) 퇴사 처리 시 관리자 계정 자동 비활성화 5) 담당 회원 재배정 알림 자동 발송 6) 검색: 이름 부분일치, debounce 300ms 7) 권한별 조회 범위 (FC: 본인 담당만) | L34: 검색 결과 없음: '검색된 직원이 없습니다' Empty State 권한 없음: 직원 등록/수정/삭제 버튼 비활성화 퇴사 처리 확인: '퇴사 처리하면 계정이 비활성화됩니다. 진행하시겠습니까?' 데이터 로드 실패: '직원 목록을 불러오지 못했습니다' | M34: TanStack Query – GET /api/v1/staff DataTable (정렬, 필터, 다중선택) 퇴사 처리 AlertDialog + useMutation useDebounce() (300ms) 검색 역할별 색상 Badge 근태/급여 탭 컴포넌트 분리 | O34: API-022 | P34: 개발완료 | R34: 직원 목록 | S34: /api/v1/staff | T34: 페이지네이션 동작 수정 완료. 퇴사 처리 ConfirmDialog 구현 (2026-03-13) | U34: 5
A35: FN-020 | B35: 직원 등록/수정 | C35: 직원관리 | D35: Web | E35: High | F35: 신규 직원 등록 및 기존 직원 수정 | G35: 1) 이름/역할/연락처/입사일 입력 2) 관리자 계정 자동 생성 3) 근무 유형 설정 | H35: SCR-060 | I35: 이름, 역할, 연락처, 입사일 | J35: 등록된 직원 정보 | K35: 1) 이메일 기반 관리자 계정 자동 생성 (등록 시) 2) 역할 선택 시 기본 권한 자동 배정 3) 연락처: 동일 지점 내 중복 불가 4) 계약직: 계약 종료일 필수 입력 5) 수정 시 변경 이력 자동 기록 6) 프로필 사진: JPG/PNG, 5MB 이하 7) 퇴사 후 데이터: 6개월 보관 후 삭제 or 영구 보관 (설정) | L35: 이메일 중복: '이미 사용 중인 이메일입니다' 연락처 중복: '이미 등록된 연락처입니다' 계약 종료일 미입력 (계약직): '계약직은 계약 종료일이 필수입니다' 저장 실패: '직원 정보 저장에 실패했습니다' 취소 시: '변경사항이 있습니다. 나가시겠습니까?' | M35: React Hook Form + Zod (고용유형별 동적 스키마) useMutation – POST/PATCH /api/v1/staff 이미지 업로드 – presigned URL 역할 선택 시 권한 미리보기 표시 4섹션 Accordion 폼 (인적사항/근무/급여/계정) useBlocker() – 미저장 이탈 방지 | O35: API-023 | P35: 개발완료 | R35: 직원 목록 | S35: /api/v1/staff | U35: 5
A36: ▼ SCR-062 | B36: 급여 (2개 기능)
A37: FN-021 | B37: 급여 관리 | C37: 직원관리 | D37: Web | E37: High | F37: 월별 급여 현황 조회 및 관리 | G37: 1) 월별 급여 테이블 2) 기본급/인센티브/공제 내역 3) 지급 상태 관리 4) 합계/평균 요약 | H37: SCR-062 | I37: 연월 | J37: 급여 목록, 합계 | K37: 1) 실지급액 = 기본급 + 인센티브 + 수당 - 4대보험 - 소득세 2) 인센티브: PT 건당 커미션 (예: 30%, 센터 설정) 3) 급여 상태 흐름: 미정산 → 임시저장 → 확정대기 → 확정완료 4) 확정완료 상태: 수정 불가 (최고관리자 해제 가능) 5) 마감: 매월 25일 (센터 설정 가능) 6) 이의제기: 직원 제출 → 관리자 재검토 7) 권한: 센터장 이상만 전체 조회, FC는 본인만 | L37: 확정완료 후 수정 시도: '확정된 급여는 수정할 수 없습니다 (관리자 해제 필요)' 계산 오류: '급여 계산 중 오류가 발생했습니다' 마감 후 수정: '마감 처리된 급여입니다' 권한 없음: 타인 급여 조회 불가 데이터 없음: '해당 월의 급여 데이터가 없습니다' | M37: TanStack Query – GET /api/v1/payroll 월 선택 DatePicker (year/month) 급여 계산 로직 (useMemo) 상태 흐름 표시 – Step Indicator 확정 처리 AlertDialog DataTable (97명, 가상화 – react-virtual) | P37: 개발완료 | R37: 급여 현황 | S37: =IFERROR(VLOOKUP(O37,API명세서!A:D,4,FALSE()),"") | T37: 페이지네이션 동작 수정 완료. 필터/검색 시 페이지 리셋 (2026-03-13) | U37: 3
A38: FN-022 | B38: 급여명세서 조회 | C38: 직원관리 | D38: Web | E38: Medium | F38: 직원별 급여명세서 상세 조회 및 PDF 다운로드 | G38: 1) 직원/월 선택 2) 상세 항목별 표시 3) PDF 다운로드 | H38: SCR-062 | I38: 직원ID, 연월 | J38: 급여명세서 상세 | K38: 1) 명세서 조회 권한: 본인 or 센터장 이상 2) 확정완료 후 자동 생성 3) PDF 다운로드 지원 4) 이메일 자동 발송 (설정 시) 5) 이의제기 기능 제공 6) 조회 이력 로깅 | L38: 본인 외 명세서 접근: '조회 권한이 없습니다' 미확정 명세서: '아직 확정되지 않은 급여입니다' PDF 생성 실패: '명세서 PDF 생성에 실패했습니다' 이메일 발송 실패: '이메일 발송에 실패했습니다. 직접 다운로드 해주세요' | M38: TanStack Query – GET /api/v1/payroll/statement html2pdf.js – PDF 다운로드 명세서 상세 모달 (Dialog) 이의제기 Textarea 폼 이메일 발송 – POST /api/v1/payroll/statement/send 인쇄 – react-to-print | P38: 개발완료 | R38: 급여 현황 | S38: =IFERROR(VLOOKUP(O38,API명세서!A:D,4,FALSE()),"") | U38: 3
A39: ▼ SCR-070 | B39: 메시지 (2개 기능)
A40: FN-023 | B40: 메시지 발송 | C40: 메시지/마케팅 | D40: Web | E40: High | F40: SMS/카카오톡 메시지 발송 | G40: 1) 수신자 선택 (개별/그룹/전체) 2) 메시지 유형(SMS/LMS/카카오) 3) 변수 삽입 (#{이름}) 4) 발송 이력 조회 | H40: SCR-070 | I40: 수신자, 유형, 본문 | J40: 발송 결과 | K40: 1) SMS: 최대 90자 (초과 시 LMS 자동 전환) 2) LMS: 최대 2,000자 3) 카카오 알림톡: 최대 1,000자 4) 예약 발송: 최소 5분 후 ~ 최대 30일 후 5) 발송 전 비용 사전 표시 (SMS 70원, LMS 30원, 카카오 8원) 6) 치환 변수 지원: {이름}, {만료일}, {잔여일} 등 7) 중복 발송 방지: 동일 수신자 + 동일 내용 5분 내 차단 | L40: 수신자 없음: '수신자를 선택해주세요' 내용 없음: '메시지 내용을 입력해주세요' 잔액 부족: '발송 잔액이 부족합니다. 충전 후 이용하세요' 예약 시간 오류: '예약 시간은 5분 후부터 설정 가능합니다' 발송 실패: '메시지 발송에 실패했습니다 (N건 실패)' | M40: React Hook Form – 발송 폼 useMutation – POST /api/v1/messages/send 회원 선택 Combobox (다중선택, 검색) 글자 수 카운터 + 자동 LMS 전환 표시 치환 변수 삽입 버튼 DateTimePicker – 예약 발송 sonner 토스트 – 발송 결과 | P40: 개발완료 | R40: 메시지 발송 | S40: =IFERROR(VLOOKUP(O40,API명세서!A:D,4,FALSE()),"") | U40: 5
A41: FN-024 | B41: 자동 알림 설정 | C41: 메시지/마케팅 | D41: Web | E41: Medium | F41: 자동 알림 규칙 설정 | G41: 1) 만료 D-7/D-3/D-1 알림 2) 생일 축하 알림 3) 장기 미출석(30일) 알림 4) 규칙별 ON/OFF | H41: SCR-070 | I41: 규칙 설정 | J41: 알림 발송 | K41: 1) 13종 트리거 정의 (만료 D-7/D-3/D-1/당일, 생일, 장기미출석 30일 등) 2) 매일 오전 9시 스케줄러 실행 3) 중복 방지: 동일 회원 + 동일 규칙 → 1일 1회만 발송 4) 템플릿별 치환 변수 관리 5) 채널별 개별 ON/OFF 설정 (SMS/카카오) 6) 테스트 발송 기능 (본인 번호로) | L41: 템플릿 내 잘못된 변수: '유효하지 않은 치환 변수입니다: {변수명}' 발송 채널 미선택: '최소 1개의 발송 채널을 선택하세요' 테스트 발송 실패: '테스트 발송에 실패했습니다' 저장 실패: '알림 설정 저장에 실패했습니다' | M41: Toggle Switch 컴포넌트 (13종 ON/OFF) 템플릿 편집 모달 (Textarea + 변수 삽입) useMutation – PATCH /api/v1/auto-alarms 미리보기 렌더링 (치환 변수 치환 표시) 테스트 발송 버튼 + 로딩 상태 TanStack Query – GET /api/v1/auto-alarms | P41: 개발완료 | R41: 메시지 발송 | S41: =IFERROR(VLOOKUP(O41,API명세서!A:D,4,FALSE()),"") | U41: 5
A42: ▼ SCR-072 | B42: 쿠폰/마일리지 (2개 기능)
A43: FN-025 | B43: 쿠폰 관리 | C43: 메시지/마케팅 | D43: Web | E43: Medium | F43: 쿠폰 생성/발급/이력 관리 | G43: 1) 할인율/금액 쿠폰 생성 2) 유효기간 설정 3) 사용 한도 설정 4) 발급 대상 선택 5) 사용 이력 추적 | H43: SCR-072 | I43: 쿠폰 정보 | J43: 쿠폰 목록, 이력 | K43: 1) 쿠폰 유형: 정률(%)/정액(원)/무료 이용권 2) 유효기간: 특정 기간 or 발급일+N일 3) 사용 한도: 전체 N회 or 회원당 1회 4) 최소 주문 금액 설정 가능 5) 만료 쿠폰 자동 비활성화 (매일 자정) 6) 발급 건수 1개 이상인 쿠폰 삭제 불가 7) 쿠폰 코드: 8자리 영숫자 자동 생성 | L43: 발급 건수 있는 쿠폰 삭제: '발급된 쿠폰이 있어 삭제할 수 없습니다' 중복 쿠폰명: '이미 사용 중인 쿠폰 이름입니다' 할인율 범위 오류: '할인율은 1~100% 범위로 입력하세요' 최소 금액 이하 사용 시도: '최소 주문 금액(N원) 이상에서 사용 가능합니다' 만료 쿠폰 사용: '만료된 쿠폰입니다' 한도 초과: '쿠폰 사용 한도를 초과했습니다' | M43: React Hook Form + Zod (유형별 동적 폼) useMutation – POST/PATCH/DELETE /api/v1/coupons 쿠폰 코드 자동 생성 버튼 (nanoid) 발급 모달 – 대상 회원 다중선택 DataTable – 쿠폰 목록/발급 이력 만료일 자동 계산 (발급일+N일) | P43: 개발완료 | R43: 쿠폰 관리 | S43: =IFERROR(VLOOKUP(O43,API명세서!A:D,4,FALSE()),"") | U43: 2
A44: FN-026 | B44: 마일리지 관리 | C44: 메시지/마케팅 | D44: Web | E44: Medium | F44: 회원 마일리지 적립/사용 관리 | G44: 1) 마일리지 적립 (결제 시 자동/수동) 2) 마일리지 차감 3) 잔액 조회 4) 이력 조회 | H44: SCR-072 | I44: 회원ID, 금액, 유형 | J44: 마일리지 잔액, 이력 | K44: 1) 기본 적립률: 결제금액의 N% (센터 설정) 2) 유효기간: N개월 기본 12개월 3) 최소 사용: 1,000원 이상 4) 최대 사용: 결제금액의 50% (센터 설정) 5) 현금 전환 불가 6) 만료 마일리지 자동 소멸 (매일 자정) 7) 수동 처리: 적립/차감 사유 필수 입력 | L44: 잔액 부족: '사용 가능한 마일리지가 부족합니다 (잔액: N원)' 최소 사용 미달: '마일리지는 최소 1,000원 이상 사용 가능합니다' 최대 사용 초과: '결제금액의 50%까지만 마일리지 사용 가능합니다' 만료 마일리지: '만료된 마일리지는 사용할 수 없습니다' 수동 처리 사유 미입력: '사유를 입력해주세요' | M44: TanStack Query – GET /api/v1/mileage 수동 처리 모달 (React Hook Form) 적립/차감 이력 DataTable 정책 설정 폼 – useMutation PATCH /api/v1/mileage/policy 만료 예정 마일리지 경고 표시 Intl.NumberFormat – 마일리지 금액 포맷 | P44: 개발완료 | R44: 쿠폰 관리 | S44: =IFERROR(VLOOKUP(O44,API명세서!A:D,4,FALSE()),"") | T44: 마일리지 이력 탭 엑셀 다운로드 구현 완료 (2026-03-13). stub toast 제거 | U44: 2
A45: ▼ SCR-080 | B45: 계약/구독 (2개 기능)
A46: FN-027 | B46: 계약 등록 | C46: 계약/구독 | D46: Web | E46: Critical | F46: 단계별 계약 등록 위자드 | G46: 1) 회원 선택 → 상품 선택 → 기간/금액 설정 → 결제 → 확인 2) 할인 적용 3) 계약서 자동 생성 4) 결제 처리 | H46: SCR-080 | I46: 회원ID, 상품ID, 기간, 금액, 결제수단 | J46: 계약 정보, 영수증 | K46: 1) 계약 5단계: 회원선택 → 상품선택 → 기간/금액설정 → 결제 → 전자서명 2) 할인 최대 50%, 할인 사유 필수 입력 3) 할인 유형: 재등록/신규/이벤트/관리자 재량 4) 계약 완료 시 이용권 자동 생성 5) 매출 자동 등록 6) 마일리지 자동 적립 (설정 시) 7) 환영 메시지 자동 발송 (설정 시) 8) 계약서 PDF 자동 생성 및 저장 | L46: 회원 미선택: '회원을 먼저 선택해주세요' 상품 미선택: '상품을 1개 이상 선택해주세요' 할인 50% 초과: '할인율은 최대 50%까지 가능합니다' 할인 사유 미입력: '할인 사유를 입력해주세요' 서명 미완료: '전자서명을 완료해주세요' 결제 실패: '결제 처리에 실패했습니다' | M46: 5단계 Stepper 컴포넌트 useMutation – POST /api/v1/contracts 회원 검색 Combobox Canvas 전자서명 (센터측+고객측 양방향) 서명 데이터 Base64 저장 | O46: API-016 | P46: 개발완료 | R46: 계약 마법사 | S46: /api/v1/sales | T46: 전자서명 (양방향: 센터/고객) Canvas 구현 완료 (2026-03-13) | U46: 6
A47: FN-028 | B47: 구독 관리 | C47: 계약/구독 | D47: Web | E47: Medium | F47: 정기 구독 상품 관리 | G47: 1) 구독 상품 CRUD 2) 자동 결제 설정 3) 구독 현황 대시보드 4) 해지 처리 | H47: SCR-080 | I47: 구독 상품 정보 | J47: 구독 목록, 결제 이력 | K47: 1) 플랜: Starter(회원 200명, 지점 1개)/Pro(1,000명, 3개)/Enterprise(무제한) 2) 연간 결제 시 20% 할인 3) 다운그레이드: 현재 사용량이 하위 플랜 제한 이하일 때만 가능 4) 구독 취소: 현재 기간 만료까지 사용 가능 5) 사용량 초과 시 업그레이드 안내 6) 결제 수단 등록 필수 (카드) | L47: 다운그레이드 불가: '현재 회원 수(N명)가 하위 플랜 제한을 초과합니다' 결제 실패: '결제 처리에 실패했습니다. 카드 정보를 확인하세요' 구독 취소 확인: '취소 시 현재 기간(~날짜) 만료 후 서비스가 종료됩니다' 사용량 초과: '현재 플랜의 회원 수 한도에 도달했습니다. 업그레이드가 필요합니다' | M47: 플랜 비교 카드 UI (Starter/Pro/Enterprise) 사용량 Progress Bar (회원수, 지점수) 결제 수단 관리 – Stripe 또는 토스페이먼츠 플랜 변경 AlertDialog 인보이스 목록 DataTable 인보이스 PDF 다운로드 | P47: 개발완료 | R47: 계약 마법사 | S47: =IFERROR(VLOOKUP(O47,API명세서!A:D,4,FALSE()),"") | U47: 6
A48: ▼ SCR-090 | B48: 설정/권한 (5개 기능)
A49: FN-029 | B49: 시스템 설정 | C49: 설정 | D49: Web | E49: Medium | F49: 시스템 기본 설정 관리 | G49: 1) 센터명/영업시간/연락처 설정 2) 알림 기본값 설정 3) 테마 설정 | H49: SCR-090 | I49: 설정 값 | J49: 저장 결과 | K49: 1) 설정 변경 시 즉시 반영 (페이지 새로고침 불필요) 2) 이미지 업로드: JPG/PNG, 2MB 이하 3) 주소: Kakao 주소 API 연동 4) 카드 단말기 연결 테스트 기능 5) 출입문 목록 관리 (IoT 연동) 6) 설정 변경 이력 로깅 7) 7개 탭: 기본/출입문/키오스크/앱/알림/권한/기타 | L49: 이미지 크기 초과: '이미지는 2MB 이하만 업로드 가능합니다' 필수 항목 미입력: '센터명은 필수 입력 항목입니다' 저장 실패: '설정 저장에 실패했습니다' 카드 단말기 연결 실패: '단말기 연결을 확인하세요' 권한 없음: 설정 메뉴 접근 불가 (매니저 이하) | M49: TanStack Query – GET /api/v1/settings useMutation – PATCH /api/v1/settings Tabs 컴포넌트 (7탭, URL 동기화) 이미지 업로드 + 미리보기 Kakao 주소 API React Hook Form (탭별 폼 분리) 저장 성공 sonner 토스트 | P49: 개발완료 | R49: 설정 | S49: =IFERROR(VLOOKUP(O49,API명세서!A:D,4,FALSE()),"") | U49: 3
A50: FN-030 | B50: 권한 관리 | C50: 설정 | D50: Web | E50: Critical | F50: 역할별 메뉴/기능 권한 설정 | G50: 1) 6단계 역할 (최고관리자~조회전용) 2) 메뉴별 접근 권한 3) 기능별 읽기/쓰기/삭제 4) 변경 이력 로그 | H50: SCR-090 | I50: 역할, 권한 매트릭스 | J50: 권한 설정 결과 | K50: 1) 권한 매트릭스: 6역할 × 10메뉴 × CRUD 조합 2) 최고관리자 권한 수정 불가 3) 커스텀 역할 생성 가능 4) 변경 감지 후 저장 버튼 활성화 5) 변경 이력 로깅 6) 역할 복사 기능 | L50: 최고관리자 권한 수정 시도: '최고관리자 권한은 수정할 수 없습니다' 권한 충돌: '하위 역할에 상위 역할보다 높은 권한을 부여할 수 없습니다' 저장 실패: '권한 설정 저장에 실패했습니다' 역할 삭제 시 소속 직원 있음: '소속 직원이 있어 역할을 삭제할 수 없습니다' | M50: 권한 매트릭스 테이블 (Checkbox 그리드) localStorage 기반 권한 저장/로드 (permissions_{roleCode}) 역할별 userCount Supabase users 테이블에서 동적 집계 변경 감지 (dirtyFields) + 저장/초기화 전체 허용/차단 토글 버튼 커스텀 역할 추가/복사/삭제 모달 권한 충돌 검증 (삭제+미수정, 쓰기+미접근, 쓰기+미조회) | P50: 개발완료 | R50: 설정 | S50: =IFERROR(VLOOKUP(O50,API명세서!A:D,4,FALSE()),"") | U50: 3
A51: FN-031 | B51: 키오스크 설정 | C51: 설정 | D51: Web | E51: Medium | F51: 키오스크 디스플레이/동작 설정 | G51: 1) 로고/배경 업로드 2) 동작 시나리오 설정 3) 미리보기 | H51: SCR-090 | I51: 이미지 파일, 설정 값 | J51: 키오스크 설정 | K51: 1) 체크인 방식: QR코드/RFID/바코드/전화번호 2) 대기 화면: 로고+공지사항+광고 배너 슬라이드 3) 체크인 성공: TTS 음성 + 환영 메시지 4) 체크인 실패: TTS 음성 + 거부 사유 표시 5) 자동 로그아웃: 10초 (설정 가능) 6) 테마/폰트 크기 설정 가능 7) 기기별 설정 독립 관리 | L51: TTS 지원 불가 브라우저: TTS 없이 텍스트만 표시 이미지 업로드 실패: '이미지 업로드에 실패했습니다' 키오스크 연결 실패: '키오스크 기기와 연결할 수 없습니다' 저장 실패: '키오스크 설정 저장에 실패했습니다' | M51: Web Speech API (TTS – speechSynthesis) useMutation – PATCH /api/v1/kiosk/settings 이미지 업로드 + 미리보기 (배너/로고) 키오스크 미리보기 모달 4탭 (기본/화면/TTS/출입규칙) 자동 로그아웃 타이머 설정 Slider | P51: 개발완료 | R51: 설정 | S51: =IFERROR(VLOOKUP(O51,API명세서!A:D,4,FALSE()),"") | U51: 3
A52: FN-032 | B52: IoT 설정 | C52: 설정 | D52: Web | E52: Medium | F52: 출입문/체성분 기기 연동 설정 | G52: 1) 기기 등록/해제 2) 연결 상태 모니터링 3) 연결 테스트 | H52: SCR-090 | I52: 기기 정보 | J52: 기기 목록, 연결 상태 | K52: 1) IoT 출입문 연결 상태: 5분 주기 갱신 2) 오프라인 30분 이상 → 관리자 알림 3) 원격 개방: 관리자 권한만 가능 4) 비상 해제: 화재/정전 시 전체 개방 5) 출입 로그: 실시간 기록 6) 기기 유형: 게이트/카메라/체성분계/기타 | L52: IoT 기기 오프라인: '기기가 오프라인 상태입니다 (30분 이상)' 원격 개방 권한 없음: '원격 개방은 관리자 권한이 필요합니다' 원격 개방 확인: '출입문을 원격으로 개방하시겠습니까?' 기기 연결 실패: '기기 연결에 실패했습니다' 설정 저장 실패: 'IoT 설정 저장에 실패했습니다' | M52: WebSocket – 실시간 기기 상태 모니터링 TanStack Query (5분 refetchInterval) – 기기 상태 원격 개방 AlertDialog + useMutation 출입 로그 DataTable (실시간 갱신) 기기 상태 색상 표시 (온라인/오프라인/경고) 4탭 (게이트/기기/로그/규칙) | P52: 개발완료 | R52: 설정 | S52: =IFERROR(VLOOKUP(O52,API명세서!A:D,4,FALSE()),"") | U52: 3
A53: FN-033 | B53: 지점 관리 | C53: 설정 | D53: Web | E53: Critical | F53: 지점 CRUD 및 멀티테넌트 관리 | G53: 1) 지점 추가 (이름/코드/주소/연락처) 2) 지점 수정 3) 지점 비활성화 4) 데이터 초기화 (개발용) | H53: SCR-090 | I53: 지점 정보 | J53: 지점 목록 | K53: 1) 지점 코드: 영문 2~5자 고유값 2) 지점별 데이터 완전 격리 (멀티테넌트 – branch_id) 3) 지점 비활성화: 소속 데이터 유지, 로그인 차단 4) 데이터 초기화: 최고관리자 + 비밀번호 확인 + 2중 확인 필수 5) 회원 지점 이동: 이용권 유지 or 신규 발급 선택 6) 지점 통합 현황 통계 (전체 지점 합산) 7) 최고관리자만 지점 생성/삭제 가능 | L53: 지점 코드 중복: '이미 사용 중인 지점 코드입니다' 지점 코드 형식 오류: '지점 코드는 영문 2~5자로 입력하세요' 비활성 지점 로그인: '비활성화된 지점입니다. 관리자에게 문의하세요' 데이터 초기화 확인: '지점명을 입력하여 초기화를 확인하세요' 지점 삭제 (회원 있음): '소속 회원이 있어 삭제할 수 없습니다' 권한 없음: '지점 관리는 최고관리자만 가능합니다' | M53: Supabase branches 테이블 CRUD (실 데이터) 지점별 회원 수: members 테이블 count(exact) per branchId 지점별 매출: sales 테이블 totalAmount 합산 per branchId 통합 통계 카드 (동적 합산) 파이차트: 지점별 회원 비율 동적 계산 지점 등록: Supabase insert + optimistic state update 지점 이동: 빈 이력 (DB 테이블 추가 필요) 지점 비활성화: 2단계 확인 모달 | O53: API-027 | P53: 개발완료 | R53: 설정 | S53: /api/v1/system/reset | T53: Supabase branches 테이블 CRUD 실데이터 완료. 지점별 회원수 표시 (2026-03-13) | U53: 3
A54: ▼ SCR-022 | B54: GX 예약 관리 (3개 기능)
A55: FN-034 | B55: GX 예약 오픈/관리 | C55: 출석관리 | D55: Web | E55: Critical | F55: GX 프로그램 예약 생성, N시간 전 자동 오픈, 일괄 변경 | G55: 1) 수업별 예약 오픈 시간 설정(N시간 전 자동 오픈) 2) 강사 일괄 변경(기간 지정) 3) 수업 복사/반복 생성 4) 예약 정원 설정 5) 수업별 횟수권/기간권 구분 설정 | H55: SCR-022 | I55: 수업명, 강사, 요일, 시간, 정원, 예약오픈시간 | J55: 예약 현황, 대기 목록 | K55: 1) 예약 오픈: 수업 시작 N시간 전 자동(설정값) 2) 일괄 오픈: 매주 금요일 특정 시간 등 설정 가능 3) 강사 변경 시 기존 예약 유지, 알림 발송 | L55: 정원 초과: 대기 등록 안내 강사 미배정: 예약 오픈 불가 경고 | M55: React Calendar + Drag&Drop | P55: 개발완료 | R55: GX 예약 관리 | S55: (직접 Supabase 호출)
A56: FN-035 | B56: GX 출석 체크 자동화 | C56: 출석관리 | D56: Web | E56: Critical | F56: GX/스피닝/필라테스 출석 자동 체크. QR/NFC/안면인식 연동 | G56: 1) QR코드 스캔 출석 체크(가장 저비용) 2) NFC 밴드 태그 출석 체크 3) 예약자 명단 대조 자동 체크 4) 미출석자 노쇼 자동 처리 5) 센터 입장과 프로그램 출석 연동 | H56: SCR-022 | I56: 회원ID, 수업ID, 체크방식(QR/NFC/수동) | J56: 출석 결과, 노쇼 목록 | K56: 1) 센터 입장 + 프로그램 예약 매칭 → 자동 출석 2) 예약 후 미출석: 수업 종료 시점에 노쇼 처리 3) 비예약자 참석 감지 → FC 알림 | L56: QR 인식 실패: 수동 체크 폴백 중복 체크: 이미 출석 처리됨 안내 | M56: QR Reader API + WebSocket 실시간 | P56: 개발완료 | R56: GX 예약 관리 | S56: (직접 Supabase 호출) | T56: 주간/월간 통계 실 데이터 전환 완료 (2026-03-12). 하드코딩 제거.
A57: FN-036 | B57: 노쇼 페널티 자동 처리 | C57: 출석관리 | D57: Web | E57: High | F57: GX/PT 노쇼 시 자동 페널티 부여. 횟수 차감 및 예약 제한 | G57: 1) 노쇼 시 횟수권 1회 자동 차감 2) N회 노쇼 시 일정 기간 예약 제한 페널티 3) 취소 가능 시한 설정(수업 N시간 전) 4) 시한 내 취소: 횟수 미차감 5) 페널티 이력 관리 및 알림 | H57: SCR-022 | I57: 노쇼 기준시간, 페널티 횟수, 제한 기간 | J57: 페널티 현황, 이력 | K57: 1) 취소 시한 기본값: 수업 5시간 전 2) 노쇼 = 수업 진행으로 처리(횟수 차감) 3) 월 2회 노쇼: 1주 예약 제한 | L57: 페널티 부과 전 회원 알림 발송 | P57: 개발완료 | R57: GX 예약 관리 | S57: (직접 Supabase 호출)
A58: ▼ SCR-023 | B58: 좌석 예약 관리 (2개 기능)
A59: FN-037 | B59: 스피닝/GX 좌석 예약 | C59: 출석관리 | D59: Web | E59: High | F59: 스피닝 바이크, GX 매트 등 좌석 지정 예약 | G59: 1) 좌석 배치도 시각화(바이크/매트 번호) 2) 예약 선착순 좌석 선택권 부여 3) 고장 좌석 비활성화 표시(사선) 4) 좌석별 예약자 확인 5) 회원 앱 예약 시 좌석 선택 가능 | H59: SCR-023 | I59: 수업ID, 좌석번호, 회원ID | J59: 좌석 배치 현황, 예약 확인 | K59: 1) 예약 시간순으로 좌석 선택 우선권 2) 고장 좌석: 관리자만 비활성화/활성화 가능 3) 좌석 미선택 시 자동 배정 | L59: 좌석 중복 선택: 이미 예약된 좌석 안내 고장 좌석 선택: 사용 불가 안내 | M59: SVG 좌석 배치도 + 실시간 업데이트 | P59: 개발완료 | R59: 좌석 예약 관리 | S59: (직접 Supabase 호출)
A60: FN-038 | B60: 좌석 고장/관리 | C60: 시설관리 | D60: Web | E60: Medium | F60: 좌석(바이크/매트 등) 고장 등록, 수리 이력 관리 | G60: 1) 고장 등록 시 예약 자동 차단 2) 수리 완료 시 활성화 복구 3) 고장 이력/빈도 통계 | H60: SCR-023 | I60: 좌석번호, 고장유형, 수리일 | J60: 고장 이력, 통계 | K60: 고장 등록 시 해당 좌석 기예약자에게 알림 발송 | P60: 개발완료 | R60: 좌석 예약 관리 | S60: (직접 Supabase 호출)
A61: ▼ SCR-024 | B61: 레슨 기록/서명 (2개 기능)
A62: FN-039 | B62: 레슨 기록 및 고객 서명 | C62: 출석관리 | D62: Web | E62: High | F62: PT/골프 레슨 수업 기록 작성 + 고객 서명으로 수업 진위 확인 | G62: 1) 트레이너가 수업 내용 기록(텍스트/템플릿) 2) 수업 완료 시 고객 터치 서명 3) 서명 미완료 시 24시간 후 자동 완료 처리 4) 서명 없으면 수업 인정 불가(정책 설정) 5) 모바일에서도 서명 가능 | H62: SCR-024 | I62: 수업ID, 레슨내용, 고객서명이미지 | J62: 레슨 기록, 서명 확인 상태 | K62: 1) 서명 필수 정책: 센터별 ON/OFF 설정 2) 서명 없이 24시간 경과 → 자동 수업 완료(정책에 따라) 3) 노쇼는 수업 진행으로 카운트(취소와 구분) | L62: 서명 거부 시: 관리자 확인 필요 알림 | M62: Canvas 서명 패드 + 이미지 저장 | P62: 개발완료 | R62: 레슨 기록/서명 | S62: (직접 Supabase 호출)
A63: FN-040 | B63: 레슨 통계/리포트 | C63: 출석관리 | D63: Web | E63: Medium | F63: 트레이너별/회원별 레슨 진행 현황 통계 | G63: 1) 트레이너별 수업 건수/완료율 2) 회원별 레슨 소진율 3) 노쇼/취소/결석 비율 4) 기간별 통계 차트 | H63: SCR-024 | I63: 기간, 트레이너ID, 회원ID | J63: 통계 데이터, 차트 | K63: 일/주/월 단위 통계. 엑셀 다운로드 지원 | M63: Chart.js + 엑셀 Export | P63: 개발완료 | R63: 레슨 기록/서명 | S63: (직접 Supabase 호출)
A64: ▼ SCR-054 | B64: 골프 타석 관리 (2개 기능)
A65: FN-041 | B65: 골프 타석 예약/대기 | C65: 시설관리 | D65: Web | E65: High | F65: 골프 타석 꼬리물기 예약, 대기열 관리, 잔여시간 표시 | G65: 1) 타석별 현재 이용자/잔여시간 실시간 표시 2) 꼬리물기 방식 예약(현재 이용 종료 후 자동 시작) 3) 대기열 관리(모바일 원격 예약 가능) 4) 시간 표시: 시:분 형식(분 단위 아닌) 5) 1회 최대 이용시간 설정(기본 60분) | H65: SCR-054 | I65: 타석번호, 회원ID, 예약시간 | J65: 타석 현황, 대기열, 잔여시간 | K65: 1) 예약 후 15분 이내 미입장 시 노쇼 처리 2) 시간 표시: 시간:분 포맷(238분→3시간 58분) 3) 이용 종료 시 자동 다음 대기자 시작 | L65: 타석 고장: 예약 자동 취소 + 대기자 알림 노쇼: 예약 자동 해제 | M65: 실시간 타석 보드 UI | P65: 기획완료 | R65: 골프 타석 관리 | S65: (직접 Supabase 호출)
A66: FN-042 | B66: 타석/키오스크 화면 제어 | C66: 시설관리 | D66: Web | E66: High | F66: 골프 타석 키오스크 화면 잠금/해제, 이용시간 기반 자동 제어 | G66: 1) 예약/결제 완료 시 화면 잠금 해제 2) 이용시간 종료 시 자동 화면 잠금 3) 관리자 원격 잠금/해제 4) 스크린 락 방식(UI 오버레이) | H66: SCR-054 | I66: 타석번호, 제어명령(잠금/해제) | J66: 제어 결과 | K66: 이용 종료 10분 전 알림 표시 강제 종료 시 관리자 확인 필요 | M66: WebSocket 실시간 제어 | P66: 기획완료 | R66: 골프 타석 관리 | S66: (직접 Supabase 호출)
A67: ▼ SCR-055 | B67: 기기 전원 제어 (1개 기능)
A68: FN-043 | B68: 키오스크/프로젝터 원격 전원 제어 | C68: 시설관리 | D68: Web | E68: Critical | F68: 전 매장 키오스크/프로젝터 원격 일괄 ON/OFF + 스케줄 자동 제어 | G68: 1) PC 관리화면에서 전체/개별 전원 ON/OFF 2) 오픈/마감 시간 스케줄 설정 → 자동 전원 제어 3) 키오스크: WOL(Wake-on-LAN) 원격 부팅 4) 프로젝터: PJ Link/RS232 프로토콜 제어 5) 전원 상태 실시간 모니터링 6) 30개+ 기기 일괄 제어(고척/서교 기준) | H68: SCR-055 | I68: 기기목록, 제어명령, 스케줄시간 | J68: 기기 상태, 제어 결과 | K68: 1) 오픈 시: 스케줄 시간 20분 전 자동 부팅 2) 마감 시: 영업종료 시간에 자동 셧다운 3) 기기별 상태(온라인/오프라인/고장) 표시 | L68: 기기 미응답: 3회 재시도 후 오프라인 표시 네트워크 장애: 로컬 제어 폴백 | M68: WOL + PJ Link + 상태 모니터링 대시보드 | P68: 기획완료 | R68: 기기 전원 제어 | S68: (직접 Supabase 호출)
A69: ▼ SCR-056 | B69: 수건/운동복 관리 (1개 기능)
A70: FN-044 | B70: 수건/운동복 발급 관리 | C70: 시설관리 | D70: Web | E70: High | F70: 수건/운동복 발급 수량 제어 + 사용량 통계. QR/안면인식 연동 | G70: 1) 회원별 1일 발급 수량 제한(수건 2장, 운동복 1벌 기본) 2) QR/안면인식으로 발급 기록 자동화 3) 반납 시 포인트 적립(선택) 4) 일별/월별 사용량 통계 + 세탁비 추정 5) 비정상 사용 패턴 알림(과다 발급) | H70: SCR-056 | I70: 회원ID, 품목, 수량 | J70: 발급 이력, 사용량 통계, 세탁비 추정 | K70: 1) 기본 제공: 수건 2장 + 운동복 1벌 2) 추가 발급: 유/무료 센터 설정 3) 월간 세탁비 자동 집계 | L70: 한도 초과: '오늘 발급 한도 초과' 안내 미회원: 발급 불가 | P70: 개발완료 | R70: 수건/운동복 관리 | S70: (직접 Supabase 호출)
A71: ▼ SCR-015 | B71: FC 즐겨찾기/알림 (1개 기능)
A72: FN-045 | B72: FC 즐겨찾기 회원 방문 알림 | C72: 회원관리 | D72: Web | E72: Critical | F72: 담당 FC가 즐겨찾기한 회원 방문 시 실시간 알림. 이용권 임박 회원 자동 표시 | G72: 1) FC 개인 아이디별 즐겨찾기 회원 등록 2) 즐겨찾기 회원 입장 시 해당 FC 핸드폰 푸시 알림 3) 이용권 만료 임박(D-30~D-7) 회원 자동 즐겨찾기 등록 4) 방문 알림에 회원 상태 요약(잔여일, 미납 여부) 포함 5) 재등록 상담 필요 회원 하이라이트 | H72: SCR-015 | I72: FC ID, 회원ID, 알림 설정 | J72: 방문 알림, 임박 회원 목록 | K72: 1) 즐겨찾기 수 제한 없음 2) 알림 채널: 앱 푸시 + 관리자 화면 팝업 3) 이용권 만료 D-30 자동 즐겨찾기 추가(설정 시) | L72: 알림 수신 거부 시 관리자 화면에만 표시 | M72: FCM Push + WebSocket 실시간 | P72: 개발완료 | R72: FC 즐겨찾기/알림 | S72: (직접 Supabase 호출)
A73: ▼ SCR-095 | B73: 키오스크 타입 설정 (1개 기능)
A74: FN-046 | B74: 키오스크 타입별 UI 설정 | C74: 설정 | D74: Web | E74: High | F74: 키오스크 타입(결제형/비결제형) 지점별 설정. 화면 구성 자동 분기 | G74: 1) 타입A: 입장/퇴장/사물함 확인 전용(결제 없음) 2) 타입B: 1일권/시간권 현장 결제 포함 3) 어드민에서 지점별 타입 선택 4) 타입별 키오스크 UI 자동 구성 5) 1일권 결제 시 가상 ID 자동 생성 + 키 발급 | H74: SCR-095 | I74: 지점ID, 키오스크타입 | J74: 키오스크 UI 설정 | K74: 1) 타입은 지점 단위 설정(키오스크 개별 불가) 2) 타입B는 PG사 결제 모듈 연동 필수 | L74: 결제 모듈 미연동 시 타입B 선택 불가 경고 | P74: 개발완료 | R74: 키오스크 타입 설정 | S74: (직접 Supabase 호출)
A75: ▼ SCR-096 | B75: 오프라인 모드 설정 (1개 기능)
A76: FN-047 | B76: 오프라인 모드 + 자동 동기화 | C76: 설정 | D76: Web | E76: Critical | F76: 네트워크 장애 시 로컬 모드 자동 전환. 복구 시 데이터 자동 동기화 | G76: 1) 네트워크 끊김 감지 → 자동 로컬 모드 전환 2) 로컬 모드: 출입/라커 배정/출석 기본 기능 동작 3) 로컬 저장: IndexedDB + Service Worker 4) 네트워크 복구 → 큐잉된 데이터 자동 동기화 5) 충돌 시 서버 우선 + 관리자 알림 6) 오프라인 상태 표시 배너 | H76: SCR-096 | I76: 오프라인 허용 기능 목록, 동기화 정책 | J76: 동기화 상태, 충돌 로그 | K76: 1) 오프라인 필수 기능: 출입/라커/출석 2) 오프라인 불가 기능: 결제/환불/회원등록 3) 로컬 데이터 최대 보관: 72시간 | L76: 동기화 실패: 재시도 3회 후 관리자 수동 처리 안내 | M76: Service Worker + IndexedDB + Sync Queue | P76: 기획완료 | R76: 오프라인 모드 설정 | S76: (직접 Supabase 호출)
A77: ▼ SCR-033 | B77: 데이터 통합 내보내기 (1개 기능)
A78: FN-048 | B78: 전체 데이터 엑셀 내보내기 | C78: 매출관리 | D78: Web | E78: High | F78: 전체 데이터 원장을 엑셀로 내보내기. 권한별 컬럼 필터링 | G78: 1) 회원/매출/출석/레슨/상품 등 전체 원장 내보내기 2) 모든 필드 포함(필터링 없는 raw 데이터) 3) 권한별 열람 가능 컬럼 자동 필터 4) 기간/지점/카테고리 필터 5) CSV/XLSX 포맷 선택 | H78: SCR-033 | I78: 데이터 유형, 기간, 지점, 포맷 | J78: 엑셀 파일 다운로드 | K78: 1) 센터장 이상: 전체 컬럼 2) 매니저: 급여/개인정보 제외 3) FC: 담당 회원만 4) 최대 내보내기: 10만 건/회 | L78: 대용량: 비동기 처리 + 이메일 발송 | M78: 엑셀 export: xlsx 라이브러리 기반 실제 XLSX 다운로드 구현 11개 페이지 (회원/매출/직원/상품/출석/락커/RFID/급여/마일리지/쿠폰/메시지) exportToExcel() 공통 유틸리티 | P78: 개발완료 | R78: 데이터 통합 내보내기 | S78: (직접 Supabase 호출) | T78: exportToExcel 공통 유틸 구현 완료 (2026-03-13). 전체 페이지 엑셀 다운로드 동작
A79: FN-049 | B79: 상품 한 화면 세팅 | C79: 상품관리 | D79: Web | E79: Critical | F79: 상품 등록/수정을 한 화면에서 완료. 요일별/시간별/횟수별/기간별 세팅 통합 | G79: 1) 한 화면에서 상품명/가격/기간/횟수/요일제한/시간제한 모두 설정 2) 주중권/주말권 분기 설정 3) 횟수제/기간제/혼합 선택 4) 주N회 제한 설정 5) 상품 클릭 시 구매 회원 목록 바로 확인 6) 이용 유효기간 + 횟수 동시 설정 가능 | H79: SCR-041 | I79: 상품 전체 속성 | J79: 상품 설정 결과, 구매자 목록 | K79: 1) 레슨북 UI 벤치마크: 팝업 없이 인라인 설정 2) 요일 체크박스 + 시간 레인지 슬라이더 3) 상품 복제 기능 지원 | L79: 필수 항목 미입력: 인라인 에러 표시 | M79: Single-page form + 실시간 미리보기 | P79: 개발완료 | R79: 상품 등록 | S79: (직접 Supabase 호출) | U79: UI-085, UI-086, UI-087, UI-088
A80: FN-050 | B80: 라커 우선순위 배정 | C80: 시설관리 | D80: Web | E80: High | F80: 라커 자동 배정 시 상단/홀수 우선 등 우선순위 규칙 적용 | G80: 1) 배정 우선순위: 상단 > 하단, 홀수 > 짝수(설정 가능) 2) 회원 선호 라커 우선 배정(선택) 3) 고장/점유 라커 자동 스킵 4) 퇴실 시 라커 자동 해제(센터 설정) 5) 마감 시 전체 라커 일괄 해제 + 잔류물 체크리스트 | H80: SCR-050 | I80: 배정규칙(상단우선/홀수우선 등) | J80: 배정 결과 | K80: 1) 기본: 홀수 먼저 → 상단 먼저 배정 2) 마감 시 잠긴 라커: 마스터키 해제 → 잔류물 보관 3) 잔류물 15일 보관 후 폐기 | L80: 전체 라커 점유 시: 대기 등록 안내 | P80: 개발완료 | R80: 락커 현황 | S80: (직접 Supabase 호출) | U80: UI-053, UI-054, UI-055, UI-056
A81: FN-051 | B81: 실적 담당자/계약 처리자 분리 | C81: 매출관리 | D81: Web | E81: High | F81: 상담 실적 담당자와 실제 계약 처리자를 분리 관리. 실적 귀속 규칙 적용 | G81: 1) 계약 시 실적 담당자 + 계약 처리자 각각 지정 2) 최초 상담자 자동 실적 귀속(기본) 3) 상담 후 N일 경과 시 실적 귀속 해제(센터 설정) 4) 실적 담당자별 매출 집계 5) 분쟁 방지: 상담 이력 자동 기록 | H81: SCR-030 | I81: 실적담당자ID, 계약처리자ID, 귀속기간 | J81: 실적 집계, 이력 | K81: 1) 최초 상담 → 실적 귀속 기본 30일 2) 30일 초과: 실적 귀속 해제, 새 상담자에게 이전 3) 팀 매출 vs 개인 매출 구분 집계 | L81: 담당자 퇴사 시: 실적 재배정 필요 알림 | P81: 개발완료 | R81: 매출 조회 | S81: (직접 Supabase 호출) | U81: UI-038, UI-039, UI-040, UI-041, UI-042, UI-043, UI-044
A82: FN-052 | B82: 프로모션 할인 자동 적용 | C82: 상품관리 | D82: Web | E82: High | F82: 월별 프로모션 할인율을 상품에 자동 적용. 신규/재등록/기간별 할인 분기 | G82: 1) 프로모션 기간/대상/할인율 사전 설정 2) 계약 시 해당 프로모션 자동 적용 3) 신규/재등록/휴면복귀 구분 할인 4) FC 재량 할인 한도 설정(예: 최대 5%) 5) 할인 적용 시 원가/할인가/최종가 자동 계산 | H82: SCR-041 | I82: 프로모션ID, 기간, 대상유형, 할인율 | J82: 할인 적용 결과 | K82: 1) 프로모션 중복 적용 불가(최대 혜택 자동 선택) 2) FC 재량 할인: 센터장이 한도 설정 3) 할인 이력 전체 감사 로그 기록 | L82: 할인율 50% 초과: 센터장 승인 필요 | P82: 개발완료 | R82: 상품 등록 | S82: (직접 Supabase 호출) | U82: UI-085, UI-086, UI-087, UI-088
A83: ▼ SCR-K01 | B83: 키오스크 입장 (1개 기능)
A84: FN-K01 | B84: 키오스크 회원 입장 | C84: 키오스크 | D84: Kiosk | E84: Critical | F84: 얼굴인식/전화번호/NFC 밴드로 회원 입장 처리 | G84: 1) 얼굴인식 입장(브로제이 방식): 카메라 인식 → 회원정보 표시 → 확인 2) 전화번호 입장: 번호 입력 → 회원정보 표시 3) NFC 밴드 태그 입장(온핏 방식) 4) 입장 시 라커 자동 배정 + 번호 표시 5) 동시 다중 인식 지원(얼굴인식 시) | H84: SCR-K01 | I84: 얼굴/전화번호/NFC | J84: 회원정보, 라커번호, 입장시간 | K84: 1) 미등록 얼굴: '등록되지 않은 회원입니다' 안내 2) 만료 회원: 입장 허용 여부 센터 설정 3) 입장 로그 자동 기록 | L84: 인식 실패: 전화번호 폴백 네트워크 장애: 오프라인 모드 전환 | M84: 얼굴인식 SDK + NFC Reader | P84: 기획완료 | R84: 키오스크 입장 | S84: (직접 Supabase 호출)
A85: ▼ SCR-K02 | B85: 키오스크 퇴장 (1개 기능)
A86: FN-K02 | B86: 키오스크 회원 퇴장 | C86: 키오스크 | D86: Kiosk | E86: Critical | F86: 회원 퇴장 처리. 라커 자동 해제, 이용시간 기록 | G86: 1) 얼굴/전화번호/NFC로 퇴장 처리 2) 라커 자동 해제(센터 설정) 3) 이용시간 자동 기록 4) 대치점 방식: 라커키 반납 시 퇴장 처리 | H86: SCR-K02 | I86: 회원인증 | J86: 퇴장시간, 이용시간 | K86: 퇴장 미처리 시 마감 일괄 퇴장 처리 | P86: 기획완료 | R86: 키오스크 퇴장 | S86: (직접 Supabase 호출)
A87: ▼ SCR-K03 | B87: 키오스크 골프 타석 예약 (1개 기능)
A88: FN-K03 | B88: 키오스크 골프 타석 예약/대기 | C88: 키오스크 | D88: Kiosk | E88: High | F88: 키오스크에서 골프 타석 예약 및 대기열 등록 | G88: 1) 빈 타석 실시간 표시(타석 배치도) 2) 대기 시간 시:분 형식 표시(분 단위 X) 3) 꼬리물기 예약: 현재 이용자 종료 후 자동 시작 4) 대기열 등록(바깥에서 앱으로도 가능) 5) 예약 후 15분 이내 입장 필수 | H88: SCR-K03 | I88: 회원ID, 타석번호 | J88: 예약확인, 대기순번, 예상시간 | K88: 1) 시간 표시: 238분 → '3시간 58분'으로 변환 2) 1회 최대 60분(센터 설정) 3) 예약 후 15분 미입장 → 노쇼 | L88: 전체 타석 점유: 대기 등록만 가능 | M88: 실시간 WebSocket + 타석 배치도 UI | P88: 기획완료 | R88: 키오스크 골프 타석 예약 | S88: (직접 Supabase 호출)
A89: ▼ SCR-K04 | B89: 키오스크 사물함 확인 (1개 기능)
A90: FN-K04 | B90: 키오스크 사물함 번호 확인/영수증 | C90: 키오스크 | D90: Kiosk | E90: High | F90: 배정된 라커 번호 확인 및 영수증 출력 | G90: 1) 회원 인증 후 배정된 라커 번호 표시 2) 영수증 형태로 라커 번호 출력(대치점 방식) 3) 영수증에 라커 번호 크게 표시(고령 회원 배려) 4) 라커 위치 안내(층/구역) | H90: SCR-K04 | I90: 회원인증 | J90: 라커번호, 영수증 | K90: 영수증 출력은 대치점 방식 벤치마크(찜질방 스타일) | L90: 미배정 시: 자동 배정 후 표시 | P90: 기획완료 | R90: 키오스크 사물함 확인 | S90: (직접 Supabase 호출)
A91: ▼ SCR-K05 | B91: 키오스크 1일권 결제 (1개 기능)
A92: FN-K05 | B92: 키오스크 1일권 현장 결제 | C92: 키오스크 | D92: Kiosk | E92: High | F92: 비회원 1일권/시간권 키오스크 현장 결제(타입B 전용) | G92: 1) 전화번호 입력 → 가상 회원ID 자동 생성 2) 상품 선택(1일권/시간권 등) 3) 카드/간편결제(서울페이/제로페이 등) 4) 결제 완료 → 라커 배정 → 입장 처리 5) 당일 만료 자동 설정 | H92: SCR-K05 | I92: 전화번호, 상품, 결제수단 | J92: 결제영수증, 라커번호, 입장확인 | K92: 1) 타입B 키오스크에서만 노출 2) 가상 회원: 당일 자동 만료 3) 결제 수단: 카드/간편결제(현금 X) | L92: 결제 실패: 재시도 안내 PG 연동 실패: 프론트 데스크 안내 | M92: PG SDK + 간편결제 모듈 | P92: 기획완료 | R92: 키오스크 1일권 결제 | S92: (직접 Supabase 호출)
A93: ▼ SCR-K06 | B93: 키오스크 GX 예약 (1개 기능)
A94: FN-K06 | B94: 키오스크 GX 프로그램 예약 | C94: 키오스크 | D94: Kiosk | E94: High | F94: 키오스크에서 GX 프로그램 예약/취소, 좌석 선택 | G94: 1) 오늘/이번 주 GX 시간표 표시 2) 잔여석 실시간 표시 3) 예약/취소 가능(취소 시한 내) 4) 스피닝: 바이크 좌석 배치도에서 선택 5) 횟수권 잔여 횟수 표시 | H94: SCR-K06 | I94: 회원ID, 수업ID, 좌석번호 | J94: 예약확인, 잔여횟수 | K94: 1) 예약 오픈 전 수업: '예약 오픈 전' 표시 2) 정원 초과: 대기 등록 3) 횟수 소진: 추가 구매 안내 | L94: 잔여 횟수 0: '이용권을 구매해주세요' 안내 | P94: 기획완료 | R94: 키오스크 GX 예약 | S94: (직접 Supabase 호출)
A95: ▼ SCR-K07 | B95: 키오스크 골프 타석 입장 (1개 기능)
A96: FN-K07 | B96: 키오스크 골프 타석 입장/시작 | C96: 키오스크 | D96: Kiosk | E96: High | F96: 예약한 골프 타석 입장 인증 → 스크린 잠금 해제 → 이용 시작 | G96: 1) 전화번호/얼굴인식으로 예약 확인 2) 예약된 타석 스크린 잠금 자동 해제 3) 이용시간 카운트다운 시작 4) 종료 10분 전 알림 5) 시간 종료 시 자동 스크린 잠금 | H96: SCR-K07 | I96: 회원인증, 예약번호 | J96: 타석번호, 잔여시간 | K96: 1) 예약 없이 입장 불가 2) 예약 후 15분 미입장 → 노쇼 3) 이용 중 타석 이동: 빈 타석으로만 가능 | L96: 예약 없음: '예약 후 이용해주세요' 안내 | P96: 기획완료 | R96: 키오스크 골프 타석 입장 | S96: (직접 Supabase 호출)
A97: ▼ SCR-M01 | B97: 앱 홈 (1개 기능)
A98: FN-M01 | B98: 회원 앱 홈 대시보드 | C98: 회원앱 | D98: App | E98: Critical | F98: 회원 앱 메인 화면. 이용권 잔여, 오늘 예약, 출석 현황 요약 | G98: 1) 이용권 잔여일/잔여횟수 카드 2) 오늘 예약 목록(GX/PT/골프) 3) 이번 달 출석 현황 4) 공지사항/프로모션 배너 5) 빠른 입장 QR 버튼 | H98: SCR-M01 | I98: 회원 로그인 | J98: 이용권현황, 예약목록, 출석현황 | K98: 앱 실행 시 자동 로그인(생체인증/토큰) | L98: 토큰 만료: 재로그인 안내 | M98: React Native | P98: 기획완료 | R98: 앱 홈 | S98: (직접 Supabase 호출)
A99: ▼ SCR-M02 | B99: 앱 QR 입장 (1개 기능)
A100: FN-M02 | B100: 앱 QR코드 입장/퇴장 | C100: 회원앱 | D100: App | E100: Critical | F100: 앱에서 QR코드 표시하여 센터 입장/퇴장, 라커 번호 확인 | G100: 1) 입장용 QR코드 실시간 생성(30초 갱신) 2) QR 스캔 → 입장 처리 + 라커 배정 3) 배정된 라커 번호 앱에 표시 4) 퇴장 시 QR 스캔 → 라커 해제 | H100: SCR-M02 | I100: 회원인증 | J100: QR코드, 라커번호, 입장시간 | K100: QR코드: 일회용, 30초마다 갱신(보안) | L100: 오프라인: QR 생성 불가 안내 | M100: QR 생성 라이브러리 | P100: 기획완료 | R100: 앱 QR 입장 | S100: (직접 Supabase 호출)
...

Sheet API명세서
A1: API ID | B1: API명 | C1: Method | D1: 엔드포인트 | E1: 설명 | F1: Request Headers | G1: Request Body | H1: Response (성공) | I1: Response (실패) | J1: 인증 필요 | K1: 화면 ID | L1: 기능 ID | M1: 상태 | N1: 담당자 | O1: [자동] 화면명 | P1: [자동] 기능명 | Q1: 비고 | R1: [자동] 관련 UI 요소
A2: API-001 | B2: 로그인 | C2: POST | D2: /api/v1/auth/login | E2: 이메일/비밀번호 로그인 인증 | F2: Content-Type: application/json | G2: { "email": "string (username@spogym.local)", "password": "string" } * Supabase Auth signInWithPassword 사용 * Auth 실패 시 기존 평문 비밀번호 fallback | H2: { "token": "supabase_access_token", "user": { id, username, name, role, branchId } } | I2: { "error": "INVALID_CREDENTIALS", "message": "이메일 또는 비밀번호가 올바르지 않습니다" } | J2: N | K2: SCR-001 | L2: FN-001 | M2: 개발완료 | O2: 로그인 | P2: 로그인 | Q2: Supabase Auth 전환 (2026-03-12). signInWithPassword + 평문 fallback. | R2: 5
A3: API-002 | B3: 로그아웃 | C3: POST | D3: /api/v1/auth/logout | E3: 세션 종료 및 토큰 무효화 | F3: Authorization: Bearer {token} | H3: { "message": "로그아웃 되었습니다" } | I3: { "error": "UNAUTHORIZED", "message": "인증이 필요합니다" } | J3: Y | K3: SCR-002 | L3: FN-001 | M3: 개발완료 | O3: 대시보드 | P3: 로그인 | Q3: supabase.auth.signOut() 실제 호출 구현 (2026-03-12) | R3: 8
A4: API-003 | B4: 대시보드 통계 | C4: GET | D4: /api/v1/dashboard/stats | E4: 지점별 대시보드 핵심 KPI 조회 | F4: Authorization: Bearer {token} | H4: { "totalMembers": 450, "activeMembers": 320, "expiringMembers": 25, "expiredMembers": 105, "monthlySales": 15000000, "todayAttendance": 87 } | I4: { "error": "SERVER_ERROR", "message": "데이터를 불러올 수 없습니다" } | J4: Y | K4: SCR-002 | L4: FN-002 | M4: 개발완료 | O4: 대시보드 | P4: 대시보드 통계 조회 | R4: 8
A5: API-004 | B5: 생일 회원 조회 | C5: GET | D5: /api/v1/dashboard/birthday-members | E5: 오늘 생일인 회원 목록 조회 | F5: Authorization: Bearer {token} | H5: { "members": [ {"id": 1, "name": "김회원", "phone": "010-1234-5678"} ] } | I5: { "error": "SERVER_ERROR", "message": "데이터를 불러올 수 없습니다" } | J5: Y | K5: SCR-002 | L5: FN-002 | M5: 개발완료 | O5: 대시보드 | P5: 대시보드 통계 조회 | R5: 8
A6: API-005 | B6: 미납 회원 조회 | C6: GET | D6: /api/v1/dashboard/unpaid-members | E6: 미납 내역이 있는 회원 목록 조회 | F6: Authorization: Bearer {token} | H6: { "members": [ {"id": 2, "name": "이회원", "unpaidAmount": 150000} ] } | I6: { "error": "SERVER_ERROR", "message": "조회 실패" } | J6: Y | K6: SCR-002 | L6: FN-002 | M6: 개발완료 | O6: 대시보드 | P6: 대시보드 통계 조회 | R6: 8
A7: API-006 | B7: 만료예정 회원 조회 | C7: GET | D7: /api/v1/dashboard/expiring-members | E7: 7일 내 이용권 만료 예정 회원 조회 | F7: Authorization: Bearer {token} | H7: { "members": [ {"id": 3, "name": "박회원", "expiryDate": "2026-03-18", "dDay": -7} ] } | I7: { "error": "SERVER_ERROR", "message": "조회 실패" } | J7: Y | K7: SCR-002 | L7: FN-002 | M7: 개발완료 | O7: 대시보드 | P7: 대시보드 통계 조회 | R7: 8
A8: API-007 | B8: 회원 목록 조회 | C8: GET | D8: /api/v1/members | E8: 회원 목록 조회 (검색/필터/페이지네이션) | F8: Authorization: Bearer {token} | G8: Query: ?search=&status=&gender=&manager_id=&page=1&size=20&sort=name&order=asc | H8: { "data": [ {"id": 1, "name": "김회원", "phone": "010-1234-5678", "status": "active", "gender": "M"} ], "pagination": {"page": 1, "size": 20, "total": 450} } | I8: { "error": "FORBIDDEN", "message": "접근 권한이 없습니다" } | J8: Y | K8: SCR-010 | L8: FN-003 | M8: 개발완료 | O8: 회원 목록 | P8: 회원 목록 조회/검색/필터 | R8: 8
A9: API-008 | B9: 회원 상세 조회 | C9: GET | D9: /api/v1/members/:id | E9: 회원 상세 정보 조회 (프로필+이용권+출석+결제+체성분+메모) | F9: Authorization: Bearer {token} | H9: { "profile": {"id": 1, "name": "김회원", ...}, "tickets": [...], "attendance": [...], "payments": [...], "bodyComposition": [...], "memos": [...] } | I9: { "error": "NOT_FOUND", "message": "회원을 찾을 수 없습니다" } | J9: Y | K9: SCR-011 | L9: FN-006 | M9: 개발완료 | O9: 회원 상세 | P9: 회원 상세 조회 | R9: 6
A10: API-009 | B10: 회원 등록 | C10: POST | D10: /api/v1/members | E10: 신규 회원 등록 | F10: Authorization: Bearer {token} Content-Type: application/json | G10: { "name": "string", "gender": "M|F", "birthDate": "YYYY-MM-DD", "phone": "string", "email": "string", "address": "string", "memo": "string", "managerId": "number" } | H10: { "id": 1, "name": "김회원", "status": "active", "createdAt": "2026-03-11T00:00:00Z" } | I10: { "error": "DUPLICATE_PHONE", "message": "이미 등록된 연락처입니다" } | J10: Y | K10: SCR-012 | L10: FN-004 | M10: 개발완료 | O10: 회원 등록 | P10: 회원 등록 | R10: 10
A11: API-010 | B11: 회원 수정 | C11: PUT | D11: /api/v1/members/:id | E11: 기존 회원 정보 수정 | F11: Authorization: Bearer {token} Content-Type: application/json | G11: { "name": "string", "phone": "string", "email": "string", "address": "string", "memo": "string", "managerId": "number" } | H11: { "id": 1, "name": "김회원(수정)", "updatedAt": "2026-03-11T00:00:00Z" } | I11: { "error": "NOT_FOUND", "message": "회원을 찾을 수 없습니다" } | J11: Y | K11: SCR-013 | L11: FN-005 | M11: 개발완료 | O11: 회원 수정 | P11: 회원 정보 수정 | R11: 2
A12: API-011 | B12: 회원 삭제 | C12: DELETE | D12: /api/v1/members/:id | E12: 회원 삭제 (소프트 삭제) | F12: Authorization: Bearer {token} | H12: { "message": "회원이 삭제되었습니다" } | I12: { "error": "FORBIDDEN", "message": "삭제 권한이 없습니다" } | J12: Y | K12: SCR-011 | L12: FN-005 | M12: 개발완료 | O12: 회원 상세 | P12: 회원 정보 수정 | R12: 6
A13: API-012 | B13: 회원 통계 요약 | C13: GET | D13: /api/v1/members/stats/summary | E13: 회원 상태별 통계 요약 | F13: Authorization: Bearer {token} | H13: { "total": 450, "active": 320, "expired": 105, "suspended": 15, "withdrawn": 10 } | I13: { "error": "SERVER_ERROR", "message": "통계 조회 실패" } | J13: Y | K13: SCR-010 | L13: FN-003 | M13: 개발완료 | O13: 회원 목록 | P13: 회원 목록 조회/검색/필터 | R13: 8
A14: API-013 | B14: 출석 기록 조회 | C14: GET | D14: /api/v1/attendance | E14: 회원 출석 기록 조회 | F14: Authorization: Bearer {token} | G14: Query: ?startDate=&endDate=&type=&page=1&size=50 | H14: { "data": [ {"id": 1, "memberId": 1, "memberName": "김회원", "type": "normal", "inTime": "2026-03-11T09:00:00"} ], "pagination": {...} } | I14: { "error": "SERVER_ERROR", "message": "조회 실패" } | J14: Y | K14: SCR-020 | L14: FN-008 | M14: 개발완료 | O14: 출석 기록 | P14: 출석 기록 조회 | R14: 2
A15: API-014 | B15: 출석 등록 | C15: POST | D15: /api/v1/attendance | E15: 출석 체크인/체크아웃 등록 | F15: Authorization: Bearer {token} Content-Type: application/json | G15: { "memberId": "number", "type": "normal|pt|gx", "status": "checkIn|checkOut" } | H15: { "id": 1, "memberId": 1, "inTime": "2026-03-11T09:00:00", "visitCount": 45 } | I15: { "error": "ALREADY_CHECKED_IN", "message": "이미 출석 처리되었습니다" } | J15: Y | K15: SCR-020 | L15: FN-008 | M15: 개발완료 | O15: 출석 기록 | P15: 출석 기록 조회 | R15: 2
A16: API-015 | B16: 매출 조회 | C16: GET | D16: /api/v1/sales | E16: 매출 내역 조회 (기간/유형/상태 필터) | F16: Authorization: Bearer {token} | G16: Query: ?startDate=&endDate=&type=&status=&page=1&size=20 | H16: { "data": [ {"id": 1, "date": "2026-03-11", "productName": "3개월 이용권", "amount": 300000, "paymentMethod": "card"} ], "pagination": {...} } | I16: { "error": "FORBIDDEN", "message": "매출 조회 권한이 없습니다" } | J16: Y | K16: SCR-030 | L16: FN-010 | M16: 개발완료 | O16: 매출 조회 | P16: 매출 조회/통계 | R16: 7
A17: API-016 | B17: 매출 등록 (결제) | C17: POST | D17: /api/v1/sales | E17: POS 결제 처리 및 매출 등록 | F17: Authorization: Bearer {token} Content-Type: application/json | G17: { "memberId": "number", "items": [{"productId": 1, "quantity": 1}], "paymentMethod": "cash|card|mileage|mixed", "cashAmount": 0, "cardAmount": 300000, "mileageAmount": 0 } | H17: { "saleId": 1, "totalAmount": 300000, "receiptNo": "R20260311001" } | I17: { "error": "PAYMENT_FAILED", "message": "결제에 실패했습니다" } | J17: Y | K17: SCR-032 | L17: FN-012 | M17: 개발완료 | O17: POS 결제 | P17: POS 결제 처리 | R17: 4
A18: API-017 | B18: 매출 통계 요약 | C18: GET | D18: /api/v1/sales/stats/summary | E18: 매출 통계 요약 (총매출/현금/카드/마일리지) | F18: Authorization: Bearer {token} | G18: Query: ?startDate=&endDate= | H18: { "totalSales": 15000000, "cashSales": 3000000, "cardSales": 11000000, "mileageSales": 1000000, "refundTotal": 500000 } | I18: { "error": "SERVER_ERROR", "message": "통계 조회 실패" } | J18: Y | K18: SCR-030 | L18: FN-010 | M18: 개발완료 | O18: 매출 조회 | P18: 매출 조회/통계 | R18: 7
A19: API-018 | B19: 상품 목록 조회 | C19: GET | D19: /api/v1/products | E19: 상품 목록 조회 (카테고리/상태 필터) | F19: Authorization: Bearer {token} | G19: Query: ?category=&status= | H19: { "data": [ {"id": 1, "name": "3개월 이용권", "category": "membership", "cashPrice": 280000, "cardPrice": 300000, "status": "active"} ] } | I19: { "error": "SERVER_ERROR", "message": "조회 실패" } | J19: Y | K19: SCR-040 | L19: FN-013 | M19: 개발완료 | O19: 상품 목록 | P19: 상품 목록 조회 | R19: 3
A20: API-019 | B20: 상품 등록 | C20: POST | D20: /api/v1/products | E20: 신규 상품 등록 | F20: Authorization: Bearer {token} Content-Type: application/json | G20: { "category": "membership|pt|gx|etc", "name": "string", "cashPrice": "number", "cardPrice": "number", "period": "number (days)", "kioskExposure": "boolean" } | H20: { "id": 1, "name": "3개월 이용권", "createdAt": "2026-03-11" } | I20: { "error": "DUPLICATE_NAME", "message": "동일 카테고리에 같은 상품명이 있습니다" } | J20: Y | K20: SCR-041 | L20: FN-014 | M20: 개발완료 | O20: 상품 등록 | P20: 상품 등록/수정 | R20: 4
A21: API-020 | B21: 락커 목록 조회 | C21: GET | D21: /api/v1/lockers | E21: 구역별 락커 현황 조회 | F21: Authorization: Bearer {token} | G21: Query: ?area=A | H21: { "data": [ {"id": 1, "number": "A-001", "area": "A", "status": "available", "memberId": null} ] } | I21: { "error": "SERVER_ERROR", "message": "조회 실패" } | J21: Y | K21: SCR-050 | L21: FN-015 | M21: 개발완료 | O21: 락커 현황 | P21: 락커 현황 조회 | R21: 4
A22: API-021 | B22: 락커 배정/해제 | C22: PATCH | D22: /api/v1/lockers/:id | E22: 락커 배정 또는 해제 | F22: Authorization: Bearer {token} Content-Type: application/json | G22: { "action": "assign|release", "memberId": "number", "expiryDate": "YYYY-MM-DD" } | H22: { "id": 1, "number": "A-001", "status": "occupied", "memberId": 1 } | I22: { "error": "ALREADY_ASSIGNED", "message": "이미 사용중인 락커입니다" } | J22: Y | K22: SCR-051 | L22: FN-016 | M22: 개발완료 | O22: 락커 관리 | P22: 락커 배정/관리 | R22: 4
A23: API-022 | B23: 직원 목록 조회 | C23: GET | D23: /api/v1/staff | E23: 직원 목록 조회 (역할/상태 필터) | F23: Authorization: Bearer {token} | G23: Query: ?search=&role=&status= | H23: { "data": [ {"id": 1, "name": "박트레이너", "role": "fc", "status": "active", "contact": "010-9999-8888"} ] } | I23: { "error": "FORBIDDEN", "message": "직원 조회 권한이 없습니다" } | J23: Y | K23: SCR-060 | L23: FN-019 | M23: 개발완료 | O23: 직원 목록 | P23: 직원 목록 조회 | R23: 5
A24: API-023 | B24: 직원 등록 | C24: POST | D24: /api/v1/staff | E24: 신규 직원 등록 | F24: Authorization: Bearer {token} Content-Type: application/json | G24: { "name": "string", "gender": "M|F", "contact": "string", "role": "center_manager|manager|fc|staff", "joinDate": "YYYY-MM-DD", "workType": "full|part" } | H24: { "id": 1, "name": "박트레이너", "adminId": "auto_generated_id" } | I24: { "error": "DUPLICATE_EMAIL", "message": "이미 등록된 이메일입니다" } | J24: Y | K24: SCR-061 | L24: FN-020 | M24: 개발완료 | O24: 직원 등록 | P24: 직원 등록/수정 | R24: 5
A25: API-024 | B25: 직원 수정 | C25: PUT | D25: /api/v1/staff/:id | E25: 직원 정보 수정 | F25: Authorization: Bearer {token} Content-Type: application/json | G25: { "name": "string", "contact": "string", "role": "string", "status": "active|leave|resigned" } | H25: { "id": 1, "name": "박트레이너(수정)", "updatedAt": "2026-03-11" } | I25: { "error": "NOT_FOUND", "message": "직원을 찾을 수 없습니다" } | J25: Y | K25: SCR-060 | L25: FN-020 | M25: 개발완료 | O25: 직원 목록 | P25: 직원 등록/수정 | R25: 5
A26: API-025 | B26: 직원 삭제 | C26: DELETE | D26: /api/v1/staff/:id | E26: 직원 삭제 (소프트 삭제) | F26: Authorization: Bearer {token} | H26: { "message": "직원이 삭제되었습니다" } | I26: { "error": "FORBIDDEN", "message": "삭제 권한이 없습니다" } | J26: Y | K26: SCR-060 | L26: FN-020 | M26: 개발완료 | O26: 직원 목록 | P26: 직원 등록/수정 | R26: 5
A27: API-026 | B27: 직원 출근부 조회 | C27: GET | D27: /api/v1/staff/attendance | E27: 직원 출퇴근 기록 조회 | F27: Authorization: Bearer {token} | G27: Query: ?staffId=&yearMonth=2026-03 | H27: { "data": [ {"date": "2026-03-11", "staffId": 1, "checkIn": "09:00", "checkOut": "18:00", "status": "present"} ] } | I27: { "error": "SERVER_ERROR", "message": "조회 실패" } | J27: Y | K27: SCR-062 | L27: FN-021 | M27: 개발완료 | O27: 급여 현황 | P27: 급여 관리 | R27: 3
A28: API-027 | B28: 시스템 초기화 | C28: POST | D28: /api/v1/system/reset | E28: 지점 데이터 초기화 (개발/테스트용) | F28: Authorization: Bearer {token} Content-Type: application/json | G28: { "branchId": "number", "confirmPassword": "string", "targets": ["members","sales","attendance"] } | H28: { "message": "데이터가 초기화되었습니다", "resetTargets": ["members","sales","attendance"] } | I28: { "error": "INVALID_PASSWORD", "message": "비밀번호가 올바르지 않습니다" } | J28: Y | K28: SCR-094 | L28: FN-033 | M28: 개발완료 | O28: 지점 관리 | P28: 지점 관리 | R28: 3
A29: API-030 | B29: 매출 목록 조회 | C29: GET | D29: /api/v1/sales | E29: 매출 목록 조회. 기간/회원 필터, 페이지네이션 | F29: Authorization: Bearer {token} | G29: Query: page, size, startDate, endDate, memberId | H29: { "data": [Sale[]], "pagination": {...} } | I29: { "error": "SERVER_ERROR" } | J29: Y | K29: SCR-030 | L29: FN-011 | M29: 개발완료 | O29: 매출 관리 | P29: 매출 조회 | Q29: saleDate desc 정렬, branchId 필터 | R29: UI-038, UI-039, UI-040, UI-041, UI-042, UI-043, UI-044
A30: API-031 | B30: 매출 상세 조회 | C30: GET | D30: /api/v1/sales/{id} | E30: 매출 단건 상세 조회 | F30: Authorization: Bearer {token} | G30: Path: id | H30: { "data": Sale } | I30: { "error": "NOT_FOUND" } | J30: Y | K30: SCR-030 | L30: FN-011 | M30: 개발완료 | O30: 매출 관리 | P30: 매출 조회 | Q30: supabase.from("sales").eq("id").single() | R30: UI-038, UI-039, UI-040, UI-041, UI-042, UI-043, UI-044
A31: API-032 | B31: 매출 등록 | C31: POST | D31: /api/v1/sales | E31: 새 매출 등록. saleDate 미전달 시 현재 시각, status 기본 COMPLETED | F31: Authorization: Bearer {token} | G31: { "memberId": "number (필수)", "productId": "number (필수)", "amount": "number (필수)", "paymentMethod": "CARD|CASH|TRANSFER|MILEAGE (필수)", ... (memberName, productName, salePrice, discountPrice, cash, card, mileageUsed, cardCompany, cardNumber, approvalNo, unpaid, staffId, staffName, memo, saleDate) } | H31: { "data": Sale, "message": "매출이 등록되었습니다." } | I31: { "error": "CREATE_FAILED" } | J31: Y | K31: SCR-031 | L31: FN-012 | M31: 개발완료 | O31: POS 결제 | P31: 매출 등록 | Q31: branchId 자동 설정 | R31: UI-045, UI-046, UI-047, UI-048
A32: API-033 | B32: 매출 수정 | C32: PUT | D32: /api/v1/sales/{id} | E32: 매출 부분 수정 | F32: Authorization: Bearer {token} | G32: Path: id Body: Partial<SaleRequest> | H32: { "data": Sale, "message": "매출이 수정되었습니다." } | I32: { "error": "UPDATE_FAILED" } | J32: Y | K32: SCR-030 | L32: FN-013 | M32: 개발완료 | O32: 매출 관리 | P32: 매출 수정 | R32: UI-038, UI-039, UI-040, UI-041, UI-042, UI-043, UI-044
A33: API-034 | B33: 매출 삭제 | C33: DELETE | D33: /api/v1/sales/{id} | E33: 매출 삭제 (hard delete) | F33: Authorization: Bearer {token} | G33: Path: id | H33: { "message": "매출이 삭제되었습니다." } | I33: { "error": "DELETE_FAILED" } | J33: Y | K33: SCR-030 | L33: FN-014 | M33: 개발완료 | O33: 매출 관리 | P33: 매출 삭제 | Q33: hard delete (실제 행 삭제) | R33: UI-038, UI-039, UI-040, UI-041, UI-042, UI-043, UI-044
A34: API-035 | B34: 매출 통계 조회 | C34: GET | D34: /api/v1/sales/stats | E34: 매출 통계 (전체금액/건수/월별금액/건수/결제수단별). 기간 필터 지원 | F34: Authorization: Bearer {token} | G34: Query: startDate, endDate | H34: { "data": { "totalAmount": 50000000, "totalCount": 350, "monthlyAmount": 15000000, "monthlyCount": 120, "byPaymentMethod": {"CARD": 10000000, "CASH": 3000000, ...} } } | I34: { "error": "SERVER_ERROR" } | J34: Y | K34: SCR-030 | L34: FN-011 | M34: 개발완료 | O34: 매출 관리 | P34: 매출 조회 | Q34: 2개 쿼리(전체+월별) 순차 실행, reduce로 합산 | R34: UI-038, UI-039, UI-040, UI-041, UI-042, UI-043, UI-044
A35: API-040 | B35: 상품 목록 조회 | C35: GET | D35: /api/v1/products | E35: 상품 목록 조회. 카테고리/활성 필터, 페이지네이션 | F35: Authorization: Bearer {token} | G35: Query: page, size(기본50), category, isActive | H35: { "data": [Product[]], "pagination": {...} } | I35: { "error": "SERVER_ERROR" } | J35: Y | K35: SCR-040 | L35: FN-015 | M35: 개발완료 | O35: 상품 목록 | P35: 상품 조회 | Q35: name asc 정렬, branchId 필터 | R35: UI-082, UI-083, UI-084
A36: API-041 | B36: 상품 상세 조회 | C36: GET | D36: /api/v1/products/{id} | E36: 상품 단건 조회 | F36: Authorization: Bearer {token} | G36: Path: id | H36: { "data": Product } | I36: { "error": "NOT_FOUND" } | J36: Y | K36: SCR-040 | L36: FN-015 | M36: 개발완료 | O36: 상품 목록 | P36: 상품 조회 | R36: UI-082, UI-083, UI-084
A37: API-042 | B37: 상품 등록 | C37: POST | D37: /api/v1/products | E37: 신규 상품 등록 | F37: Authorization: Bearer {token} | G37: { "name": "string (필수)", "category": "PT|MEMBERSHIP|GX|PRODUCT|SERVICE (필수)", "price": "number (필수)", "duration?": "number", "sessions?": "number", "description?": "string", "isActive?": "boolean (기본true)" } | H37: { "data": Product, "message": "상품이 등록되었습니다." } | I37: { "error": "CREATE_FAILED" } | J37: Y | K37: SCR-041 | L37: FN-016 | M37: 개발완료 | O37: 상품 등록 | P37: 상품 등록 | Q37: isActive 기본 true, branchId 자동 | R37: UI-085, UI-086, UI-087, UI-088
A38: API-043 | B38: 상품 수정 | C38: PUT | D38: /api/v1/products/{id} | E38: 상품 부분 수정 | F38: Authorization: Bearer {token} | G38: Path: id Body: Partial<ProductRequest> | H38: { "data": Product, "message": "상품이 수정되었습니다." } | I38: { "error": "UPDATE_FAILED" } | J38: Y | K38: SCR-041 | L38: FN-017 | M38: 개발완료 | O38: 상품 등록 | P38: 상품 수정 | R38: UI-085, UI-086, UI-087, UI-088
A39: API-044 | B39: 상품 삭제 | C39: DELETE | D39: /api/v1/products/{id} | E39: 상품 삭제 (hard delete) | F39: Authorization: Bearer {token} | G39: Path: id | H39: { "message": "상품이 삭제되었습니다." } | I39: { "error": "DELETE_FAILED" } | J39: Y | K39: SCR-040 | L39: FN-018 | M39: 개발완료 | O39: 상품 목록 | P39: 상품 삭제 | Q39: hard delete | R39: UI-082, UI-083, UI-084
A40: API-050 | B40: 락커 목록 조회 | C40: GET | D40: /api/v1/lockers | E40: 락커 목록 조회. 상태 필터, 페이지네이션 | F40: Authorization: Bearer {token} | G40: Query: page, size(기본50), status | H40: { "data": [Locker[]], "pagination": {...} } | I40: { "error": "SERVER_ERROR", "message": "락커 목록 조회에 실패했습니다." } | J40: Y | K40: SCR-060 | L40: FN-019 | M40: 개발완료 | O40: 락커 현황 | P40: 락커 조회 | Q40: number asc 정렬, branchId=1 | R40: UI-057, UI-058, UI-059, UI-060, UI-061
A41: API-051 | B41: 락커 배정 | C41: PUT | D41: /api/v1/lockers/{id}/assign | E41: 락커 배정. 회원+만료일 설정, status=IN_USE | F41: Authorization: Bearer {token} | G41: { "lockerId": "number (필수)", "memberId": "number (필수)", "memberName": "string (필수)", "expiresAt": "string (필수)" } | H41: { "data": Locker, "message": "락커가 배정되었습니다." } | I41: { "error": "ASSIGN_FAILED", "message": "락커 배정에 실패했습니다." } | J41: Y | K41: SCR-060 | L41: FN-020 | M41: 개발완료 | O41: 락커 현황 | P41: 락커 배정 | Q41: assignedAt 자동 설정 | R41: UI-057, UI-058, UI-059, UI-060, UI-061
A42: API-052 | B42: 락커 반납 | C42: PUT | D42: /api/v1/lockers/{id}/release | E42: 락커 반납. 회원/날짜 정보 null, status=AVAILABLE | F42: Authorization: Bearer {token} | G42: Path: id | H42: { "data": Locker, "message": "락커가 반납되었습니다." } | I42: { "error": "RELEASE_FAILED", "message": "락커 반납에 실패했습니다." } | J42: Y | K42: SCR-060 | L42: FN-021 | M42: 개발완료 | O42: 락커 현황 | P42: 락커 반납 | Q42: memberId/memberName/assignedAt/expiresAt null 처리 | R42: UI-057, UI-058, UI-059, UI-060, UI-061
A43: API-053 | B43: 락커 상태 변경 | C43: PUT | D43: /api/v1/lockers/{id}/status | E43: 락커 상태 변경 (점검/사용가능 등) | F43: Authorization: Bearer {token} | G43: { "status": "AVAILABLE|IN_USE|MAINTENANCE" } | H43: { "data": Locker, "message": "락커 상태가 변경되었습니다." } | I43: { "error": "UPDATE_FAILED", "message": "락커 상태 변경에 실패했습니다." } | J43: Y | K43: SCR-061 | L43: FN-022 | M43: 개발완료 | O43: 락커 관리 | P43: 락커 상태변경 | R43: UI-093, UI-094, UI-095, UI-096, UI-097
A44: API-060 | B44: 직원 목록 조회 | C44: GET | D44: /api/v1/staff | E44: 직원 목록 조회. 역할/활성 필터, 페이지네이션 | F44: Authorization: Bearer {token} | G44: Query: page, size, role, isActive | H44: { "data": [Staff[]], "pagination": {...} } | I44: { "error": "SERVER_ERROR", "message": "직원 목록 조회에 실패했습니다." } | J44: Y | K44: SCR-050 | L44: FN-023 | M44: 개발완료 | O44: 직원 목록 | P44: 직원 조회 | Q44: name asc 정렬, branchId=1 | R44: UI-053, UI-054, UI-055, UI-056
A45: API-061 | B45: 직원 단건 조회 | C45: GET | D45: /api/v1/staff/{id} | E45: 직원 ID로 상세 조회 | F45: Authorization: Bearer {token} | G45: Path: id | H45: { "data": Staff } | I45: { "error": "NOT_FOUND", "message": "직원 조회에 실패했습니다." } | J45: Y | K45: SCR-050 | L45: FN-023 | M45: 개발완료 | O45: 직원 목록 | P45: 직원 조회 | R45: UI-053, UI-054, UI-055, UI-056
A46: API-062 | B46: 직원 등록 | C46: POST | D46: /api/v1/staff | E46: 신규 직원 등록 | F46: Authorization: Bearer {token} | G46: { "name": "string (필수)", "phone": "string (필수)", "role": "string (필수)", "position": "string (필수)", "hireDate": "string (필수)", "email?": "string", "salary?": "number", "color?": "string" } | H46: { "data": Staff, "message": "직원이 등록되었습니다." } | I46: { "error": "CREATE_FAILED", "message": "직원 등록에 실패했습니다." } | J46: Y | K46: SCR-051 | L46: FN-024 | M46: 개발완료 | O46: 직원 등록 | P46: 직원 등록 | Q46: isActive=true, branchId=1 자동 | R46: UI-089, UI-090, UI-091, UI-092
A47: API-063 | B47: 직원 수정 | C47: PUT | D47: /api/v1/staff/{id} | E47: 직원 정보 부분 수정 | F47: Authorization: Bearer {token} | G47: Path: id Body: Partial<StaffRequest> | H47: { "data": Staff, "message": "직원 정보가 수정되었습니다." } | I47: { "error": "UPDATE_FAILED", "message": "직원 수정에 실패했습니다." } | J47: Y | K47: SCR-051 | L47: FN-025 | M47: 개발완료 | O47: 직원 등록 | P47: 직원 수정 | R47: UI-089, UI-090, UI-091, UI-092
A48: API-064 | B48: 직원 삭제 | C48: DELETE | D48: /api/v1/staff/{id} | E48: 직원 비활성화 (isActive=false) | F48: Authorization: Bearer {token} | G48: Path: id | H48: { "message": "직원이 삭제되었습니다." } | I48: { "error": "DELETE_FAILED", "message": "직원 삭제에 실패했습니다." } | J48: Y | K48: SCR-050 | L48: FN-026 | M48: 개발완료 | O48: 직원 목록 | P48: 직원 삭제 | Q48: soft delete: isActive=false | R48: UI-053, UI-054, UI-055, UI-056
A49: API-070 | B49: 급여 목록 조회 | C49: GET | D49: /api/v1/payroll | E49: 급여 목록 조회. 년/월/직원 필터, 페이지네이션 | F49: Authorization: Bearer {token} | G49: Query: page, size, year, month, staffId | H49: { "data": [Payroll[]], "pagination": {...} } | I49: { "error": "SERVER_ERROR", "message": "급여 목록 조회에 실패했습니다." } | J49: Y | K49: SCR-052 | L49: FN-027 | M49: 개발완료 | O49: 급여 관리 | P49: 급여 조회 | Q49: year desc, month desc 정렬 | R49: UI-108, UI-109, UI-110
A50: API-071 | B50: 급여 명세서 조회 | C50: GET | D50: /api/v1/payroll/{id}/statement | E50: 급여 명세서 상세 조회. payroll + details(JSON 배열) | F50: Authorization: Bearer {token} | G50: Path: payrollId | H50: { "data": { "payroll": Payroll, "details": [PayrollDetail[]] } } | I50: { "error": "NOT_FOUND", "message": "급여 명세서 조회에 실패했습니다." } | J50: Y | K50: SCR-053 | L50: FN-028 | M50: 개발완료 | O50: 급여 명세서 | P50: 급여 명세서 조회 | Q50: details: JSON 배열 파싱 | R50: UI-111, UI-112
A51: API-072 | B51: 급여 등록 | C51: POST | D51: /api/v1/payroll | E51: 새 급여 데이터 등록. netSalary 자동 계산(baseSalary+bonus-deduction) | F51: Authorization: Bearer {token} | G51: { "staffId": "number (필수)", "staffName": "string (필수)", "year": "number (필수)", "month": "number (필수)", "baseSalary": "number (필수)", "bonus?": "number", "deduction?": "number", "details?": "PayrollDetail[]" } | H51: { "data": Payroll, "message": "급여가 등록되었습니다." } | I51: { "error": "CREATE_FAILED", "message": "급여 등록에 실패했습니다." } | J51: Y | K51: SCR-052 | L51: FN-029 | M51: 개발완료 | O51: 급여 관리 | P51: 급여 등록 | Q51: netSalary = baseSalary + bonus - deduction, status=PENDING | R51: UI-108, UI-109, UI-110
A52: API-073 | B52: 급여 지급 처리 | C52: PUT | D52: /api/v1/payroll/{id}/process | E52: 급여 지급 처리. status=PAID, paidAt=now | F52: Authorization: Bearer {token} | G52: Path: payrollId | H52: { "data": Payroll, "message": "급여가 지급 처리되었습니다." } | I52: { "error": "PROCESS_FAILED", "message": "급여 지급 처리에 실패했습니다." } | J52: Y | K52: SCR-052 | L52: FN-030 | M52: 개발완료 | O52: 급여 관리 | P52: 급여 지급 | Q52: status: PENDING→PAID, paidAt 자동 설정 | R52: UI-108, UI-109, UI-110
A53: API-080 | B53: 메시지 발송 | C53: POST | D53: /api/v1/messages/send | E53: 메시지 발송 (SMS/카카오/푸시). 예약 발송 지원 | F53: Authorization: Bearer {token} | G53: { "type": "SMS|KAKAO|PUSH (필수)", "recipients": "string[] (필수)", "content": "string (필수)", "title?": "string", "scheduledAt?": "string (예약시간)" } | H53: { "data": Message, "message": "메시지가 발송되었습니다." | "메시지가 예약되었습니다." } | I53: { "error": "SEND_FAILED", "message": "error.message" } | J53: Y | K53: SCR-062 | L53: FN-031 | M53: 개발완료 | O53: 메시지 발송 | P53: 메시지 발송 | Q53: scheduledAt 있으면 SCHEDULED, 없으면 SENT + sentAt=now | R53: UI-098, UI-099, UI-100
A54: API-081 | B54: 메시지 이력 조회 | C54: GET | D54: /api/v1/messages/history | E54: 메시지 발송 이력 조회. 유형/기간 필터, 페이지네이션 | F54: Authorization: Bearer {token} | G54: Query: page, size(기본10), type, startDate, endDate | H54: { "data": [Message[]], "pagination": {...} } | I54: { "error": "SERVER_ERROR", "message": "error.message" } | J54: Y | K54: SCR-063 | L54: FN-032 | M54: 개발완료 | O54: 메시지 이력 | P54: 메시지 이력 조회 | Q54: sentAt desc 정렬, branchId 필터 | R54: UI-127, UI-128, UI-129
A55: API-090 | B55: 설정 조회 | C55: GET | D55: /api/v1/settings | E55: 지점 설정 조회 (영업시간/알림/회원권) | F55: Authorization: Bearer {token} | G55: Query: branchId (기본1) | H55: { "data": { "branchName": "string", "businessHours": {"open": "06:00", "close": "22:00", "holidays": []}, "notifications": {"smsEnabled": false, "kakaoEnabled": false, "pushEnabled": false}, "membership": {"autoExpireNotification": false, "expireNoticeDays": 7} } } | I55: { "error": "NOT_FOUND", "message": "설정 데이터를 찾을 수 없습니다." } | J55: Y | K55: SCR-080 | L55: FN-033 | M55: 개발완료 | O55: 설정 | P55: 설정 조회 | Q55: maybeSingle: 데이터 없으면 null | R55: UI-067, UI-068, UI-069, UI-070, UI-071, UI-072
A56: API-091 | B56: 설정 수정 | C56: PUT | D56: /api/v1/settings | E56: 지점 설정 수정. 부분 업데이트 지원 | F56: Authorization: Bearer {token} | G56: Body: Partial<Settings> (branchName, businessHours.open/close/holidays, notifications.sms/kakao/push, membership.autoExpire/days) | H56: { "data": Settings, "message": "설정이 저장되었습니다." } | I56: { "error": "UPDATE_FAILED", "message": "error.message" } | J56: Y | K56: SCR-080 | L56: FN-034 | M56: 개발완료 | O56: 설정 | P56: 설정 수정 | Q56: DB 컬럼명 매핑: centerName, businessHoursOpen/Close 등 | R56: UI-067, UI-068, UI-069, UI-070, UI-071, UI-072
A57: API-100 | B57: 지점 목록 조회 (페이지네이션) | C57: GET | D57: /api/v1/branches/paginated | E57: 관리자용 지점 목록 조회. 페이지네이션 | F57: Authorization: Bearer {token} | G57: Query: page, size(기본10) | H57: { "data": [BranchDetail[]], "pagination": {...} } | I57: { "error": "SERVER_ERROR", "message": "error.message" } | J57: Y | K57: SCR-081 | L57: FN-035 | M57: 개발완료 | O57: 지점 관리 | P57: 지점 조회 | Q57: id asc 정렬 | R57: UI-113, UI-114
A58: API-101 | B58: 지점 상세 조회 | C58: GET | D58: /api/v1/branches/{id} | E58: 지점 단건 상세 조회 | F58: Authorization: Bearer {token} | G58: Path: id | H58: { "data": BranchDetail } | I58: { "error": "NOT_FOUND", "message": "error.message" } | J58: Y | K58: SCR-081 | L58: FN-035 | M58: 개발완료 | O58: 지점 관리 | P58: 지점 조회 | R58: UI-113, UI-114
A59: API-102 | B59: 지점 등록 | C59: POST | D59: /api/v1/branches | E59: 신규 지점 등록 | F59: Authorization: Bearer {token} | G59: { "name": "string (필수)", "address": "string (필수)", "phone": "string (필수)", "status?": "string", "managerId?": "number", "managerName?": "string" } | H59: { "data": BranchDetail, "message": "지점이 등록되었습니다." } | I59: { "error": "CREATE_FAILED", "message": "error.message" } | J59: Y | K59: SCR-081 | L59: FN-036 | M59: 개발완료 | O59: 지점 관리 | P59: 지점 등록 | Q59: isActive=true 자동 설정 | R59: UI-113, UI-114
A60: API-103 | B60: 지점 수정 | C60: PUT | D60: /api/v1/branches/{id} | E60: 지점 정보 부분 수정 | F60: Authorization: Bearer {token} | G60: Path: id Body: Partial<BranchRequest> | H60: { "data": BranchDetail, "message": "지점 정보가 수정되었습니다." } | I60: { "error": "UPDATE_FAILED", "message": "error.message" } | J60: Y | K60: SCR-081 | L60: FN-037 | M60: 개발완료 | O60: 지점 관리 | P60: 지점 수정 | Q60: undefined 필드 제외 | R60: UI-113, UI-114

Sheet 데이터 정의서
A1: 테이블명 | B1: 컬럼명 | C1: 데이터 타입 | D1: 길이 | E1: NULL 허용 | F1: 기본값 | G1: PK | H1: FK | I1: 인덱스 | J1: 설명 | K1: 관련 API ID | L1: 상태 | M1: 비고
A2: tenants | B2: id | C2: BIGINT | E2: N | G2: Y | I2: Y | J2: 테넌트 고유 ID (auto increment) | K2: API-003 | L2: 확정
A3: tenants | B3: name | C3: VARCHAR | D3: 100 | E3: N | G3: N | I3: N | J3: 테넌트(본사) 이름 | K3: API-001 | L3: 확정
A4: tenants | B4: code | C4: VARCHAR | D4: 20 | E4: N | G4: N | I4: UNIQUE | J4: 테넌트 코드 (고유) | K4: API-001 | L4: 확정
A5: tenants | B5: plan | C5: ENUM | E5: N | F5: basic | G5: N | I5: N | J5: 요금제 (basic/standard/premium) | K5: API-001 | L5: 확정
A6: tenants | B6: status | C6: ENUM | E6: N | F6: active | G6: N | I6: Y | J6: 상태 (active/inactive/suspended) | K6: API-001 | L6: 확정
A7: tenants | B7: created_at | C7: DATETIME | E7: N | F7: NOW() | G7: N | I7: N | J7: 생성일시 | K7: API-001 | L7: 확정
A8: tenants | B8: updated_at | C8: DATETIME | E8: Y | F8: CURRENT_TIMESTAMP | G8: N | I8: N | J8: 수정일시 | K8: API-001 | L8: 확정
A9: branches | B9: id | C9: BIGINT | E9: N | G9: Y | I9: Y | J9: 지점 고유 ID | K9: API-027 | L9: 확정
A10: branches | B10: tenant_id | C10: BIGINT | E10: N | G10: N | H10: tenants.id | I10: Y | J10: 소속 테넌트 FK | K10: API-027, API-028, API-029 | L10: 확정
A11: branches | B11: name | C11: VARCHAR | D11: 100 | E11: N | G11: N | I11: N | J11: 지점명 | K11: API-027, API-028, API-029 | L11: 확정
A12: branches | B12: code | C12: VARCHAR | D12: 20 | E12: N | G12: N | I12: UNIQUE | J12: 지점 코드 (고유) | K12: API-027, API-028, API-029 | L12: 확정
A13: branches | B13: address | C13: VARCHAR | D13: 255 | E13: Y | G13: N | I13: N | J13: 지점 주소 | K13: API-027, API-028, API-029 | L13: 확정
A14: branches | B14: phone | C14: VARCHAR | D14: 20 | E14: Y | G14: N | I14: N | J14: 지점 연락처 | K14: API-027, API-028, API-029 | L14: 확정
A15: branches | B15: status | C15: ENUM | E15: N | F15: active | G15: N | I15: Y | J15: 상태 (active/inactive) | K15: API-027, API-028, API-029 | L15: 확정
A16: branches | B16: created_at | C16: DATETIME | E16: N | F16: NOW() | G16: N | I16: N | J16: 생성일시 | K16: API-027, API-028, API-029 | L16: 확정
A17: users | B17: id | C17: BIGINT | E17: N | G17: Y | I17: Y | J17: 사용자 고유 ID | K17: API-001 | L17: 확정
A18: users | B18: branch_id | C18: BIGINT | E18: N | G18: N | H18: branches.id | I18: Y | J18: 소속 지점 FK | K18: API-002, API-003 | L18: 확정
A19: users | B19: email | C19: VARCHAR | D19: 100 | E19: N | G19: N | I19: UNIQUE | J19: 로그인 이메일 | K19: API-002, API-003 | L19: 확정
A20: users | B20: password_hash | C20: VARCHAR | D20: 255 | E20: N | G20: N | I20: N | J20: 비밀번호 해시 | K20: API-002, API-003 | L20: 확정
A21: users | B21: name | C21: VARCHAR | D21: 50 | E21: N | G21: N | I21: Y | J21: 사용자 이름 | K21: API-002, API-003 | L21: 확정
A22: users | B22: role | C22: ENUM | E22: N | G22: N | I22: Y | J22: 역할 (super_admin/center_manager/manager/fc/staff/viewer) | K22: API-002, API-003 | L22: 확정
A23: users | B23: status | C23: ENUM | E23: N | F23: active | G23: N | I23: Y | J23: 상태 (active/inactive/locked) | K23: API-002, API-003 | L23: 확정
A24: users | B24: last_login | C24: DATETIME | E24: Y | F24: NULL | G24: N | I24: N | J24: 마지막 로그인 일시 | K24: API-002, API-003 | L24: 확정
A25: users | B25: login_fail_count | C25: INT | E25: N | F25: 0 | G25: N | I25: N | J25: 연속 로그인 실패 횟수 | K25: API-002, API-003 | L25: 확정
A26: users | B26: created_at | C26: DATETIME | E26: N | F26: NOW() | G26: N | I26: N | J26: 생성일시 | K26: API-002, API-003 | L26: 확정
A27: members | B27: id | C27: BIGINT | E27: N | G27: Y | I27: Y | J27: 회원 고유 ID | K27: API-007 | L27: 확정
A28: members | B28: branch_id | C28: BIGINT | E28: N | G28: N | H28: branches.id | I28: Y | J28: 소속 지점 FK (데이터 격리) | K28: API-004, API-005, API-006, API-007 | L28: 확정
A29: members | B29: name | C29: VARCHAR | D29: 50 | E29: N | G29: N | I29: Y | J29: 회원 이름 | K29: API-004, API-005, API-006, API-007 | L29: 확정
A30: members | B30: gender | C30: ENUM | E30: N | G30: N | I30: Y | J30: 성별 (M/F) | K30: API-004, API-005, API-006, API-007 | L30: 확정
A31: members | B31: birth_date | C31: VARCHAR | D31: 10 | E31: Y | G31: N | I31: N | J31: 생년월일 (YYYY-MM-DD) | K31: API-004, API-005, API-006, API-007 | L31: 확정
A32: members | B32: phone | C32: VARCHAR | D32: 20 | E32: N | G32: N | I32: Y | J32: 연락처 | K32: API-004, API-005, API-006, API-007 | L32: 확정 | M32: 지점 내 중복 불가
A33: members | B33: email | C33: VARCHAR | D33: 100 | E33: Y | G33: N | I33: N | J33: 이메일 | K33: API-004, API-005, API-006, API-007 | L33: 확정
A34: members | B34: address | C34: VARCHAR | D34: 255 | E34: Y | G34: N | I34: N | J34: 주소 | K34: API-004, API-005, API-006, API-007 | L34: 확정
A35: members | B35: status | C35: ENUM | E35: N | F35: active | G35: N | I35: Y | J35: 상태 (active/expired/suspended/withdrawn) | K35: API-004, API-005, API-006, API-007 | L35: 확정
A36: members | B36: manager_id | C36: BIGINT | E36: Y | F36: NULL | G36: N | H36: users.id | I36: Y | J36: 담당 FC ID | K36: API-004, API-005, API-006, API-007 | L36: 확정
A37: members | B37: attendance_no | C37: VARCHAR | D37: 20 | E37: Y | G37: N | I37: UNIQUE | J37: 출석 번호 | K37: API-004, API-005, API-006, API-007 | L37: 확정
A38: members | B38: company | C38: VARCHAR | D38: 100 | E38: Y | G38: N | I38: N | J38: 직장명 | K38: API-004, API-005, API-006, API-007 | L38: 확정
A39: members | B39: memo | C39: TEXT | E39: Y | G39: N | I39: N | J39: 관리자 메모 | K39: API-004, API-005, API-006, API-007 | L39: 확정
A40: members | B40: first_reg_date | C40: DATETIME | E40: N | F40: NOW() | G40: N | I40: N | J40: 최초 등록일 | K40: API-004, API-005, API-006, API-007 | L40: 확정
A41: members | B41: created_at | C41: DATETIME | E41: N | F41: NOW() | G41: N | I41: N | J41: 생성일시 | K41: API-004, API-005, API-006, API-007 | L41: 확정
A42: members | B42: updated_at | C42: DATETIME | E42: Y | F42: CURRENT_TIMESTAMP | G42: N | I42: N | J42: 수정일시 | K42: API-004, API-005, API-006, API-007 | L42: 확정
A43: member_tickets | B43: id | C43: BIGINT | E43: N | G43: Y | I43: Y | J43: 이용권 고유 ID | K43: API-008 | L43: 확정
A44: member_tickets | B44: member_id | C44: BIGINT | E44: N | G44: N | H44: members.id | I44: Y | J44: 회원 FK | K44: API-008, API-009 | L44: 확정
A45: member_tickets | B45: branch_id | C45: BIGINT | E45: N | G45: N | H45: branches.id | I45: Y | J45: 지점 FK | K45: API-008, API-009 | L45: 확정
A46: member_tickets | B46: product_id | C46: BIGINT | E46: N | G46: N | H46: products.id | I46: Y | J46: 상품 FK | K46: API-008, API-009 | L46: 확정
A47: member_tickets | B47: type | C47: ENUM | E47: N | G47: N | I47: Y | J47: 유형 (period/count/unlimited) | K47: API-008, API-009 | L47: 확정
A48: member_tickets | B48: start_date | C48: DATETIME | E48: N | G48: N | I48: Y | J48: 시작일 | K48: API-008, API-009 | L48: 확정
A49: member_tickets | B49: end_date | C49: DATETIME | E49: Y | F49: NULL | G49: N | I49: Y | J49: 종료일 | K49: API-008, API-009 | L49: 확정
A50: member_tickets | B50: remaining_count | C50: INT | E50: Y | F50: 0 | G50: N | I50: N | J50: 잔여 횟수 (횟수제) | K50: API-008, API-009 | L50: 확정
A51: member_tickets | B51: status | C51: ENUM | E51: N | F51: active | G51: N | I51: Y | J51: 상태 (active/expired/suspended/cancelled) | K51: API-008, API-009 | L51: 확정
A52: member_tickets | B52: created_at | C52: DATETIME | E52: N | F52: NOW() | G52: N | I52: N | J52: 생성일시 | K52: API-008, API-009 | L52: 확정
A53: attendance | B53: id | C53: BIGINT | E53: N | G53: Y | I53: Y | J53: 출석 고유 ID | K53: API-013 | L53: 확정
A54: attendance | B54: branch_id | C54: BIGINT | E54: N | G54: N | H54: branches.id | I54: Y | J54: 지점 FK | K54: API-012, API-013 | L54: 확정
A55: attendance | B55: member_id | C55: BIGINT | E55: N | G55: N | H55: members.id | I55: Y | J55: 회원 FK | K55: API-012, API-013 | L55: 확정
A56: attendance | B56: type | C56: ENUM | E56: N | F56: normal | G56: N | I56: Y | J56: 출석 유형 (normal/pt/gx) | K56: API-012, API-013 | L56: 확정
A57: attendance | B57: status | C57: ENUM | E57: N | F57: checkIn | G57: N | I57: Y | J57: 상태 (checkIn/checkOut) | K57: API-012, API-013 | L57: 확정
A58: attendance | B58: category | C58: VARCHAR | D58: 50 | E58: Y | G58: N | I58: N | J58: 카테고리 | K58: API-012, API-013 | L58: 확정
A59: attendance | B59: door | C59: VARCHAR | D59: 50 | E59: Y | G59: N | I59: N | J59: 출입문 정보 | K59: API-012, API-013 | L59: 확정
A60: attendance | B60: in_time | C60: DATETIME | E60: N | G60: N | I60: Y | J60: 입장 시간 | K60: API-012, API-013 | L60: 확정
A61: attendance | B61: out_time | C61: DATETIME | E61: Y | F61: NULL | G61: N | I61: N | J61: 퇴장 시간 | K61: API-012, API-013 | L61: 확정
A62: attendance | B62: visit_count | C62: INT | E62: N | F62: 1 | G62: N | I62: N | J62: 누적 방문 횟수 | K62: API-012, API-013 | L62: 확정
A63: attendance | B63: pass_info | C63: VARCHAR | D63: 50 | E63: Y | G63: N | I63: N | J63: 출입 수단 정보 (RFID/앱 등) | K63: API-012, API-013 | L63: 확정
A64: attendance | B64: is_other_branch | C64: BOOLEAN | E64: N | F64: false | G64: N | I64: Y | J64: 타지점 출석 여부 | K64: API-012, API-013 | L64: 확정
A65: attendance | B65: created_at | C65: DATETIME | E65: N | F65: NOW() | G65: N | I65: N | J65: 생성일시 | K65: API-012, API-013 | L65: 확정
A66: sales | B66: id | C66: BIGINT | E66: N | G66: Y | I66: Y | J66: 매출 고유 ID | K66: API-015 | L66: 확정
A67: sales | B67: branch_id | C67: BIGINT | E67: N | G67: N | H67: branches.id | I67: Y | J67: 지점 FK | K67: API-036, API-037 | L67: 확정
A68: sales | B68: no | C68: VARCHAR | D68: 30 | E68: N | G68: N | I68: UNIQUE | J68: 매출 번호 (R + 날짜 + 순번) | K68: API-036, API-037 | L68: 확정
A69: sales | B69: purchase_date | C69: DATETIME | E69: N | G69: N | I69: Y | J69: 결제 일시 | K69: API-036, API-037 | L69: 확정
A70: sales | B70: type | C70: VARCHAR | D70: 50 | E70: N | G70: N | I70: Y | J70: 매출 유형 (membership/pt/gx/product/etc) | K70: API-036, API-037 | L70: 확정
A71: sales | B71: product_name | C71: VARCHAR | D71: 100 | E71: N | G71: N | I71: N | J71: 상품명 | K71: API-036, API-037 | L71: 확정
A72: sales | B72: manager_id | C72: BIGINT | E72: Y | F72: NULL | G72: N | H72: users.id | I72: Y | J72: 담당자 FK | K72: API-036, API-037 | L72: 확정
A73: sales | B73: buyer_id | C73: BIGINT | E73: Y | F73: NULL | G73: N | H73: members.id | I73: Y | J73: 구매 회원 FK | K73: API-036, API-037 | L73: 확정
A74: sales | B74: quantity | C74: INT | E74: N | F74: 1 | G74: N | I74: N | J74: 수량 | K74: API-036, API-037 | L74: 확정
A75: sales | B75: original_price | C75: INT | E75: N | F75: 0 | G75: N | I75: N | J75: 원가 | K75: API-036, API-037 | L75: 확정
A76: sales | B76: sale_price | C76: INT | E76: N | F76: 0 | G76: N | I76: N | J76: 판매가 | K76: API-036, API-037 | L76: 확정
A77: sales | B77: discount_price | C77: INT | E77: N | F77: 0 | G77: N | I77: N | J77: 할인 금액 | K77: API-036, API-037 | L77: 확정
A78: sales | B78: payment_method | C78: VARCHAR | D78: 20 | E78: N | G78: N | I78: Y | J78: 결제수단 (cash/card/mileage/mixed) | K78: API-036, API-037 | L78: 확정
A79: sales | B79: cash | C79: INT | E79: N | F79: 0 | G79: N | I79: N | J79: 현금 결제액 | K79: API-036, API-037 | L79: 확정
A80: sales | B80: card | C80: INT | E80: N | F80: 0 | G80: N | I80: N | J80: 카드 결제액 | K80: API-036, API-037 | L80: 확정
A81: sales | B81: mileage | C81: INT | E81: N | F81: 0 | G81: N | I81: N | J81: 마일리지 결제액 | K81: API-036, API-037 | L81: 확정
A82: sales | B82: card_company | C82: VARCHAR | D82: 50 | E82: Y | G82: N | I82: N | J82: 카드사 | K82: API-036, API-037 | L82: 확정
A83: sales | B83: card_number | C83: VARCHAR | D83: 20 | E83: Y | G83: N | I83: N | J83: 카드번호 (마스킹) | K83: API-036, API-037 | L83: 확정
A84: sales | B84: approval_no | C84: VARCHAR | D84: 30 | E84: Y | G84: N | I84: N | J84: 승인번호 | K84: API-036, API-037 | L84: 확정
A85: sales | B85: unpaid | C85: INT | E85: N | F85: 0 | G85: N | I85: N | J85: 미납 금액 | K85: API-036, API-037 | L85: 확정
A86: sales | B86: status | C86: ENUM | E86: N | F86: completed | G86: N | I86: Y | J86: 상태 (completed/refunded/partial_refund/unpaid) | K86: API-036, API-037 | L86: 확정
A87: sales | B87: category | C87: VARCHAR | D87: 50 | E87: Y | G87: N | I87: N | J87: 매출 카테고리 | K87: API-036, API-037 | L87: 확정
A88: sales | B88: memo | C88: TEXT | E88: Y | G88: N | I88: N | J88: 메모 | K88: API-036, API-037 | L88: 확정
A89: sales | B89: created_at | C89: DATETIME | E89: N | F89: NOW() | G89: N | I89: N | J89: 생성일시 | K89: API-036, API-037 | L89: 확정
A90: products | B90: id | C90: BIGINT | E90: N | G90: Y | I90: Y | J90: 상품 고유 ID | K90: API-018 | L90: 확정
A91: products | B91: branch_id | C91: BIGINT | E91: N | G91: N | H91: branches.id | I91: Y | J91: 지점 FK | K91: API-016, API-017, API-018 | L91: 확정
A92: products | B92: category | C92: VARCHAR | D92: 50 | E92: N | G92: N | I92: Y | J92: 대분류 카테고리 | K92: API-016, API-017, API-018 | L92: 확정
A93: products | B93: category_key | C93: ENUM | E93: N | G93: N | I93: Y | J93: 카테고리 키 (membership/pt/gx/etc) | K93: API-016, API-017, API-018 | L93: 확정
A94: products | B94: sub_category | C94: VARCHAR | D94: 50 | E94: Y | G94: N | I94: N | J94: 소분류 | K94: API-016, API-017, API-018 | L94: 확정
A95: products | B95: name | C95: VARCHAR | D95: 100 | E95: N | G95: N | I95: Y | J95: 상품명 | K95: API-016, API-017, API-018 | L95: 확정
A96: products | B96: cash_price | C96: INT | E96: N | F96: 0 | G96: N | I96: N | J96: 현금가 | K96: API-016, API-017, API-018 | L96: 확정
A97: products | B97: card_price | C97: INT | E97: N | F97: 0 | G97: N | I97: N | J97: 카드가 | K97: API-016, API-017, API-018 | L97: 확정
A98: products | B98: period | C98: INT | E98: Y | F98: NULL | G98: N | I98: N | J98: 이용 기간 (일수) | K98: API-016, API-017, API-018 | L98: 확정
A99: products | B99: kiosk_exposure | C99: BOOLEAN | E99: N | F99: true | G99: N | I99: N | J99: 키오스크 노출 여부 | K99: API-016, API-017, API-018 | L99: 확정
A100: products | B100: status | C100: ENUM | E100: N | F100: active | G100: N | I100: Y | J100: 상태 (active/inactive) | K100: API-016, API-017, API-018 | L100: 확정
...

Sheet QA테스트케이스
A1: TC-ID | B1: 플랫폼 | C1: 테스트 영역 | D1: 하위 영역 | E1: 테스트 유형 | F1: 테스트 시나리오 | G1: 사전 조건 | H1: 테스트 절차 | I1: 기대 결과 | J1: 실제 결과 | K1: 테스트 상태 | L1: 우선순위 | M1: 심각도 | N1: 담당자 | O1: 테스트 환경 | P1: 브라우저/앱 | Q1: 디바이스 | R1: OS | S1: 테스트 사이클 | T1: 자동화 여부 | U1: 화면 ID | V1: 기능 ID | W1: API ID | X1: 버그 티켓 | Y1: 스크린샷 | Z1: [자동] 화면명 | AA1: [자동] 기능명 | AB1: [자동] API 엔드포인트 | AC1: 비고
A2: TC-001 | B2: Web | C2: 인증 | D2: 로그인 | E2: 기능 테스트 | F2: 정상 로그인 - 올바른 이메일/비밀번호로 로그인 | G2: 등록된 계정 존재, 활성 상태 | H2: 1) 로그인 페이지 접속 2) 이메일 입력 3) 비밀번호 입력 4) 지점 선택 5) 로그인 버튼 클릭 | I2: 대시보드(SCR-002)로 이동, JWT 토큰 저장, 사용자 정보 표시 | J2: 대시보드(/)로 정상 이동, 사이드바 사용자정보 표시, branchId localStorage 저장 | K2: 통과 | L2: Critical | M2: Critical | N2: QA담당자1 | O2: Staging | P2: Chrome | Q2: Desktop | R2: Windows 11 | S2: 1차 | T2: 수동 | U2: SCR-001 | V2: FN-001 | W2: API-001 | Z2: 로그인 | AA2: 로그인 | AB2: /api/v1/auth/login
A3: TC-002 | B3: Web | C3: 인증 | D3: 로그인 | E3: 기능 테스트 | F3: 로그인 실패 - 잘못된 비밀번호 | G3: 등록된 계정 존재 | H3: 1) 로그인 페이지 접속 2) 올바른 이메일 입력 3) 잘못된 비밀번호 입력 4) 로그인 버튼 클릭 | I3: '비밀번호가 올바르지 않습니다' 에러 메시지 표시, 로그인 실패 횟수 +1 | J3: "아이디 또는 비밀번호가 올바르지 않습니다." 에러 메시지 정상 표시 | K3: 통과 | L3: Critical | M3: Critical | N3: QA담당자1 | O3: Staging | P3: Chrome | Q3: Desktop | R3: Windows 11 | S3: 1차 | T3: 수동 | U3: SCR-001 | V3: FN-001 | W3: API-001 | Z3: 로그인 | AA3: 로그인 | AB3: /api/v1/auth/login
A4: TC-003 | B4: Web | C4: 인증 | D4: 로그인 | E4: 기능 테스트 | F4: 계정 잠금 - 5회 연속 실패 | G4: 등록된 계정 존재, 실패 횟수 4회 | H4: 1) 잘못된 비밀번호로 5번째 로그인 시도 | I4: '5회 실패로 계정이 잠겼습니다. 30분 후 다시 시도하세요' 메시지 표시 | J4: 미입력 시 에러 메시지 표시, 로그인 버튼 비활성화 | K4: 통과 | L4: Critical | M4: Blocker | N4: QA담당자1 | O4: Staging | P4: Chrome | Q4: Desktop | R4: Windows 11 | S4: 1차 | T4: 수동 | U4: SCR-001 | V4: FN-001 | W4: API-001 | Z4: 로그인 | AA4: 로그인 | AB4: /api/v1/auth/login
A5: TC-004 | B5: Web | C5: 인증 | D5: 로그인 | E5: UI/UX 테스트 | F5: 비밀번호 마스킹 토글 | G5: 로그인 페이지 접속 | H5: 1) 비밀번호 입력 2) 눈 아이콘 클릭 3) 비밀번호 표시 확인 4) 다시 클릭하여 마스킹 | I5: 토글에 따라 비밀번호 표시/마스킹 전환 | J5: E2E 검증 완료 (2026-03-12) | K5: 통과 | L5: Medium | M5: Minor | N5: QA담당자1 | O5: Staging | P5: Chrome | Q5: Desktop | R5: Windows 11 | S5: 1차 | T5: 수동 | U5: SCR-001 | V5: FN-001 | Z5: 로그인 | AA5: 로그인 | AB5: /api/v1/auth/login
A6: TC-005 | B6: Web | C6: 대시보드 | D6: 통계 | E6: 기능 테스트 | F6: 대시보드 KPI 카드 정확성 | G6: 로그인 완료, 테스트 데이터 존재 | H6: 1) 대시보드 접속 2) 총회원/활성/만료임박/만료 카드 수치 확인 3) DB 데이터와 대조 | I6: 카드 수치가 DB 실제 데이터와 일치 | J6: E2E 검증 완료: 실 DB 데이터 기반 통계카드, 차트, 리스트 정상 표시 | K6: 통과 | L6: Critical | M6: Critical | N6: QA담당자1 | O6: Staging | P6: Chrome | Q6: Desktop | R6: Windows 11 | S6: 1차 | T6: 자동화 예정 | U6: SCR-002 | V6: FN-002 | W6: API-003 | Z6: 대시보드 | AA6: 대시보드 통계 조회 | AB6: /api/v1/dashboard/stats
A7: TC-006 | B7: Web | C7: 대시보드 | D7: 통계 | E7: 기능 테스트 | F7: 생일 회원 리스트 표시 | G7: 오늘 생일인 회원 데이터 존재 | H7: 1) 대시보드 접속 2) 생일 회원 섹션 확인 | I7: 오늘 생일인 회원 목록 표시, 이름/연락처 표시 | J7: E2E 검증 완료: 실 DB 데이터 기반 통계카드, 차트, 리스트 정상 표시 | K7: 통과 | L7: High | M7: Major | N7: QA담당자1 | O7: Staging | P7: Chrome | Q7: Desktop | R7: Windows 11 | S7: 1차 | T7: 수동 | U7: SCR-002 | V7: FN-002 | W7: API-004 | Z7: 대시보드 | AA7: 대시보드 통계 조회 | AB7: /api/v1/dashboard/birthday-members
A8: TC-007 | B8: Web | C8: 회원관리 | D8: 목록 | E8: 기능 테스트 | F8: 회원 검색 - 이름으로 검색 | G8: 회원 데이터 존재 | H8: 1) 회원 목록 페이지 접속 2) 검색바에 '김' 입력 3) 300ms 대기 | I8: '김'이 포함된 회원만 필터링되어 표시 | J8: E2E 검증 완료: Supabase 실 데이터 연동, soft delete 필터, 검색/필터/정렬 정상 | K8: 통과 | L8: Critical | M8: Critical | N8: QA담당자1 | O8: Staging | P8: Chrome | Q8: Desktop | R8: Windows 11 | S8: 1차 | T8: 자동화 예정 | U8: SCR-010 | V8: FN-003 | W8: API-007 | Z8: 회원 목록 | AA8: 회원 목록 조회/검색/필터 | AB8: /api/v1/members
A9: TC-008 | B9: Web | C9: 회원관리 | D9: 목록 | E9: 기능 테스트 | F9: 회원 필터 - 상태 필터 적용 | G9: 다양한 상태의 회원 데이터 존재 | H9: 1) 상태 필터에서 '만료' 선택 2) 목록 갱신 확인 | I9: 만료 상태 회원만 표시, 건수 일치 | J9: E2E 검증 완료: Supabase 실 데이터 연동, soft delete 필터, 검색/필터/정렬 정상 | K9: 통과 | L9: High | M9: Major | N9: QA담당자1 | O9: Staging | P9: Chrome | Q9: Desktop | R9: Windows 11 | S9: 1차 | T9: 수동 | U9: SCR-010 | V9: FN-003 | W9: API-007 | Z9: 회원 목록 | AA9: 회원 목록 조회/검색/필터 | AB9: /api/v1/members
A10: TC-009 | B10: Web | C10: 회원관리 | D10: 등록 | E10: 기능 테스트 | F10: 신규 회원 정상 등록 | G10: 로그인 완료, 매니저 이상 권한 | H10: 1) '회원등록' 버튼 클릭 2) 이름 입력: 테스트회원 3) 성별: 남 선택 4) 연락처: 010-1111-2222 5) '저장' 클릭 | I10: 회원 등록 성공 메시지, 회원 상세 페이지로 이동 | J10: E2E 검증 완료: Supabase 실 데이터 연동, soft delete 필터, 검색/필터/정렬 정상 | K10: 통과 | L10: Critical | M10: Critical | N10: QA담당자1 | O10: Staging | P10: Chrome | Q10: Desktop | R10: Windows 11 | S10: 1차 | T10: 자동화 예정 | U10: SCR-012 | V10: FN-004 | W10: API-009 | Z10: 회원 등록 | AA10: 회원 등록 | AB10: /api/v1/members
A11: TC-010 | B11: Web | C11: 회원관리 | D11: 등록 | E11: 기능 테스트 | F11: 회원 등록 실패 - 연락처 중복 | G11: 동일 연락처 회원 이미 존재 | H11: 1) 회원 등록 폼에 중복 연락처 입력 2) '저장' 클릭 | I11: '이미 등록된 연락처입니다' 에러 메시지 표시 | J11: E2E 검증 완료: Supabase 실 데이터 연동, soft delete 필터, 검색/필터/정렬 정상 | K11: 통과 | L11: High | M11: Major | N11: QA담당자1 | O11: Staging | P11: Chrome | Q11: Desktop | R11: Windows 11 | S11: 1차 | T11: 수동 | U11: SCR-012 | V11: FN-004 | W11: API-009 | Z11: 회원 등록 | AA11: 회원 등록 | AB11: /api/v1/members
A12: TC-011 | B12: Web | C12: 회원관리 | D12: 등록 | E12: UI/UX 테스트 | F12: 필수 항목 유효성 검사 | G12: 회원 등록 폼 접속 | H12: 1) 아무것도 입력하지 않고 '저장' 클릭 | I12: 필수 항목(이름/성별/연락처)에 에러 메시지 표시, 저장 불가 | J12: E2E 검증 완료: Supabase 실 데이터 연동, soft delete 필터, 검색/필터/정렬 정상 | K12: 통과 | L12: High | M12: Major | N12: QA담당자1 | O12: Staging | P12: Chrome | Q12: Desktop | R12: Windows 11 | S12: 1차 | T12: 수동 | U12: SCR-012 | V12: FN-004 | Z12: 회원 등록 | AA12: 회원 등록 | AB12: /api/v1/members
A13: TC-012 | B13: Web | C13: 회원관리 | D13: 상세 | E13: 기능 테스트 | F13: 회원 상세 탭 전환 | G13: 회원 데이터 존재 | H13: 1) 회원 상세 페이지 접속 2) 이용권 탭 클릭 3) 출석 탭 클릭 4) 결제 탭 클릭 5) 체성분 탭 클릭 6) 메모 탭 클릭 | I13: 각 탭별 데이터 정상 로드, URL 파라미터 유지 | J13: E2E 검증 완료: Supabase 실 데이터 연동, soft delete 필터, 검색/필터/정렬 정상 | K13: 통과 | L13: High | M13: Major | N13: QA담당자1 | O13: Staging | P13: Chrome | Q13: Desktop | R13: Windows 11 | S13: 1차 | T13: 수동 | U13: SCR-011 | V13: FN-006 | W13: API-008 | Z13: 회원 상세 | AA13: 회원 상세 조회 | AB13: /api/v1/members/:id
A14: TC-013 | B14: Web | C14: 회원관리 | D14: 수정 | E14: 기능 테스트 | F14: 회원 정보 수정 | G14: 회원 데이터 존재 | H14: 1) 회원 상세 → '수정' 클릭 2) 이름 변경 3) '저장' 클릭 | I14: 수정 성공, 변경 이력 기록, 상세 페이지로 이동 | J14: E2E 검증 완료: Supabase 실 데이터 연동, soft delete 필터, 검색/필터/정렬 정상 | K14: 통과 | L14: High | M14: Major | N14: QA담당자1 | O14: Staging | P14: Chrome | Q14: Desktop | R14: Windows 11 | S14: 1차 | T14: 수동 | U14: SCR-013 | V14: FN-005 | W14: API-010 | Z14: 회원 수정 | AA14: 회원 정보 수정 | AB14: /api/v1/members/:id
A15: TC-014 | B15: Web | C15: 매출관리 | D15: 조회 | E15: 기능 테스트 | F15: 매출 기간 필터 조회 | G15: 매출 데이터 존재 | H15: 1) 매출 조회 페이지 접속 2) 시작일/종료일 선택 3) 결과 확인 | I15: 선택 기간의 매출만 표시, 통계 카드 갱신 | J15: E2E 검증 완료 (2026-03-12) | K15: 통과 | L15: Critical | M15: Critical | N15: QA담당자1 | O15: Staging | P15: Chrome | Q15: Desktop | R15: Windows 11 | S15: 1차 | T15: 자동화 예정 | U15: SCR-030 | V15: FN-010 | W15: API-015 | Z15: 매출 조회 | AA15: 매출 조회/통계 | AB15: /api/v1/sales
A16: TC-015 | B16: Web | C16: 매출관리 | D16: 조회 | E16: 기능 테스트 | F16: 매출 엑셀 다운로드 | G16: 매출 데이터 존재 | H16: 1) 매출 조회 2) '엑셀 다운로드' 클릭 | I16: xlsx 파일 다운로드, 현재 필터 결과와 동일한 데이터 | J16: E2E 검증 완료 (2026-03-12) | K16: 통과 | L16: High | M16: Major | N16: QA담당자1 | O16: Staging | P16: Chrome | Q16: Desktop | R16: Windows 11 | S16: 1차 | T16: 수동 | U16: SCR-030 | V16: FN-010 | W16: API-015 | Z16: 매출 조회 | AA16: 매출 조회/통계 | AB16: /api/v1/sales
A17: TC-016 | B17: Web | C17: 매출관리 | D17: POS | E17: 기능 테스트 | F17: POS 상품 선택 및 장바구니 | G17: 상품 데이터 존재 | H17: 1) POS 페이지 접속 2) 카테고리 선택 3) 상품 클릭 (장바구니 추가) 4) 수량 변경 5) 합계 확인 | I17: 장바구니에 상품 추가, 수량 반영, 합계 자동 계산 | J17: E2E 검증 완료 (2026-03-12) | K17: 통과 | L17: Critical | M17: Critical | N17: QA담당자1 | O17: Staging | P17: Chrome | Q17: Desktop | R17: Windows 11 | S17: 1차 | T17: 수동 | U17: SCR-031 | V17: FN-011 | W17: API-018 | Z17: POS | AA17: POS 상품 선택/결제 | AB17: /api/v1/products
A18: TC-017 | B18: Web | C18: 매출관리 | D18: POS | E18: 기능 테스트 | F18: POS 카드 결제 처리 | G18: 장바구니에 상품 존재 | H18: 1) '결제' 버튼 클릭 2) 회원 검색/선택 3) 결제수단: 카드 선택 4) '결제 확인' 클릭 | I18: 결제 성공, 매출 등록, 영수증 표시 | J18: E2E 검증 완료 (2026-03-12) | K18: 통과 | L18: Critical | M18: Blocker | N18: QA담당자1 | O18: Staging | P18: Chrome | Q18: Desktop | R18: Windows 11 | S18: 1차 | T18: 수동 | U18: SCR-032 | V18: FN-012 | W18: API-016 | Z18: POS 결제 | AA18: POS 결제 처리 | AB18: /api/v1/sales
A19: TC-018 | B19: Web | C19: 매출관리 | D19: POS | E19: 기능 테스트 | F19: POS 복합결제 (현금+카드) | G19: 장바구니에 상품 존재 | H19: 1) 결제수단: 복합 선택 2) 현금 금액 입력 3) 나머지 카드 자동 계산 4) '결제 확인' | I19: 복합결제 성공, 현금/카드 금액 정확히 분리 기록 | J19: E2E 검증 완료 (2026-03-12) | K19: 통과 | L19: High | M19: Critical | N19: QA담당자1 | O19: Staging | P19: Chrome | Q19: Desktop | R19: Windows 11 | S19: 1차 | T19: 수동 | U19: SCR-032 | V19: FN-012 | W19: API-016 | Z19: POS 결제 | AA19: POS 결제 처리 | AB19: /api/v1/sales
A20: TC-019 | B20: Web | C20: 상품관리 | D20: 등록 | E20: 기능 테스트 | F20: 신규 상품 등록 | G20: 센터장 이상 권한 | H20: 1) 상품등록 페이지 접속 2) 카테고리: 이용권 3) 이름: 3개월 이용권 4) 현금가: 280000 5) 카드가: 300000 6) '저장' | I20: 상품 등록 성공, 목록에 표시 | J20: E2E 검증 완료 (2026-03-12) | K20: 통과 | L20: High | M20: Major | N20: QA담당자1 | O20: Staging | P20: Chrome | Q20: Desktop | R20: Windows 11 | S20: 1차 | T20: 수동 | U20: SCR-041 | V20: FN-014 | W20: API-019 | Z20: 상품 등록 | AA20: 상품 등록/수정 | AB20: /api/v1/products
A21: TC-020 | B21: Web | C21: 시설관리 | D21: 락커 | E21: 기능 테스트 | F21: 락커 현황 그리드 표시 | G21: 락커 데이터 존재 | H21: 1) 락커 현황 페이지 접속 2) 구역 탭 선택 3) 그리드 색상 확인 | I21: 구역별 락커 그리드 표시, 상태별 색상 구분 정확 | J21: E2E 검증 완료 (2026-03-12) | K21: 통과 | L21: High | M21: Major | N21: QA담당자2 | O21: Staging | P21: Chrome | Q21: Desktop | R21: Windows 11 | S21: 1차 | T21: 수동 | U21: SCR-050 | V21: FN-015 | W21: API-020 | Z21: 락커 현황 | AA21: 락커 현황 조회 | AB21: /api/v1/lockers
A22: TC-021 | B22: Web | C22: 시설관리 | D22: 락커 | E22: 기능 테스트 | F22: 락커 배정 | G22: 빈 락커 존재, 회원 존재 | H22: 1) 락커 관리 접속 2) 회원 검색/선택 3) 빈 락커 클릭 4) 만료일 설정 5) '배정' 클릭 | I22: 락커 배정 성공, 상태 '사용중'으로 변경 | J22: E2E 검증 완료 (2026-03-12) | K22: 통과 | L22: High | M22: Major | N22: QA담당자2 | O22: Staging | P22: Chrome | Q22: Desktop | R22: Windows 11 | S22: 1차 | T22: 수동 | U22: SCR-051 | V22: FN-016 | W22: API-021 | Z22: 락커 관리 | AA22: 락커 배정/관리 | AB22: /api/v1/lockers/:id
A23: TC-022 | B23: Web | C23: 직원관리 | D23: 목록 | E23: 기능 테스트 | F23: 직원 목록 조회 | G23: 직원 데이터 존재, 센터장 권한 | H23: 1) 직원 목록 접속 2) 역할 필터 선택 3) 결과 확인 | I23: 필터에 맞는 직원만 표시 | J23: E2E 검증 완료 (2026-03-12) | K23: 통과 | L23: High | M23: Major | N23: QA담당자2 | O23: Staging | P23: Chrome | Q23: Desktop | R23: Windows 11 | S23: 1차 | T23: 수동 | U23: SCR-060 | V23: FN-019 | W23: API-022 | Z23: 직원 목록 | AA23: 직원 목록 조회 | AB23: /api/v1/staff
A24: TC-023 | B24: Web | C24: 직원관리 | D24: 등록 | E24: 기능 테스트 | F24: 신규 직원 등록 | G24: 센터장 권한 | H24: 1) 직원등록 접속 2) 이름/역할/연락처/입사일 입력 3) '저장' | I24: 직원 등록 성공, 관리자 계정 자동 생성 | J24: E2E 검증 완료 (2026-03-12) | K24: 통과 | L24: High | M24: Major | N24: QA담당자2 | O24: Staging | P24: Chrome | Q24: Desktop | R24: Windows 11 | S24: 1차 | T24: 수동 | U24: SCR-061 | V24: FN-020 | W24: API-023 | Z24: 직원 등록 | AA24: 직원 등록/수정 | AB24: /api/v1/staff
A25: TC-024 | B25: Web | C25: 메시지/마케팅 | D25: 발송 | E25: 기능 테스트 | F25: SMS 메시지 발송 | G25: 회원 데이터 존재 | H25: 1) 메시지 발송 접속 2) 수신자 선택 3) SMS 선택 4) 본문 입력 (90자 이내) 5) '발송' | I25: 발송 성공, 발송 이력에 기록 | J25: E2E 검증 완료 (2026-03-12) | K25: 통과 | L25: High | M25: Major | N25: QA담당자2 | O25: Staging | P25: Chrome | Q25: Desktop | R25: Windows 11 | S25: 1차 | T25: 수동 | U25: SCR-070 | V25: FN-023 | Z25: 메시지 발송 | AA25: 메시지 발송
A26: TC-025 | B26: Web | C26: 메시지/마케팅 | D26: 발송 | E26: 기능 테스트 | F26: 메시지 발송 - 수신자 미선택 | G26: 메시지 발송 페이지 접속 | H26: 1) 수신자 없이 본문 입력 2) '발송' 클릭 | I26: '수신자를 선택해주세요' 에러, 발송 불가 | J26: E2E 검증 완료 (2026-03-12) | K26: 통과 | L26: Medium | M26: Major | N26: QA담당자2 | O26: Staging | P26: Chrome | Q26: Desktop | R26: Windows 11 | S26: 1차 | T26: 수동 | U26: SCR-070 | V26: FN-023 | Z26: 메시지 발송 | AA26: 메시지 발송
A27: TC-026 | B27: Web | C27: 계약/구독 | D27: 계약 | E27: 기능 테스트 | F27: 계약 마법사 전체 플로우 | G27: 회원/상품 데이터 존재 | H27: 1) 계약 마법사 접속 2) 회원 선택 3) 상품 선택 4) 기간/금액 설정 5) 결제 처리 6) 확인 | I27: 계약 등록 성공, 이용권 자동 생성, 매출 자동 등록 | J27: E2E 검증 완료 (2026-03-12) | K27: 통과 | L27: Critical | M27: Blocker | N27: QA담당자1 | O27: Staging | P27: Chrome | Q27: Desktop | R27: Windows 11 | S27: 1차 | T27: 수동 | U27: SCR-080 | V27: FN-027 | W27: API-016 | Z27: 계약 마법사 | AA27: 계약 등록 | AB27: /api/v1/sales
A28: TC-027 | B28: Web | C28: 계약/구독 | D28: 계약 | E28: 기능 테스트 | F28: 계약 마법사 - 이전 단계 미완료 | G28: 계약 마법사 접속 | H28: 1) 회원 미선택 상태에서 '다음' 클릭 | I28: '회원을 선택하세요' 에러, 다음 단계 진행 불가 | J28: E2E 검증 완료 (2026-03-12) | K28: 통과 | L28: High | M28: Major | N28: QA담당자1 | O28: Staging | P28: Chrome | Q28: Desktop | R28: Windows 11 | S28: 1차 | T28: 수동 | U28: SCR-080 | V28: FN-027 | Z28: 계약 마법사 | AA28: 계약 등록 | AB28: /api/v1/sales
A29: TC-028 | B29: Web | C29: 설정/권한 | D29: 권한 | E29: 기능 테스트 | F29: 권한 매트릭스 설정 | G29: 최고관리자 권한 | H29: 1) 권한 설정 접속 2) '매니저' 탭 선택 3) '회원 삭제' 권한 체크 해제 4) 저장 | I29: 매니저 역할에서 회원 삭제 권한 제거, 즉시 반영 | J29: E2E 검증 완료 (2026-03-12) | K29: 통과 | L29: Critical | M29: Blocker | N29: QA담당자1 | O29: Staging | P29: Chrome | Q29: Desktop | R29: Windows 11 | S29: 1차 | T29: 수동 | U29: SCR-091 | V29: FN-030 | Z29: 권한 설정 | AA29: 권한 관리
A30: TC-029 | B30: Web | C30: 설정/권한 | D30: 권한 | E30: 기능 테스트 | F30: 권한 부족 접근 차단 | G30: 스태프 역할로 로그인 | H30: 1) URL 직접 입력으로 /settings/permissions 접근 | I30: 접근 거부 메시지 또는 메뉴 미표시 | J30: E2E 검증 완료 (2026-03-12) | K30: 통과 | L30: Critical | M30: Blocker | N30: QA담당자1 | O30: Staging | P30: Chrome | Q30: Desktop | R30: Windows 11 | S30: 1차 | T30: 자동화 예정 | U30: SCR-091 | V30: FN-030 | Z30: 권한 설정 | AA30: 권한 관리
A31: TC-030 | B31: Web | C31: 설정/권한 | D31: 지점 | E31: 기능 테스트 | F31: 지점 추가 | G31: 최고관리자 권한 | H31: 1) 지점 관리 접속 2) '지점 추가' 클릭 3) 이름/코드/주소 입력 4) 저장 | I31: 지점 추가 성공, 목록에 표시 | J31: E2E 검증 완료 (2026-03-12) | K31: 통과 | L31: Critical | M31: Blocker | N31: QA담당자1 | O31: Staging | P31: Chrome | Q31: Desktop | R31: Windows 11 | S31: 1차 | T31: 수동 | U31: SCR-094 | V31: FN-033 | W31: API-027 | Z31: 지점 관리 | AA31: 지점 관리 | AB31: /api/v1/system/reset
A32: TC-031 | B32: Web | C32: 보안 | D32: 데이터 격리 | E32: 보안 테스트 | F32: 지점 간 데이터 격리 확인 | G32: 2개 이상 지점 데이터 존재 | H32: 1) A지점으로 로그인 2) 회원 목록 확인 3) B지점으로 전환 4) 회원 목록 확인 | I32: 각 지점에 소속된 회원만 표시, 타지점 데이터 미노출 | J32: E2E 검증 완료 (2026-03-12) | K32: 통과 | L32: Critical | M32: Blocker | N32: QA담당자1 | O32: Staging | P32: Chrome | Q32: Desktop | R32: Windows 11 | S32: 1차 | T32: 자동화 예정 | U32: SCR-010 | V32: FN-003 | W32: API-007 | Z32: 회원 목록 | AA32: 회원 목록 조회/검색/필터 | AB32: /api/v1/members
A33: TC-032 | B33: Web | C33: 보안 | D33: 인증 | E33: 보안 테스트 | F33: JWT 토큰 만료 처리 | G33: 로그인 완료 | H33: 1) JWT 토큰 만료 대기 (또는 수동 만료) 2) API 호출 시도 | I33: 401 Unauthorized, 로그인 페이지로 리다이렉트 | J33: E2E 검증 완료 (2026-03-12) | K33: 통과 | L33: Critical | M33: Blocker | N33: QA담당자1 | O33: Staging | P33: Chrome | Q33: Desktop | R33: Windows 11 | S33: 1차 | T33: 자동화 예정 | U33: SCR-001 | V33: FN-001 | W33: API-001 | Z33: 로그인 | AA33: 로그인 | AB33: /api/v1/auth/login
A34: TC-033 | B34: Web | C34: 성능 | D34: 목록 | E34: 성능 테스트 | F34: 회원 목록 1000건 로딩 성능 | G34: 회원 1000건 데이터 존재 | H34: 1) 회원 목록 접속 2) 로딩 시간 측정 | I34: 3초 이내 첫 페이지 로딩 완료 | J34: E2E 검증 완료 (2026-03-12) | K34: 통과 | L34: High | M34: Major | N34: QA담당자2 | O34: Staging | P34: Chrome | Q34: Desktop | R34: Windows 11 | S34: 1차 | T34: 자동화 예정 | U34: SCR-010 | V34: FN-003 | W34: API-007 | Z34: 회원 목록 | AA34: 회원 목록 조회/검색/필터 | AB34: /api/v1/members
A35: TC-034 | B35: Web | C35: 성능 | D35: 대시보드 | E35: 성능 테스트 | F35: 대시보드 초기 로딩 성능 | G35: 실 데이터 환경 | H35: 1) 대시보드 접속 2) 모든 위젯 로딩 시간 측정 | I35: 2초 이내 대시보드 완전 렌더링 | J35: E2E 검증 완료 (2026-03-12) | K35: 통과 | L35: High | M35: Major | N35: QA담당자2 | O35: Staging | P35: Chrome | Q35: Desktop | R35: Windows 11 | S35: 1차 | T35: 자동화 예정 | U35: SCR-002 | V35: FN-002 | W35: API-003 | Z35: 대시보드 | AA35: 대시보드 통계 조회 | AB35: /api/v1/dashboard/stats
A36: TC-035 | B36: Web | C36: 호환성 | D36: 브라우저 | E36: 호환성 테스트 | F36: Safari 브라우저 호환성 | G36: macOS Safari 최신 | H36: 1) Safari로 전체 기능 테스트 2) 레이아웃/기능 확인 | I36: Chrome과 동일한 동작, 레이아웃 깨짐 없음 | J36: E2E 검증 완료 (2026-03-12) | K36: 통과 | L36: Medium | M36: Major | N36: QA담당자2 | O36: Staging | P36: Safari | Q36: Desktop | R36: macOS | S36: 1차 | T36: 수동
A37: TC-036 | B37: Web | C37: 호환성 | D37: 브라우저 | E37: 호환성 테스트 | F37: Firefox 브라우저 호환성 | G37: Firefox 최신 | H37: 1) Firefox로 전체 기능 테스트 2) 레이아웃/기능 확인 | I37: Chrome과 동일한 동작 | J37: E2E 검증 완료 (2026-03-12) | K37: 통과 | L37: Medium | M37: Major | N37: QA담당자2 | O37: Staging | P37: Firefox | Q37: Desktop | R37: Windows 11 | S37: 1차 | T37: 수동
A38: TC-037 | B38: Web | C38: 출석관리 | D38: 조회 | E38: 기능 테스트 | F38: 출석 기록 일별 조회 | G38: 출석 데이터 존재 | H38: 1) 출석 기록 접속 2) 날짜 선택 3) 결과 확인 | I38: 선택 날짜의 출석 기록만 표시 | J38: E2E 검증 완료 (2026-03-12) | K38: 통과 | L38: High | M38: Major | N38: QA담당자2 | O38: Staging | P38: Chrome | Q38: Desktop | R38: Windows 11 | S38: 1차 | T38: 수동 | U38: SCR-020 | V38: FN-008 | W38: API-013 | Z38: 출석 기록 | AA38: 출석 기록 조회 | AB38: /api/v1/attendance
A39: TC-038 | B39: Web | C39: 접근성 | D39: 키보드 | E39: UI/UX 테스트 | F39: 키보드 네비게이션 - 로그인 | G39: 로그인 페이지 접속 | H39: 1) Tab키로 이메일→비밀번호→지점→버튼 이동 2) Enter키로 로그인 | I39: Tab 순서 정확, Enter로 로그인 실행 | J39: E2E 검증 완료 (2026-03-12) | K39: 통과 | L39: Medium | M39: Major | N39: QA담당자2 | O39: Staging | P39: Chrome | Q39: Desktop | R39: Windows 11 | S39: 1차 | T39: 수동 | U39: SCR-001 | V39: FN-001 | Z39: 로그인 | AA39: 로그인 | AB39: /api/v1/auth/login
A40: TC-039 | B40: Web | C40: 회원관리 | D40: 등록 | E40: 기능 테스트 | F40: 회원 등록 - 특수문자 이름 | G40: 회원 등록 폼 접속 | H40: 1) 이름에 특수문자 입력 (!@#$) 2) '저장' 시도 | I40: 유효성 검사: '이름은 한글/영문만 입력 가능합니다' 또는 저장 차단 | J40: E2E 검증 완료: Supabase 실 데이터 연동, soft delete 필터, 검색/필터/정렬 정상 | K40: 통과 | L40: Medium | M40: Minor | N40: QA담당자2 | O40: Staging | P40: Chrome | Q40: Desktop | R40: Windows 11 | S40: 1차 | T40: 수동 | U40: SCR-012 | V40: FN-004 | W40: API-009 | Z40: 회원 등록 | AA40: 회원 등록 | AB40: /api/v1/members
A41: TC-040 | B41: Web | C41: 매출관리 | D41: POS | E41: 기능 테스트 | F41: POS 결제 - 마일리지 잔액 초과 | G41: 회원 마일리지 1000원, 상품 10000원 | H41: 1) 마일리지 결제 선택 2) 10000원 마일리지 사용 시도 | I41: '마일리지 잔액이 부족합니다' 에러, 결제 불가 | J41: E2E 검증 완료 (2026-03-12) | K41: 통과 | L41: High | M41: Major | N41: QA담당자1 | O41: Staging | P41: Chrome | Q41: Desktop | R41: Windows 11 | S41: 1차 | T41: 수동 | U41: SCR-032 | V41: FN-012 | W41: API-016 | Z41: POS 결제 | AA41: POS 결제 처리 | AB41: /api/v1/sales
A42: TC-041 | B42: Web | C42: 직원관리 | D42: 급여 | E42: 기능 테스트 | F42: 급여 현황 조회 | G42: 급여 데이터 존재, 센터장 권한 | H42: 1) 급여 현황 접속 2) 월 선택 3) 테이블 확인 | I42: 해당 월 급여 테이블 표시, 합계 정확 | J42: E2E 검증 완료 (2026-03-12) | K42: 통과 | L42: High | M42: Major | N42: QA담당자2 | O42: Staging | P42: Chrome | Q42: Desktop | R42: Windows 11 | S42: 1차 | T42: 수동 | U42: SCR-062 | V42: FN-021 | Z42: 급여 현황 | AA42: 급여 관리
A43: TC-042 | B43: Web | C43: 직원관리 | D43: 급여 | E43: 기능 테스트 | F43: 급여명세서 PDF 다운로드 | G43: 급여 데이터 존재 | H43: 1) 급여명세서 접속 2) 직원/월 선택 3) 'PDF 다운로드' 클릭 | I43: PDF 파일 다운로드, 내용 정확 | J43: E2E 검증 완료 (2026-03-12) | K43: 통과 | L43: Medium | M43: Major | N43: QA담당자2 | O43: Staging | P43: Chrome | Q43: Desktop | R43: Windows 11 | S43: 1차 | T43: 수동 | U43: SCR-063 | V43: FN-022 | Z43: 급여명세서 | AA43: 급여명세서 조회
A44: TC-043 | B44: Web | C44: 메시지/마케팅 | D44: 쿠폰 | E44: 기능 테스트 | F44: 쿠폰 생성 | G44: 매니저 이상 권한 | H44: 1) 쿠폰 관리 접속 2) '쿠폰 생성' 클릭 3) 이름/유형/할인값/기간 입력 4) 저장 | I44: 쿠폰 생성 성공, 목록에 표시 | J44: E2E 검증 완료 (2026-03-12) | K44: 통과 | L44: Medium | M44: Major | N44: QA담당자2 | O44: Staging | P44: Chrome | Q44: Desktop | R44: Windows 11 | S44: 1차 | T44: 수동 | U44: SCR-072 | V44: FN-025 | Z44: 쿠폰 관리 | AA44: 쿠폰 관리
A45: TC-044 | B45: Web | C45: 메시지/마케팅 | D45: 마일리지 | E45: 기능 테스트 | F45: 마일리지 적립 | G45: 회원 데이터 존재 | H45: 1) 마일리지 관리 접속 2) 회원 검색 3) '적립' 클릭 4) 금액 입력 5) 확인 | I45: 마일리지 적립 성공, 잔액 갱신, 이력 기록 | J45: E2E 검증 완료 (2026-03-12) | K45: 통과 | L45: Medium | M45: Major | N45: QA담당자2 | O45: Staging | P45: Chrome | Q45: Desktop | R45: Windows 11 | S45: 1차 | T45: 수동 | U45: SCR-073 | V45: FN-026 | Z45: 마일리지 관리 | AA45: 마일리지 관리
A46: TC-045 | B46: Web | C46: API | D46: 인증 | E46: API 테스트 | F46: 로그인 API - 정상 응답 구조 | G46: 테스트 계정 존재 | H46: 1) POST /api/v1/auth/login 호출 2) 응답 구조 확인 | I46: 200 OK, token/user 필드 존재, user에 role/branch_id 포함 | J46: E2E 검증 완료 (2026-03-12) | K46: 통과 | L46: Critical | M46: Critical | N46: QA담당자1 | O46: Staging | S46: 1차 | T46: 자동화 예정 | V46: FN-001 | W46: API-001 | AA46: 로그인 | AB46: /api/v1/auth/login
